Workbook
Name CreditList: 'Payment Method'!$A$2:$A$4
Name PaymentList: 'Payment Method'!$A$2:$A$15
Name CategoryList: LongFormat!$A$2:$A$962
Name SubCategoryList: LongFormat!$B$2:$B$962
Name ShopList: 'Categories Wide'!$O$2:$O$50

Sheet Transaction
A1: Date | B1: Category | C1: Sub-Category | D1: Amount | E1: Pay Medthod | F1: Status | G1: Shop | H1: Note | I1: Year | J1: Month
A2: 45678 | B2: Investment | C2: US Stock | D2: 4732.46 | E2: Mobile Banking | I2: =IF(A2<>"", "_"&YEAR(A2)&"_", "") -> _2025_ | J2: =IF(A2<>"", "_"&MONTH(A2)&"_", "") -> _1_
A3: 45681 | B3: Investment | C3: US Stock | D3: 4344.1 | E3: Mobile Banking | I3: =IF(A3<>"", "_"&YEAR(A3)&"_", "") -> _2025_ | J3: =IF(A3<>"", "_"&MONTH(A3)&"_", "") -> _1_
A4: 45697 | B4: Investment | C4: US Stock | D4: 10000 | E4: Mobile Banking | I4: =IF(A4<>"", "_"&YEAR(A4)&"_", "") -> _2025_ | J4: =IF(A4<>"", "_"&MONTH(A4)&"_", "") -> _2_
A5: 45702 | B5: Investment | C5: US Stock | D5: 2200 | E5: Mobile Banking | I5: =IF(A5<>"", "_"&YEAR(A5)&"_", "") -> _2025_ | J5: =IF(A5<>"", "_"&MONTH(A5)&"_", "") -> _2_
A6: 45713 | B6: Investment | C6: US Stock | D6: 4500 | E6: Mobile Banking | I6: =IF(A6<>"", "_"&YEAR(A6)&"_", "") -> _2025_ | J6: =IF(A6<>"", "_"&MONTH(A6)&"_", "") -> _2_
A7: 45734 | B7: Investment | C7: US Stock | D7: 3000 | E7: Mobile Banking | I7: =IF(A7<>"", "_"&YEAR(A7)&"_", "") -> _2025_ | J7: =IF(A7<>"", "_"&MONTH(A7)&"_", "") -> _3_
A8: 45734 | B8: Investment | C8: TH Fund | D8: 2000 | E8: Mobile Banking | H8: SCBS&P500E, SCBNSQ(E) | I8: =IF(A8<>"", "_"&YEAR(A8)&"_", "") -> _2025_ | J8: =IF(A8<>"", "_"&MONTH(A8)&"_", "") -> _3_
A9: 45738 | B9: Transportation | C9: Fuel | D9: 650 | E9: TTB So Smart | F9: Credit Payment | G9: Bangchak | I9: =IF(A9<>"", "_"&YEAR(A9)&"_", "") -> _2025_ | J9: =IF(A9<>"", "_"&MONTH(A9)&"_", "") -> _3_
A10: 45738 | B10: Food & Drink | C10: Others | D10: 89 | E10: TTB So Smart | F10: Credit Payment | H10: ข้าวยำ | I10: =IF(A10<>"", "_"&YEAR(A10)&"_", "") -> _2025_ | J10: =IF(A10<>"", "_"&MONTH(A10)&"_", "") -> _3_
A11: 45741 | B11: Monthly Pay | C11: Salary | D11: 41044.86 | E11: Mobile Banking | I11: =IF(A11<>"", "_"&YEAR(A11)&"_", "") -> _2025_ | J11: =IF(A11<>"", "_"&MONTH(A11)&"_", "") -> _3_
A12: 45741 | B12: Investment | C12: US Stock | D12: 500 | E12: Mobile Banking | I12: =IF(A12<>"", "_"&YEAR(A12)&"_", "") -> _2025_ | J12: =IF(A12<>"", "_"&MONTH(A12)&"_", "") -> _3_
A13: 45741 | B13: Investment | C13: US Stock | D13: 5500 | E13: Mobile Banking | I13: =IF(A13<>"", "_"&YEAR(A13)&"_", "") -> _2025_ | J13: =IF(A13<>"", "_"&MONTH(A13)&"_", "") -> _3_
A14: 45743 | B14: Food & Drink | C14: Main meals | D14: 200 | E14: TTB So Smart | F14: Credit Payment | G14: Mc Donald | I14: =IF(A14<>"", "_"&YEAR(A14)&"_", "") -> _2025_ | J14: =IF(A14<>"", "_"&MONTH(A14)&"_", "") -> _3_
A15: 45743 | B15: Items | C15: Household Items | D15: 146 | E15: TTB So Smart | F15: Credit Payment | H15: หลอดไฟ | I15: =IF(A15<>"", "_"&YEAR(A15)&"_", "") -> _2025_ | J15: =IF(A15<>"", "_"&MONTH(A15)&"_", "") -> _3_
A16: 45744 | B16: Food & Drink | C16: Main meals | D16: 159 | E16: TTB So Smart | F16: Credit Payment | G16: KFC | I16: =IF(A16<>"", "_"&YEAR(A16)&"_", "") -> _2025_ | J16: =IF(A16<>"", "_"&MONTH(A16)&"_", "") -> _3_
A17: 45745 | B17: Food & Drink | C17: Snacks | D17: 134 | E17: TTB So Smart | F17: Credit Payment | I17: =IF(A17<>"", "_"&YEAR(A17)&"_", "") -> _2025_ | J17: =IF(A17<>"", "_"&MONTH(A17)&"_", "") -> _3_
A18: 45746 | B18: Food & Drink | C18: Drinks | D18: 50 | E18: TTB So Smart | F18: Credit Payment | G18: Amazon | H18: ชาเขียว | I18: =IF(A18<>"", "_"&YEAR(A18)&"_", "") -> _2025_ | J18: =IF(A18<>"", "_"&MONTH(A18)&"_", "") -> _3_
A19: 45752 | B19: Food & Drink | C19: Groceries | D19: 153.25 | E19: TTB So Smart | F19: Credit Payment | G19: Lotus | H19: ผลไม้ ขนม | I19: =IF(A19<>"", "_"&YEAR(A19)&"_", "") -> _2025_ | J19: =IF(A19<>"", "_"&MONTH(A19)&"_", "") -> _4_
A20: 45753 | B20: Food & Drink | C20: Groceries | D20: 347.25 | E20: TTB So Smart | F20: Credit Payment | G20: Lotus | H20: เนื้อ ผัก | I20: =IF(A20<>"", "_"&YEAR(A20)&"_", "") -> _2025_ | J20: =IF(A20<>"", "_"&MONTH(A20)&"_", "") -> _4_
A21: 45753 | B21: Hobby | C21: Tree | D21: 150 | E21: Mobile Banking | H21: ต้นไม้หน้าคอม | I21: =IF(A21<>"", "_"&YEAR(A21)&"_", "") -> _2025_ | J21: =IF(A21<>"", "_"&MONTH(A21)&"_", "") -> _4_
A22: 45754 | B22: Service | C22: Subscription | D22: 19 | E22: Mobile Banking | H22: Subscribe K.Earthh Evans | I22: =IF(A22<>"", "_"&YEAR(A22)&"_", "") -> _2025_ | J22: =IF(A22<>"", "_"&MONTH(A22)&"_", "") -> _4_
A23: 45754 | B23: Food & Drink | C23: Groceries | D23: 110.75 | E23: TTB So Smart | F23: Credit Payment | G23: Lotus | H23: ผลไม้ | I23: =IF(A23<>"", "_"&YEAR(A23)&"_", "") -> _2025_ | J23: =IF(A23<>"", "_"&MONTH(A23)&"_", "") -> _4_
A24: 45755 | B24: Service | C24: Haircut | D24: 120 | E24: Mobile Banking | I24: =IF(A24<>"", "_"&YEAR(A24)&"_", "") -> _2025_ | J24: =IF(A24<>"", "_"&MONTH(A24)&"_", "") -> _4_
A25: 45755 | B25: Food & Drink | C25: Snacks | D25: 124.5 | E25: Mobile Banking | G25: 7-Eleven | H25: ขนม | I25: =IF(A25<>"", "_"&YEAR(A25)&"_", "") -> _2025_ | J25: =IF(A25<>"", "_"&MONTH(A25)&"_", "") -> _4_
A26: 45755 | B26: Food & Drink | C26: Snacks | D26: 40 | E26: Mobile Banking | H26: ลูกชิ้น | I26: =IF(A26<>"", "_"&YEAR(A26)&"_", "") -> _2025_ | J26: =IF(A26<>"", "_"&MONTH(A26)&"_", "") -> _4_
A27: 45757 | B27: Food & Drink | C27: Others | D27: 55 | E27: Mobile Banking | G27: 7-Eleven | I27: =IF(A27<>"", "_"&YEAR(A27)&"_", "") -> _2025_ | J27: =IF(A27<>"", "_"&MONTH(A27)&"_", "") -> _4_
A28: 45757 | B28: Food & Drink | C28: Others | D28: 127 | E28: Mobile Banking | G28: 7-Eleven | H28: ของกินกลางวัน | I28: =IF(A28<>"", "_"&YEAR(A28)&"_", "") -> _2025_ | J28: =IF(A28<>"", "_"&MONTH(A28)&"_", "") -> _4_
A29: 45758 | B29: Food & Drink | C29: Others | D29: 152 | E29: Mobile Banking | G29: 7-Eleven | I29: =IF(A29<>"", "_"&YEAR(A29)&"_", "") -> _2025_ | J29: =IF(A29<>"", "_"&MONTH(A29)&"_", "") -> _4_
A30: 45758 | B30: Transportation | C30: Fuel | D30: 1100.1 | E30: KTC Bangchak | F30: Credit Payment | G30: Bangchak | H30: น้ำมันกลับกาฬสินธุ์ | I30: =IF(A30<>"", "_"&YEAR(A30)&"_", "") -> _2025_ | J30: =IF(A30<>"", "_"&MONTH(A30)&"_", "") -> _4_
A31: 45759 | B31: Food & Drink | C31: Main meals | D31: 27 | E31: Mobile Banking | G31: 7-Eleven | H31: มาม่า | I31: =IF(A31<>"", "_"&YEAR(A31)&"_", "") -> _2025_ | J31: =IF(A31<>"", "_"&MONTH(A31)&"_", "") -> _4_
A32: 45759 | B32: Food & Drink | C32: Groceries | D32: 55 | E32: Mobile Banking | H32: ผลไม้ | I32: =IF(A32<>"", "_"&YEAR(A32)&"_", "") -> _2025_ | J32: =IF(A32<>"", "_"&MONTH(A32)&"_", "") -> _4_
A33: 45759 | B33: Food & Drink | C33: Snacks | D33: 160 | E33: Mobile Banking | H33: หมูกระจก | I33: =IF(A33<>"", "_"&YEAR(A33)&"_", "") -> _2025_ | J33: =IF(A33<>"", "_"&MONTH(A33)&"_", "") -> _4_
A34: 45759 | B34: Food & Drink | C34: Drinks | D34: 50 | E34: UOB One | F34: Credit Payment | G34: Amazon | H34: ชาเขียว | I34: =IF(A34<>"", "_"&YEAR(A34)&"_", "") -> _2025_ | J34: =IF(A34<>"", "_"&MONTH(A34)&"_", "") -> _4_
A35: 45759 | B35: Food & Drink | C35: Snacks | D35: 70 | E35: UOB One | F35: Credit Payment | I35: =IF(A35<>"", "_"&YEAR(A35)&"_", "") -> _2025_ | J35: =IF(A35<>"", "_"&MONTH(A35)&"_", "") -> _4_
A36: 45759 | B36: Others | C36: Family | D36: =1150.5-800 -> 350.5 | E36: UOB One | F36: Credit Payment | H36: ซื้อของฝากตายายย่า -1,150 | I36: =IF(A36<>"", "_"&YEAR(A36)&"_", "") -> _2025_ | J36: =IF(A36<>"", "_"&MONTH(A36)&"_", "") -> _4_
A37: 45759 | B37: Reimbursement | C37: Reimbursement | D37: =600+275.25 -> 875.25 | E37: UOB One | F37: Credit Payment | H37: แม่ + หมวยช่วยออก | I37: =IF(A37<>"", "_"&YEAR(A37)&"_", "") -> _2025_ | J37: =IF(A37<>"", "_"&MONTH(A37)&"_", "") -> _4_
A38: 45760 | B38: Food & Drink | C38: Main meals | D38: 236 | E38: UOB One | F38: Credit Payment | G38: KFC | I38: =IF(A38<>"", "_"&YEAR(A38)&"_", "") -> _2025_ | J38: =IF(A38<>"", "_"&MONTH(A38)&"_", "") -> _4_
A39: 45760 | B39: Food & Drink | C39: Snacks | D39: 138 | E39: UOB One | F39: Credit Payment | G39: Lotus | H39: Lotus Deli | I39: =IF(A39<>"", "_"&YEAR(A39)&"_", "") -> _2025_ | J39: =IF(A39<>"", "_"&MONTH(A39)&"_", "") -> _4_
A40: 45760 | B40: Food & Drink | C40: Main meals | D40: 139 | E40: UOB One | F40: Credit Payment | G40: KFC | I40: =IF(A40<>"", "_"&YEAR(A40)&"_", "") -> _2025_ | J40: =IF(A40<>"", "_"&MONTH(A40)&"_", "") -> _4_
A41: 45760 | B41: Food & Drink | C41: Drinks | D41: 35 | E41: Mobile Banking | H41: น้ำมะพร้าว | I41: =IF(A41<>"", "_"&YEAR(A41)&"_", "") -> _2025_ | J41: =IF(A41<>"", "_"&MONTH(A41)&"_", "") -> _4_
A42: 45760 | B42: Residence | C42: Electricity Bill-A | D42: 3197.22 | E42: Mobile Banking | H42: ไฟบ้าน | I42: =IF(A42<>"", "_"&YEAR(A42)&"_", "") -> _2025_ | J42: =IF(A42<>"", "_"&MONTH(A42)&"_", "") -> _4_
A43: 45761 | B43: Food & Drink | C43: Alcohol | D43: 195 | E43: Mobile Banking | H43: เบียร์สิง | I43: =IF(A43<>"", "_"&YEAR(A43)&"_", "") -> _2025_ | J43: =IF(A43<>"", "_"&MONTH(A43)&"_", "") -> _4_
A44: 45761 | B44: Others | C44: Family | D44: 1023.13 | E44: TTB So Smart | F44: Credit Payment | H44: เลี้ยงข้าวตายายย่า -1770 | I44: =IF(A44<>"", "_"&YEAR(A44)&"_", "") -> _2025_ | J44: =IF(A44<>"", "_"&MONTH(A44)&"_", "") -> _4_
A45: 45761 | B45: Reimbursement | C45: Reimbursement | D45: =822.12-75.25 -> 746.87 | E45: TTB So Smart | F45: Credit Payment | H45: หมวยช่วยออก | I45: =IF(A45<>"", "_"&YEAR(A45)&"_", "") -> _2025_ | J45: =IF(A45<>"", "_"&MONTH(A45)&"_", "") -> _4_
A46: 45761 | B46: Food & Drink | C46: Alcohol | D46: 183 | E46: UOB One | F46: Credit Payment | H46: เบียร์ | I46: =IF(A46<>"", "_"&YEAR(A46)&"_", "") -> _2025_ | J46: =IF(A46<>"", "_"&MONTH(A46)&"_", "") -> _4_
A47: 45762 | B47: Others | C47: Family | D47: 1000 | E47: Mobile Banking | H47: ให้เงินตายายย่า | I47: =IF(A47<>"", "_"&YEAR(A47)&"_", "") -> _2025_ | J47: =IF(A47<>"", "_"&MONTH(A47)&"_", "") -> _4_
A48: 45762 | B48: Food & Drink | C48: Snacks | D48: 165 | E48: Mobile Banking | G48: 7-Eleven | H48: กาแฟ ขนม | I48: =IF(A48<>"", "_"&YEAR(A48)&"_", "") -> _2025_ | J48: =IF(A48<>"", "_"&MONTH(A48)&"_", "") -> _4_
A49: 45762 | B49: Others | C49: Family | D49: 834.25 | E49: UOB One | F49: Credit Payment | H49: ซื้อของให้ตายายย่า | I49: =IF(A49<>"", "_"&YEAR(A49)&"_", "") -> _2025_ | J49: =IF(A49<>"", "_"&MONTH(A49)&"_", "") -> _4_
A50: 45762 | B50: Transportation | C50: Fuel | D50: 620 | E50: TTB So Smart | F50: Credit Payment | G50: Bangchak | H50: กลับ กทม | I50: =IF(A50<>"", "_"&YEAR(A50)&"_", "") -> _2025_ | J50: =IF(A50<>"", "_"&MONTH(A50)&"_", "") -> _4_
A51: 45763 | B51: Food & Drink | C51: Snacks | D51: 22 | E51: Mobile Banking | G51: 7-Eleven | H51: ถั่ววาซา | I51: =IF(A51<>"", "_"&YEAR(A51)&"_", "") -> _2025_ | J51: =IF(A51<>"", "_"&MONTH(A51)&"_", "") -> _4_
A52: 45763 | B52: Transportation | C52: Toll Fee | D52: 100 | E52: Mobile Banking | I52: =IF(A52<>"", "_"&YEAR(A52)&"_", "") -> _2025_ | J52: =IF(A52<>"", "_"&MONTH(A52)&"_", "") -> _4_
A53: 45763 | B53: Transportation | C53: Fuel | D53: 650 | E53: TTB So Smart | F53: Credit Payment | G53: Bangchak | H53: กลับ กทม | I53: =IF(A53<>"", "_"&YEAR(A53)&"_", "") -> _2025_ | J53: =IF(A53<>"", "_"&MONTH(A53)&"_", "") -> _4_
A54: 45763 | B54: Food & Drink | C54: Main meals | D54: 209 | E54: UOB One | F54: Credit Payment | G54: Subway | I54: =IF(A54<>"", "_"&YEAR(A54)&"_", "") -> _2025_ | J54: =IF(A54<>"", "_"&MONTH(A54)&"_", "") -> _4_
A55: 45763 | B55: Transportation | C55: Fuel | D55: 843.6 | E55: TTB So Smart | F55: Credit Payment | G55: Caltex | I55: =IF(A55<>"", "_"&YEAR(A55)&"_", "") -> _2025_ | J55: =IF(A55<>"", "_"&MONTH(A55)&"_", "") -> _4_
A56: 45763 | B56: Food & Drink | C56: Snacks | D56: 166 | E56: UOB One | F56: Credit Payment | G56: Lotus | H56: เป๊ปซี่ | I56: =IF(A56<>"", "_"&YEAR(A56)&"_", "") -> _2025_ | J56: =IF(A56<>"", "_"&MONTH(A56)&"_", "") -> _4_
A57: 45764 | B57: Hobby | C57: Tree | D57: 60 | E57: Mobile Banking | H57: ดอกไม้ไหว้พระ | I57: =IF(A57<>"", "_"&YEAR(A57)&"_", "") -> _2025_ | J57: =IF(A57<>"", "_"&MONTH(A57)&"_", "") -> _4_
A58: 45764 | B58: Food & Drink | C58: Snacks | D58: 25 | E58: Mobile Banking | G58: 7-Eleven | H58: ข้าวโพดอบชีส | I58: =IF(A58<>"", "_"&YEAR(A58)&"_", "") -> _2025_ | J58: =IF(A58<>"", "_"&MONTH(A58)&"_", "") -> _4_
A59: 45764 | B59: Food & Drink | C59: Groceries | D59: 940.5 | E59: UOB One | F59: Credit Payment | G59: Lotus | H59: ของกิน | I59: =IF(A59<>"", "_"&YEAR(A59)&"_", "") -> _2025_ | J59: =IF(A59<>"", "_"&MONTH(A59)&"_", "") -> _4_
A60: 45766 | B60: Food & Drink | C60: Main meals | D60: 75 | E60: Mobile Banking | G60: Noodle | I60: =IF(A60<>"", "_"&YEAR(A60)&"_", "") -> _2025_ | J60: =IF(A60<>"", "_"&MONTH(A60)&"_", "") -> _4_
A61: 45767 | B61: Residence | C61: Home Renovation | D61: 561 | E61: TTB So Smart | F61: Credit Payment | G61: Thai Watsadu | H61: ก๊อกน้ำ ตลับวัดความยาว | I61: =IF(A61<>"", "_"&YEAR(A61)&"_", "") -> _2025_ | J61: =IF(A61<>"", "_"&MONTH(A61)&"_", "") -> _4_
A62: 45768 | B62: Residence | C62: Water Bill | D62: 165.58 | E62: Mobile Banking | I62: =IF(A62<>"", "_"&YEAR(A62)&"_", "") -> _2025_ | J62: =IF(A62<>"", "_"&MONTH(A62)&"_", "") -> _4_
A63: 45768 | B63: Food & Drink | C63: Main meals | D63: 159 | E63: UOB One | F63: Credit Payment | G63: KFC | H63: ไก่ | I63: =IF(A63<>"", "_"&YEAR(A63)&"_", "") -> _2025_ | J63: =IF(A63<>"", "_"&MONTH(A63)&"_", "") -> _4_
A64: 45769 | B64: Food & Drink | C64: Main meals | D64: 174 | E64: UOB One | F64: Credit Payment | G64: Mc Donald | H64: เบอร์เกอร์ | I64: =IF(A64<>"", "_"&YEAR(A64)&"_", "") -> _2025_ | J64: =IF(A64<>"", "_"&MONTH(A64)&"_", "") -> _4_
A65: 45770 | B65: Food & Drink | C65: Main meals | D65: 95 | E65: Mobile Banking | G65: 7-Eleven | H65: ข้าวเที่ยง | I65: =IF(A65<>"", "_"&YEAR(A65)&"_", "") -> _2025_ | J65: =IF(A65<>"", "_"&MONTH(A65)&"_", "") -> _4_
A66: 45770 | B66: Food & Drink | C66: Groceries | D66: 617.25 | E66: UOB One | F66: Credit Payment | G66: Lotus | H66: ซี่โครงหมู, เนื้อวัว, ผัก, ผลไม้ | I66: =IF(A66<>"", "_"&YEAR(A66)&"_", "") -> _2025_ | J66: =IF(A66<>"", "_"&MONTH(A66)&"_", "") -> _4_
A67: 45770 | B67: Monthly Pay | C67: Cashback | D67: =57.05+36 -> 93.05 | E67: Mobile Banking | H67: เก็บเข้าเงินฉุกเฉิน | I67: =IF(A67<>"", "_"&YEAR(A67)&"_", "") -> _2025_ | J67: =IF(A67<>"", "_"&MONTH(A67)&"_", "") -> _4_
A68: 45771 | B68: Service | C68: Subscription | D68: 10 | E68: Mobile Banking | H68: NF | I68: =IF(A68<>"", "_"&YEAR(A68)&"_", "") -> _2025_ | J68: =IF(A68<>"", "_"&MONTH(A68)&"_", "") -> _4_
A69: 45772 | B69: Service | C69: Home Internet | D69: 650 | E69: Mobile Banking | H69: จ่ายล่วงหน้า | I69: =IF(A69<>"", "_"&YEAR(A69)&"_", "") -> _2025_ | J69: =IF(A69<>"", "_"&MONTH(A69)&"_", "") -> _4_
A70: 45772 | B70: Service | C70: Mobile Internet | D70: 450 | E70: Mobile Banking | H70: จ่ายล่วงหน้า | I70: =IF(A70<>"", "_"&YEAR(A70)&"_", "") -> _2025_ | J70: =IF(A70<>"", "_"&MONTH(A70)&"_", "") -> _4_
A71: 45772 | B71: Investment | C71: US Stock | D71: 5000 | E71: Mobile Banking | H71: เติม Port US | I71: =IF(A71<>"", "_"&YEAR(A71)&"_", "") -> _2025_ | J71: =IF(A71<>"", "_"&MONTH(A71)&"_", "") -> _4_
A72: 45772 | B72: Investment | C72: TH Fund | D72: 2000 | E72: Mobile Banking | H72: เติม Port กองทุน เงินรอใน Kbank | I72: =IF(A72<>"", "_"&YEAR(A72)&"_", "") -> _2025_ | J72: =IF(A72<>"", "_"&MONTH(A72)&"_", "") -> _4_
A73: 45772 | B73: Investment | C73: Contigency | D73: 800 | E73: Mobile Banking | H73: เก็บเงินฉุกเฉิน | I73: =IF(A73<>"", "_"&YEAR(A73)&"_", "") -> _2025_ | J73: =IF(A73<>"", "_"&MONTH(A73)&"_", "") -> _4_
A74: 45772 | B74: Others | C74: Debt | D74: 8251 | E74: Mobile Banking | H74: Nissan Almera 2022 | I74: =IF(A74<>"", "_"&YEAR(A74)&"_", "") -> _2025_ | J74: =IF(A74<>"", "_"&MONTH(A74)&"_", "") -> _4_
A75: 45772 | B75: Others | C75: Fine | D75: 1000 | E75: Mobile Banking | H75: ค่าปรับความเร็ว 2 ใบ | I75: =IF(A75<>"", "_"&YEAR(A75)&"_", "") -> _2025_ | J75: =IF(A75<>"", "_"&MONTH(A75)&"_", "") -> _4_
A76: 45772 | B76: Others | C76: Debt | D76: 1643.86 | E76: Mobile Banking | H76: กรอ. kbank | I76: =IF(A76<>"", "_"&YEAR(A76)&"_", "") -> _2025_ | J76: =IF(A76<>"", "_"&MONTH(A76)&"_", "") -> _4_
A77: 45772 | B77: Food & Drink | C77: Others | D77: 60 | E77: Mobile Banking | H77: ข้าวหมูกรอบ | I77: =IF(A77<>"", "_"&YEAR(A77)&"_", "") -> _2025_ | J77: =IF(A77<>"", "_"&MONTH(A77)&"_", "") -> _4_
A78: 45772 | B78: Residence | C78: Home Renovation | D78: 639 | E78: TTB So Smart | F78: Credit Payment | G78: Thai Watsadu | H78: ชุดน้ำทิ้ง, สายส่งน้ำ, ไฟวง | I78: =IF(A78<>"", "_"&YEAR(A78)&"_", "") -> _2025_ | J78: =IF(A78<>"", "_"&MONTH(A78)&"_", "") -> _4_
A79: 45773 | B79: Monthly Pay | C79: Salary | D79: 41044.86 | E79: Mobile Banking | I79: =IF(A79<>"", "_"&YEAR(A79)&"_", "") -> _2025_ | J79: =IF(A79<>"", "_"&MONTH(A79)&"_", "") -> _4_
A80: 45773 | B80: Food & Drink | C80: Main meals | D80: 114 | E80: Mobile Banking | G80: 7-Eleven | H80: ข้าวเที่ยง | I80: =IF(A80<>"", "_"&YEAR(A80)&"_", "") -> _2025_ | J80: =IF(A80<>"", "_"&MONTH(A80)&"_", "") -> _4_
A81: 45773 | B81: Residence | C81: Home Renovation | D81: 754 | E81: TTB So Smart | F81: Credit Payment | G81: Thai Watsadu | H81: ก๊อกน้ำซิงค์ล้างจาน, สายเดินน้ำ 2 เส้น | I81: =IF(A81<>"", "_"&YEAR(A81)&"_", "") -> _2025_ | J81: =IF(A81<>"", "_"&MONTH(A81)&"_", "") -> _4_
A82: 45774 | B82: Food & Drink | C82: Drinks | D82: 45 | E82: UOB One | F82: Credit Payment | G82: Amazon | H82: ชาเขียว | I82: =IF(A82<>"", "_"&YEAR(A82)&"_", "") -> _2025_ | J82: =IF(A82<>"", "_"&MONTH(A82)&"_", "") -> _4_
A83: 45774 | B83: Others | C83: Family | D83: =2540-1120 -> 1420 | E83: Mobile Banking | H83: เลี้ยงหมูกะทะบ้านอาด้วง -2540 | I83: =IF(A83<>"", "_"&YEAR(A83)&"_", "") -> _2025_ | J83: =IF(A83<>"", "_"&MONTH(A83)&"_", "") -> _4_
A84: 45774 | B84: Reimbursement | C84: Reimbursement | D84: 1120 | E84: Mobile Banking | H84: หมวยช่วยออก | I84: =IF(A84<>"", "_"&YEAR(A84)&"_", "") -> _2025_ | J84: =IF(A84<>"", "_"&MONTH(A84)&"_", "") -> _4_
A85: 45774 | B85: Food & Drink | C85: Alcohol | D85: 99 | E85: Mobile Banking | H85: ซื้อใน 7-11 เอามาคิดแยกจากของกิน | I85: =IF(A85<>"", "_"&YEAR(A85)&"_", "") -> _2025_ | J85: =IF(A85<>"", "_"&MONTH(A85)&"_", "") -> _4_
A86: 45774 | B86: Food & Drink | C86: Others | D86: =283-99 -> 184 | E86: Mobile Banking | G86: 7-Eleven | H86: ซื้อของกินให้ไอข้าว | I86: =IF(A86<>"", "_"&YEAR(A86)&"_", "") -> _2025_ | J86: =IF(A86<>"", "_"&MONTH(A86)&"_", "") -> _4_
A87: 45775 | B87: Monthly Pay | C87: Interest | D87: 217.6 | E87: Mobile Banking | H87: ดอกเบี้ย Kept | I87: =IF(A87<>"", "_"&YEAR(A87)&"_", "") -> _2025_ | J87: =IF(A87<>"", "_"&MONTH(A87)&"_", "") -> _4_
A88: 45775 | B88: Hobby | C88: Camping | D88: =253+156 -> 409 | E88: UOB One | F88: Credit Payment | H88: เบาะลมลองนอนในรถ | I88: =IF(A88<>"", "_"&YEAR(A88)&"_", "") -> _2025_ | J88: =IF(A88<>"", "_"&MONTH(A88)&"_", "") -> _4_
A89: 45775 | B89: Items | C89: Personal Items | D89: 112 | E89: UOB One | F89: Credit Payment | H89: การ์ดหอม Little Trees | I89: =IF(A89<>"", "_"&YEAR(A89)&"_", "") -> _2025_ | J89: =IF(A89<>"", "_"&MONTH(A89)&"_", "") -> _4_
A90: 45775 | B90: Residence | C90: Home Renovation | D90: 84 | E90: UOB One | F90: Credit Payment | H90: จุกปิดซิงค์ | I90: =IF(A90<>"", "_"&YEAR(A90)&"_", "") -> _2025_ | J90: =IF(A90<>"", "_"&MONTH(A90)&"_", "") -> _4_
A91: 45775 | B91: Food & Drink | C91: Drinks | D91: 40 | E91: UOB One | F91: Credit Payment | G91: Amazon | H91: ชาเขียว | I91: =IF(A91<>"", "_"&YEAR(A91)&"_", "") -> _2025_ | J91: =IF(A91<>"", "_"&MONTH(A91)&"_", "") -> _4_
A92: 45775 | B92: Food & Drink | C92: Main meals | D92: 60 | E92: Mobile Banking | G92: Noodle | H92: เต๋ว | I92: =IF(A92<>"", "_"&YEAR(A92)&"_", "") -> _2025_ | J92: =IF(A92<>"", "_"&MONTH(A92)&"_", "") -> _4_
A93: 45776 | B93: Food & Drink | C93: Main meals | D93: 128 | E93: UOB One | F93: Credit Payment | G93: KFC | I93: =IF(A93<>"", "_"&YEAR(A93)&"_", "") -> _2025_ | J93: =IF(A93<>"", "_"&MONTH(A93)&"_", "") -> _4_
A94: 45777 | B94: Food & Drink | C94: Snacks | D94: 140 | E94: Mobile Banking | G94: 7-Eleven | H94: ข้าวไรเบอร์รี่ | I94: =IF(A94<>"", "_"&YEAR(A94)&"_", "") -> _2025_ | J94: =IF(A94<>"", "_"&MONTH(A94)&"_", "") -> _4_
A95: 45778 | B95: Investment | C95: US Stock | D95: 303.91 | E95: Mobile Banking | I95: =IF(A95<>"", "_"&YEAR(A95)&"_", "") -> _2025_ | J95: =IF(A95<>"", "_"&MONTH(A95)&"_", "") -> _5_
A96: 45778 | B96: Food & Drink | C96: Main meals | D96: 135 | E96: Mobile Banking | H96: เล้ง ปตท. ใกล้บ้าน | I96: =IF(A96<>"", "_"&YEAR(A96)&"_", "") -> _2025_ | J96: =IF(A96<>"", "_"&MONTH(A96)&"_", "") -> _5_
A97: 45778 | B97: Food & Drink | C97: Drinks | D97: 50 | E97: UOB One | F97: Credit Payment | G97: Amazon | H97: ช็อคโกแลต | I97: =IF(A97<>"", "_"&YEAR(A97)&"_", "") -> _2025_ | J97: =IF(A97<>"", "_"&MONTH(A97)&"_", "") -> _5_
A98: 45778 | B98: Food & Drink | C98: Groceries | D98: =532.75-179-99 -> 254.75 | E98: UOB One | F98: Credit Payment | G98: Lotus | I98: =IF(A98<>"", "_"&YEAR(A98)&"_", "") -> _2025_ | J98: =IF(A98<>"", "_"&MONTH(A98)&"_", "") -> _5_
A99: 45778 | B99: Items | C99: Household Items | D99: 179 | E99: UOB One | F99: Credit Payment | G99: Lotus | H99: น้ำยาปรับผ้านุ่ม | I99: =IF(A99<>"", "_"&YEAR(A99)&"_", "") -> _2025_ | J99: =IF(A99<>"", "_"&MONTH(A99)&"_", "") -> _5_
A100: 45778 | B100: Items | C100: Outfit | D100: 99 | E100: UOB One | F100: Credit Payment | G100: Lotus | H100: boxser | I100: =IF(A100<>"", "_"&YEAR(A100)&"_", "") -> _2025_ | J100: =IF(A100<>"", "_"&MONTH(A100)&"_", "") -> _5_
...

Sheet Monthly Dashboard
A1: Year | B1: Month | C1: Category | F1: Sub-Category breakdown by Month
A2: _2025_ | B2: _10_ | C2: All | F2: =SUM('Background-Data'!H2:H240) -> 36303.43
F23: Remaining Balance | G23: =K25-E25 -> -36303.43
A25: EXPENSES | E25: =SUM(D44:D240) -> 36303.43 | H25: INCOME | K25: =SUM(J46:J240) -> 0
A45: =IFERROR(__xludf.DUMMYFUNCTION("QUERY(Transaction!A1:J240, ""SELECT A, B, C, D, G, H WHERE B != 'Monthly Pay' AND B != 'Investment' AND B != 'Reimbursement' AND I = '""&'Monthly Dashboard'!A2&""' AND J = '""&'Monthly Dashboard'!B2&""' ORDER BY A DESC"", 1)"),"Date") -> Date | B45: =IFERROR(__xludf.DUMMYFUNCTION("""COMPUTED_VALUE"""),"Category") -> Category | C45: =IFERROR(__xludf.DUMMYFUNCTION("""COMPUTED_VALUE"""),"Sub-Category") -> Sub-Category | D45: =IFERROR(__xludf.DUMMYFUNCTION("""COMPUTED_VALUE"""),"Amount") -> Amount | E45: =IFERROR(__xludf.DUMMYFUNCTION("""COMPUTED_VALUE"""),"Shop") -> Shop | F45: =IFERROR(__xludf.DUMMYFUNCTION("""COMPUTED_VALUE"""),"Note") -> Note | H45: =IFERROR(__xludf.DUMMYFUNCTION("QUERY(Transaction!A1:J240, ""SELECT A, C, D, H WHERE B = 'Monthly Pay' AND I = '""&'Monthly Dashboard'!A2&""' AND J = '""&'Monthly Dashboard'!B2&""' ORDER BY A DESC"", 1)"),"Date") -> Date | I45: =IFERROR(__xludf.DUMMYFUNCTION("""COMPUTED_VALUE"""),"Sub-Category") -> Sub-Category | J45: =IFERROR(__xludf.DUMMYFUNCTION("""COMPUTED_VALUE"""),"Amount") -> Amount | K45: =IFERROR(__xludf.DUMMYFUNCTION("""COMPUTED_VALUE"""),"Note") -> Note
A46: =IFERROR(__xludf.DUMMYFUNCTION("""COMPUTED_VALUE"""),45960.0) -> 45960 | B46: =IFERROR(__xludf.DUMMYFUNCTION("""COMPUTED_VALUE"""),"Food & Drink") -> Food & Drink | C46: =IFERROR(__xludf.DUMMYFUNCTION("""COMPUTED_VALUE"""),"Main meals") -> Main meals | D46: =IFERROR(__xludf.DUMMYFUNCTION("""COMPUTED_VALUE"""),372.0) -> 372 | E46: =IFERROR(__xludf.DUMMYFUNCTION("""COMPUTED_VALUE"""),"Pizza") -> Pizza
A47: =IFERROR(__xludf.DUMMYFUNCTION("""COMPUTED_VALUE"""),45959.0) -> 45959 | B47: =IFERROR(__xludf.DUMMYFUNCTION("""COMPUTED_VALUE"""),"Hobby") -> Hobby | C47: =IFERROR(__xludf.DUMMYFUNCTION("""COMPUTED_VALUE"""),"Education") -> Education | D47: =IFERROR(__xludf.DUMMYFUNCTION("""COMPUTED_VALUE"""),719.0) -> 719
A48: =IFERROR(__xludf.DUMMYFUNCTION("""COMPUTED_VALUE"""),45959.0) -> 45959 | B48: =IFERROR(__xludf.DUMMYFUNCTION("""COMPUTED_VALUE"""),"Food & Drink") -> Food & Drink | C48: =IFERROR(__xludf.DUMMYFUNCTION("""COMPUTED_VALUE"""),"Main meals") -> Main meals | D48: =IFERROR(__xludf.DUMMYFUNCTION("""COMPUTED_VALUE"""),50.0) -> 50 | E48: =IFERROR(__xludf.DUMMYFUNCTION("""COMPUTED_VALUE"""),"Hainanese chicken rice") -> Hainanese chicken rice
A49: =IFERROR(__xludf.DUMMYFUNCTION("""COMPUTED_VALUE"""),45959.0) -> 45959 | B49: =IFERROR(__xludf.DUMMYFUNCTION("""COMPUTED_VALUE"""),"Food & Drink") -> Food & Drink | C49: =IFERROR(__xludf.DUMMYFUNCTION("""COMPUTED_VALUE"""),"Snacks") -> Snacks | D49: =IFERROR(__xludf.DUMMYFUNCTION("""COMPUTED_VALUE"""),36.0) -> 36 | E49: =IFERROR(__xludf.DUMMYFUNCTION("""COMPUTED_VALUE"""),"CJ") -> CJ
A50: =IFERROR(__xludf.DUMMYFUNCTION("""COMPUTED_VALUE"""),45957.0) -> 45957 | B50: =IFERROR(__xludf.DUMMYFUNCTION("""COMPUTED_VALUE"""),"Transportation") -> Transportation | C50: =IFERROR(__xludf.DUMMYFUNCTION("""COMPUTED_VALUE"""),"Maintenance") -> Maintenance | D50: =IFERROR(__xludf.DUMMYFUNCTION("""COMPUTED_VALUE"""),1883.2) -> 1883.2 | F50: =IFERROR(__xludf.DUMMYFUNCTION("""COMPUTED_VALUE"""),"เข้าเช็คระยะ 63,000 km") -> เข้าเช็คระยะ 63,000 km
A51: =IFERROR(__xludf.DUMMYFUNCTION("""COMPUTED_VALUE"""),45957.0) -> 45957 | B51: =IFERROR(__xludf.DUMMYFUNCTION("""COMPUTED_VALUE"""),"Transportation") -> Transportation | C51: =IFERROR(__xludf.DUMMYFUNCTION("""COMPUTED_VALUE"""),"Fee") -> Fee | D51: =IFERROR(__xludf.DUMMYFUNCTION("""COMPUTED_VALUE"""),50.0) -> 50 | F51: =IFERROR(__xludf.DUMMYFUNCTION("""COMPUTED_VALUE"""),"ค่าจอดรถสนามบินส่งมิ้น") -> ค่าจอดรถสนามบินส่งมิ้น
A52: =IFERROR(__xludf.DUMMYFUNCTION("""COMPUTED_VALUE"""),45957.0) -> 45957 | B52: =IFERROR(__xludf.DUMMYFUNCTION("""COMPUTED_VALUE"""),"Food & Drink") -> Food & Drink | C52: =IFERROR(__xludf.DUMMYFUNCTION("""COMPUTED_VALUE"""),"Snacks") -> Snacks | D52: =IFERROR(__xludf.DUMMYFUNCTION("""COMPUTED_VALUE"""),204.0) -> 204 | E52: =IFERROR(__xludf.DUMMYFUNCTION("""COMPUTED_VALUE"""),"7-Eleven") -> 7-Eleven | F52: =IFERROR(__xludf.DUMMYFUNCTION("""COMPUTED_VALUE"""),"ตั้งแต่วันที่ 27-29") -> ตั้งแต่วันที่ 27-29
A53: =IFERROR(__xludf.DUMMYFUNCTION("""COMPUTED_VALUE"""),45956.0) -> 45956 | B53: =IFERROR(__xludf.DUMMYFUNCTION("""COMPUTED_VALUE"""),"Others") -> Others | C53: =IFERROR(__xludf.DUMMYFUNCTION("""COMPUTED_VALUE"""),"Others") -> Others | D53: =IFERROR(__xludf.DUMMYFUNCTION("""COMPUTED_VALUE"""),27.0) -> 27 | F53: =IFERROR(__xludf.DUMMYFUNCTION("""COMPUTED_VALUE"""),"ค่าส่งหูฟัง soundcore") -> ค่าส่งหูฟัง soundcore
A54: =IFERROR(__xludf.DUMMYFUNCTION("""COMPUTED_VALUE"""),45956.0) -> 45956 | B54: =IFERROR(__xludf.DUMMYFUNCTION("""COMPUTED_VALUE"""),"Food & Drink") -> Food & Drink | C54: =IFERROR(__xludf.DUMMYFUNCTION("""COMPUTED_VALUE"""),"Main meals") -> Main meals | D54: =IFERROR(__xludf.DUMMYFUNCTION("""COMPUTED_VALUE"""),85.0) -> 85 | E54: =IFERROR(__xludf.DUMMYFUNCTION("""COMPUTED_VALUE"""),"Noodle") -> Noodle
A55: =IFERROR(__xludf.DUMMYFUNCTION("""COMPUTED_VALUE"""),45956.0) -> 45956 | B55: =IFERROR(__xludf.DUMMYFUNCTION("""COMPUTED_VALUE"""),"Food & Drink") -> Food & Drink | C55: =IFERROR(__xludf.DUMMYFUNCTION("""COMPUTED_VALUE"""),"Drinks") -> Drinks | D55: =IFERROR(__xludf.DUMMYFUNCTION("""COMPUTED_VALUE"""),40.0) -> 40 | E55: =IFERROR(__xludf.DUMMYFUNCTION("""COMPUTED_VALUE"""),"CJ") -> CJ | F55: =IFERROR(__xludf.DUMMYFUNCTION("""COMPUTED_VALUE"""),"ชาไทย") -> ชาไทย
A56: =IFERROR(__xludf.DUMMYFUNCTION("""COMPUTED_VALUE"""),45956.0) -> 45956 | B56: =IFERROR(__xludf.DUMMYFUNCTION("""COMPUTED_VALUE"""),"Food & Drink") -> Food & Drink | C56: =IFERROR(__xludf.DUMMYFUNCTION("""COMPUTED_VALUE"""),"Groceries") -> Groceries | D56: =IFERROR(__xludf.DUMMYFUNCTION("""COMPUTED_VALUE"""),120.0) -> 120 | F56: =IFERROR(__xludf.DUMMYFUNCTION("""COMPUTED_VALUE"""),"ผัก") -> ผัก
A57: =IFERROR(__xludf.DUMMYFUNCTION("""COMPUTED_VALUE"""),45956.0) -> 45956 | B57: =IFERROR(__xludf.DUMMYFUNCTION("""COMPUTED_VALUE"""),"Transportation") -> Transportation | C57: =IFERROR(__xludf.DUMMYFUNCTION("""COMPUTED_VALUE"""),"Maintenance") -> Maintenance | D57: =IFERROR(__xludf.DUMMYFUNCTION("""COMPUTED_VALUE"""),1000.0) -> 1000 | F57: =IFERROR(__xludf.DUMMYFUNCTION("""COMPUTED_VALUE"""),"เปลี่ยนคิ้วรถ") -> เปลี่ยนคิ้วรถ
A58: =IFERROR(__xludf.DUMMYFUNCTION("""COMPUTED_VALUE"""),45955.0) -> 45955 | B58: =IFERROR(__xludf.DUMMYFUNCTION("""COMPUTED_VALUE"""),"Food & Drink") -> Food & Drink | C58: =IFERROR(__xludf.DUMMYFUNCTION("""COMPUTED_VALUE"""),"Main meals") -> Main meals | D58: =IFERROR(__xludf.DUMMYFUNCTION("""COMPUTED_VALUE"""),80.0) -> 80 | F58: =IFERROR(__xludf.DUMMYFUNCTION("""COMPUTED_VALUE"""),"กะเพรา") -> กะเพรา
A59: =IFERROR(__xludf.DUMMYFUNCTION("""COMPUTED_VALUE"""),45955.0) -> 45955 | B59: =IFERROR(__xludf.DUMMYFUNCTION("""COMPUTED_VALUE"""),"Food & Drink") -> Food & Drink | C59: =IFERROR(__xludf.DUMMYFUNCTION("""COMPUTED_VALUE"""),"Groceries") -> Groceries | D59: =IFERROR(__xludf.DUMMYFUNCTION("""COMPUTED_VALUE"""),162.0) -> 162 | F59: =IFERROR(__xludf.DUMMYFUNCTION("""COMPUTED_VALUE"""),"ผัก") -> ผัก
A60: =IFERROR(__xludf.DUMMYFUNCTION("""COMPUTED_VALUE"""),45955.0) -> 45955 | B60: =IFERROR(__xludf.DUMMYFUNCTION("""COMPUTED_VALUE"""),"Food & Drink") -> Food & Drink | C60: =IFERROR(__xludf.DUMMYFUNCTION("""COMPUTED_VALUE"""),"Drinks") -> Drinks | D60: =IFERROR(__xludf.DUMMYFUNCTION("""COMPUTED_VALUE"""),40.0) -> 40 | E60: =IFERROR(__xludf.DUMMYFUNCTION("""COMPUTED_VALUE"""),"CJ") -> CJ | F60: =IFERROR(__xludf.DUMMYFUNCTION("""COMPUTED_VALUE"""),"ชาไทย") -> ชาไทย
A61: =IFERROR(__xludf.DUMMYFUNCTION("""COMPUTED_VALUE"""),45955.0) -> 45955 | B61: =IFERROR(__xludf.DUMMYFUNCTION("""COMPUTED_VALUE"""),"Items") -> Items | C61: =IFERROR(__xludf.DUMMYFUNCTION("""COMPUTED_VALUE"""),"Household Items") -> Household Items | D61: =IFERROR(__xludf.DUMMYFUNCTION("""COMPUTED_VALUE"""),142.0) -> 142 | E61: =IFERROR(__xludf.DUMMYFUNCTION("""COMPUTED_VALUE"""),"Lotus") -> Lotus | F61: =IFERROR(__xludf.DUMMYFUNCTION("""COMPUTED_VALUE"""),"สำลี ครีมอาบน้ำไ") -> สำลี ครีมอาบน้ำไ
A62: =IFERROR(__xludf.DUMMYFUNCTION("""COMPUTED_VALUE"""),45955.0) -> 45955 | B62: =IFERROR(__xludf.DUMMYFUNCTION("""COMPUTED_VALUE"""),"Food & Drink") -> Food & Drink | C62: =IFERROR(__xludf.DUMMYFUNCTION("""COMPUTED_VALUE"""),"Groceries") -> Groceries | D62: =IFERROR(__xludf.DUMMYFUNCTION("""COMPUTED_VALUE"""),381.25) -> 381.25 | E62: =IFERROR(__xludf.DUMMYFUNCTION("""COMPUTED_VALUE"""),"Lotus") -> Lotus
A63: =IFERROR(__xludf.DUMMYFUNCTION("""COMPUTED_VALUE"""),45954.0) -> 45954 | B63: =IFERROR(__xludf.DUMMYFUNCTION("""COMPUTED_VALUE"""),"Others") -> Others | C63: =IFERROR(__xludf.DUMMYFUNCTION("""COMPUTED_VALUE"""),"Debt") -> Debt | D63: =IFERROR(__xludf.DUMMYFUNCTION("""COMPUTED_VALUE"""),8521.0) -> 8521 | F63: =IFERROR(__xludf.DUMMYFUNCTION("""COMPUTED_VALUE"""),"ค่ารถงวด 39") -> ค่ารถงวด 39
A64: =IFERROR(__xludf.DUMMYFUNCTION("""COMPUTED_VALUE"""),45954.0) -> 45954 | B64: =IFERROR(__xludf.DUMMYFUNCTION("""COMPUTED_VALUE"""),"Others") -> Others | C64: =IFERROR(__xludf.DUMMYFUNCTION("""COMPUTED_VALUE"""),"Devidend") -> Devidend | D64: =IFERROR(__xludf.DUMMYFUNCTION("""COMPUTED_VALUE"""),2000.0) -> 2000 | E64: =IFERROR(__xludf.DUMMYFUNCTION("""COMPUTED_VALUE"""),"Studentloan Debt") -> Studentloan Debt | F64: =IFERROR(__xludf.DUMMYFUNCTION("""COMPUTED_VALUE"""),"กยศ") -> กยศ
A65: =IFERROR(__xludf.DUMMYFUNCTION("""COMPUTED_VALUE"""),45954.0) -> 45954 | B65: =IFERROR(__xludf.DUMMYFUNCTION("""COMPUTED_VALUE"""),"Service") -> Service | C65: =IFERROR(__xludf.DUMMYFUNCTION("""COMPUTED_VALUE"""),"Home Internet") -> Home Internet | D65: =IFERROR(__xludf.DUMMYFUNCTION("""COMPUTED_VALUE"""),650.0) -> 650 | F65: =IFERROR(__xludf.DUMMYFUNCTION("""COMPUTED_VALUE"""),"เน็ตบ้าน") -> เน็ตบ้าน
A66: =IFERROR(__xludf.DUMMYFUNCTION("""COMPUTED_VALUE"""),45954.0) -> 45954 | B66: =IFERROR(__xludf.DUMMYFUNCTION("""COMPUTED_VALUE"""),"Service") -> Service | C66: =IFERROR(__xludf.DUMMYFUNCTION("""COMPUTED_VALUE"""),"Mobile Internet") -> Mobile Internet | D66: =IFERROR(__xludf.DUMMYFUNCTION("""COMPUTED_VALUE"""),450.0) -> 450 | F66: =IFERROR(__xludf.DUMMYFUNCTION("""COMPUTED_VALUE"""),"เน็็ตมือถือ") -> เน็็ตมือถือ
A67: =IFERROR(__xludf.DUMMYFUNCTION("""COMPUTED_VALUE"""),45954.0) -> 45954 | B67: =IFERROR(__xludf.DUMMYFUNCTION("""COMPUTED_VALUE"""),"Food & Drink") -> Food & Drink | C67: =IFERROR(__xludf.DUMMYFUNCTION("""COMPUTED_VALUE"""),"Main meals") -> Main meals | D67: =IFERROR(__xludf.DUMMYFUNCTION("""COMPUTED_VALUE"""),80.0) -> 80 | F67: =IFERROR(__xludf.DUMMYFUNCTION("""COMPUTED_VALUE"""),"ข้าวมันไก่, ลูกชิ้น") -> ข้าวมันไก่, ลูกชิ้น
A68: =IFERROR(__xludf.DUMMYFUNCTION("""COMPUTED_VALUE"""),45954.0) -> 45954 | B68: =IFERROR(__xludf.DUMMYFUNCTION("""COMPUTED_VALUE"""),"Food & Drink") -> Food & Drink | C68: =IFERROR(__xludf.DUMMYFUNCTION("""COMPUTED_VALUE"""),"Main meals") -> Main meals | D68: =IFERROR(__xludf.DUMMYFUNCTION("""COMPUTED_VALUE"""),190.0) -> 190 | E68: =IFERROR(__xludf.DUMMYFUNCTION("""COMPUTED_VALUE"""),"Bonchon") -> Bonchon
A69: =IFERROR(__xludf.DUMMYFUNCTION("""COMPUTED_VALUE"""),45953.0) -> 45953 | B69: =IFERROR(__xludf.DUMMYFUNCTION("""COMPUTED_VALUE"""),"Food & Drink") -> Food & Drink | C69: =IFERROR(__xludf.DUMMYFUNCTION("""COMPUTED_VALUE"""),"Snacks") -> Snacks | D69: =IFERROR(__xludf.DUMMYFUNCTION("""COMPUTED_VALUE"""),37.0) -> 37 | F69: =IFERROR(__xludf.DUMMYFUNCTION("""COMPUTED_VALUE"""),"โตเกียว") -> โตเกียว
A70: =IFERROR(__xludf.DUMMYFUNCTION("""COMPUTED_VALUE"""),45952.0) -> 45952 | B70: =IFERROR(__xludf.DUMMYFUNCTION("""COMPUTED_VALUE"""),"Food & Drink") -> Food & Drink | C70: =IFERROR(__xludf.DUMMYFUNCTION("""COMPUTED_VALUE"""),"Main meals") -> Main meals | D70: =IFERROR(__xludf.DUMMYFUNCTION("""COMPUTED_VALUE"""),153.0) -> 153 | E70: =IFERROR(__xludf.DUMMYFUNCTION("""COMPUTED_VALUE"""),"KFC") -> KFC
A71: =IFERROR(__xludf.DUMMYFUNCTION("""COMPUTED_VALUE"""),45952.0) -> 45952 | B71: =IFERROR(__xludf.DUMMYFUNCTION("""COMPUTED_VALUE"""),"Others") -> Others | C71: =IFERROR(__xludf.DUMMYFUNCTION("""COMPUTED_VALUE"""),"Others") -> Others | D71: =IFERROR(__xludf.DUMMYFUNCTION("""COMPUTED_VALUE"""),100.0) -> 100 | F71: =IFERROR(__xludf.DUMMYFUNCTION("""COMPUTED_VALUE"""),"ให้พาย") -> ให้พาย
A72: =IFERROR(__xludf.DUMMYFUNCTION("""COMPUTED_VALUE"""),45951.0) -> 45951 | B72: =IFERROR(__xludf.DUMMYFUNCTION("""COMPUTED_VALUE"""),"Food & Drink") -> Food & Drink | C72: =IFERROR(__xludf.DUMMYFUNCTION("""COMPUTED_VALUE"""),"Main meals") -> Main meals | D72: =IFERROR(__xludf.DUMMYFUNCTION("""COMPUTED_VALUE"""),139.0) -> 139 | E72: =IFERROR(__xludf.DUMMYFUNCTION("""COMPUTED_VALUE"""),"Noodle") -> Noodle | F72: =IFERROR(__xludf.DUMMYFUNCTION("""COMPUTED_VALUE"""),"เตี๋ยวไก่") -> เตี๋ยวไก่
A73: =IFERROR(__xludf.DUMMYFUNCTION("""COMPUTED_VALUE"""),45950.0) -> 45950 | B73: =IFERROR(__xludf.DUMMYFUNCTION("""COMPUTED_VALUE"""),"Food & Drink") -> Food & Drink | C73: =IFERROR(__xludf.DUMMYFUNCTION("""COMPUTED_VALUE"""),"Main meals") -> Main meals | D73: =IFERROR(__xludf.DUMMYFUNCTION("""COMPUTED_VALUE"""),85.0) -> 85 | F73: =IFERROR(__xludf.DUMMYFUNCTION("""COMPUTED_VALUE"""),"กะเพรา") -> กะเพรา
A74: =IFERROR(__xludf.DUMMYFUNCTION("""COMPUTED_VALUE"""),45950.0) -> 45950 | B74: =IFERROR(__xludf.DUMMYFUNCTION("""COMPUTED_VALUE"""),"Food & Drink") -> Food & Drink | C74: =IFERROR(__xludf.DUMMYFUNCTION("""COMPUTED_VALUE"""),"Dine-out") -> Dine-out | D74: =IFERROR(__xludf.DUMMYFUNCTION("""COMPUTED_VALUE"""),534.0) -> 534 | F74: =IFERROR(__xludf.DUMMYFUNCTION("""COMPUTED_VALUE"""),"BBQ Plaza") -> BBQ Plaza
A75: =IFERROR(__xludf.DUMMYFUNCTION("""COMPUTED_VALUE"""),45950.0) -> 45950 | B75: =IFERROR(__xludf.DUMMYFUNCTION("""COMPUTED_VALUE"""),"Food & Drink") -> Food & Drink | C75: =IFERROR(__xludf.DUMMYFUNCTION("""COMPUTED_VALUE"""),"Snacks") -> Snacks | D75: =IFERROR(__xludf.DUMMYFUNCTION("""COMPUTED_VALUE"""),10.0) -> 10 | F75: =IFERROR(__xludf.DUMMYFUNCTION("""COMPUTED_VALUE"""),"ถั่ว") -> ถั่ว
A76: =IFERROR(__xludf.DUMMYFUNCTION("""COMPUTED_VALUE"""),45950.0) -> 45950 | B76: =IFERROR(__xludf.DUMMYFUNCTION("""COMPUTED_VALUE"""),"Residence") -> Residence | C76: =IFERROR(__xludf.DUMMYFUNCTION("""COMPUTED_VALUE"""),"Water Bill") -> Water Bill | D76: =IFERROR(__xludf.DUMMYFUNCTION("""COMPUTED_VALUE"""),184.07) -> 184.07 | F76: =IFERROR(__xludf.DUMMYFUNCTION("""COMPUTED_VALUE"""),"ค่าน้ำ") -> ค่าน้ำ
A77: =IFERROR(__xludf.DUMMYFUNCTION("""COMPUTED_VALUE"""),45950.0) -> 45950 | B77: =IFERROR(__xludf.DUMMYFUNCTION("""COMPUTED_VALUE"""),"Food & Drink") -> Food & Drink | C77: =IFERROR(__xludf.DUMMYFUNCTION("""COMPUTED_VALUE"""),"Snacks") -> Snacks | D77: =IFERROR(__xludf.DUMMYFUNCTION("""COMPUTED_VALUE"""),278.0) -> 278 | E77: =IFERROR(__xludf.DUMMYFUNCTION("""COMPUTED_VALUE"""),"7-Eleven") -> 7-Eleven | F77: =IFERROR(__xludf.DUMMYFUNCTION("""COMPUTED_VALUE"""),"ตั้งแต่วันที่ 20-24") -> ตั้งแต่วันที่ 20-24
A78: =IFERROR(__xludf.DUMMYFUNCTION("""COMPUTED_VALUE"""),45949.0) -> 45949 | B78: =IFERROR(__xludf.DUMMYFUNCTION("""COMPUTED_VALUE"""),"Service") -> Service | C78: =IFERROR(__xludf.DUMMYFUNCTION("""COMPUTED_VALUE"""),"Subscription") -> Subscription | D78: =IFERROR(__xludf.DUMMYFUNCTION("""COMPUTED_VALUE"""),1200.0) -> 1200 | F78: =IFERROR(__xludf.DUMMYFUNCTION("""COMPUTED_VALUE"""),"เข้ากลุ่มลิงเล่นหุ้นรายปี") -> เข้ากลุ่มลิงเล่นหุ้นรายปี
A79: =IFERROR(__xludf.DUMMYFUNCTION("""COMPUTED_VALUE"""),45949.0) -> 45949 | B79: =IFERROR(__xludf.DUMMYFUNCTION("""COMPUTED_VALUE"""),"Food & Drink") -> Food & Drink | C79: =IFERROR(__xludf.DUMMYFUNCTION("""COMPUTED_VALUE"""),"Groceries") -> Groceries | D79: =IFERROR(__xludf.DUMMYFUNCTION("""COMPUTED_VALUE"""),60.0) -> 60 | F79: =IFERROR(__xludf.DUMMYFUNCTION("""COMPUTED_VALUE"""),"ผักตลาด") -> ผักตลาด
A80: =IFERROR(__xludf.DUMMYFUNCTION("""COMPUTED_VALUE"""),45949.0) -> 45949 | B80: =IFERROR(__xludf.DUMMYFUNCTION("""COMPUTED_VALUE"""),"Food & Drink") -> Food & Drink | C80: =IFERROR(__xludf.DUMMYFUNCTION("""COMPUTED_VALUE"""),"Snacks") -> Snacks | D80: =IFERROR(__xludf.DUMMYFUNCTION("""COMPUTED_VALUE"""),99.0) -> 99 | F80: =IFERROR(__xludf.DUMMYFUNCTION("""COMPUTED_VALUE"""),"bing su") -> bing su
A81: =IFERROR(__xludf.DUMMYFUNCTION("""COMPUTED_VALUE"""),45949.0) -> 45949 | B81: =IFERROR(__xludf.DUMMYFUNCTION("""COMPUTED_VALUE"""),"Food & Drink") -> Food & Drink | C81: =IFERROR(__xludf.DUMMYFUNCTION("""COMPUTED_VALUE"""),"Main meals") -> Main meals | D81: =IFERROR(__xludf.DUMMYFUNCTION("""COMPUTED_VALUE"""),110.0) -> 110 | F81: =IFERROR(__xludf.DUMMYFUNCTION("""COMPUTED_VALUE"""),"กะเพรา") -> กะเพรา
A82: =IFERROR(__xludf.DUMMYFUNCTION("""COMPUTED_VALUE"""),45949.0) -> 45949 | B82: =IFERROR(__xludf.DUMMYFUNCTION("""COMPUTED_VALUE"""),"Items") -> Items | C82: =IFERROR(__xludf.DUMMYFUNCTION("""COMPUTED_VALUE"""),"Others") -> Others | D82: =IFERROR(__xludf.DUMMYFUNCTION("""COMPUTED_VALUE"""),30.0) -> 30 | F82: =IFERROR(__xludf.DUMMYFUNCTION("""COMPUTED_VALUE"""),"พวกกุจแจของญี่ปุ่น") -> พวกกุจแจของญี่ปุ่น
A83: =IFERROR(__xludf.DUMMYFUNCTION("""COMPUTED_VALUE"""),45949.0) -> 45949 | B83: =IFERROR(__xludf.DUMMYFUNCTION("""COMPUTED_VALUE"""),"Items") -> Items | C83: =IFERROR(__xludf.DUMMYFUNCTION("""COMPUTED_VALUE"""),"Personal Items") -> Personal Items | D83: =IFERROR(__xludf.DUMMYFUNCTION("""COMPUTED_VALUE"""),157.0) -> 157 | F83: =IFERROR(__xludf.DUMMYFUNCTION("""COMPUTED_VALUE"""),"น้ำหอมรถยนต์") -> น้ำหอมรถยนต์
A84: =IFERROR(__xludf.DUMMYFUNCTION("""COMPUTED_VALUE"""),45949.0) -> 45949 | B84: =IFERROR(__xludf.DUMMYFUNCTION("""COMPUTED_VALUE"""),"Hobby") -> Hobby | C84: =IFERROR(__xludf.DUMMYFUNCTION("""COMPUTED_VALUE"""),"Computer") -> Computer | D84: =IFERROR(__xludf.DUMMYFUNCTION("""COMPUTED_VALUE"""),1017.0) -> 1017 | F84: =IFERROR(__xludf.DUMMYFUNCTION("""COMPUTED_VALUE"""),"ขาจับไมค์, แผ่นรองเม้า") -> ขาจับไมค์, แผ่นรองเม้า
A85: =IFERROR(__xludf.DUMMYFUNCTION("""COMPUTED_VALUE"""),45948.0) -> 45948 | B85: =IFERROR(__xludf.DUMMYFUNCTION("""COMPUTED_VALUE"""),"Transportation") -> Transportation | C85: =IFERROR(__xludf.DUMMYFUNCTION("""COMPUTED_VALUE"""),"Others") -> Others | D85: =IFERROR(__xludf.DUMMYFUNCTION("""COMPUTED_VALUE"""),337.0) -> 337 | F85: =IFERROR(__xludf.DUMMYFUNCTION("""COMPUTED_VALUE"""),"นั่ง grab กลับบ้าน") -> นั่ง grab กลับบ้าน
A86: =IFERROR(__xludf.DUMMYFUNCTION("""COMPUTED_VALUE"""),45948.0) -> 45948 | B86: =IFERROR(__xludf.DUMMYFUNCTION("""COMPUTED_VALUE"""),"Food & Drink") -> Food & Drink | C86: =IFERROR(__xludf.DUMMYFUNCTION("""COMPUTED_VALUE"""),"Main meals") -> Main meals | D86: =IFERROR(__xludf.DUMMYFUNCTION("""COMPUTED_VALUE"""),205.6) -> 205.6 | F86: =IFERROR(__xludf.DUMMYFUNCTION("""COMPUTED_VALUE"""),"ข้าวเที่ยง") -> ข้าวเที่ยง
A87: =IFERROR(__xludf.DUMMYFUNCTION("""COMPUTED_VALUE"""),45947.0) -> 45947 | B87: =IFERROR(__xludf.DUMMYFUNCTION("""COMPUTED_VALUE"""),"Items") -> Items | C87: =IFERROR(__xludf.DUMMYFUNCTION("""COMPUTED_VALUE"""),"Household Items") -> Household Items | D87: =IFERROR(__xludf.DUMMYFUNCTION("""COMPUTED_VALUE"""),432.0) -> 432 | F87: =IFERROR(__xludf.DUMMYFUNCTION("""COMPUTED_VALUE"""),"แปรงสีฟัน, ยาสระผม") -> แปรงสีฟัน, ยาสระผม
A88: =IFERROR(__xludf.DUMMYFUNCTION("""COMPUTED_VALUE"""),45947.0) -> 45947 | B88: =IFERROR(__xludf.DUMMYFUNCTION("""COMPUTED_VALUE"""),"Items") -> Items | C88: =IFERROR(__xludf.DUMMYFUNCTION("""COMPUTED_VALUE"""),"Skincare") -> Skincare | D88: =IFERROR(__xludf.DUMMYFUNCTION("""COMPUTED_VALUE"""),1927.0) -> 1927 | F88: =IFERROR(__xludf.DUMMYFUNCTION("""COMPUTED_VALUE"""),"น้ำหอม CK, ครีม verite, มีดโกนหนวด") -> น้ำหอม CK, ครีม verite, มีดโกนหนวด
A89: =IFERROR(__xludf.DUMMYFUNCTION("""COMPUTED_VALUE"""),45947.0) -> 45947 | B89: =IFERROR(__xludf.DUMMYFUNCTION("""COMPUTED_VALUE"""),"Food & Drink") -> Food & Drink | C89: =IFERROR(__xludf.DUMMYFUNCTION("""COMPUTED_VALUE"""),"Alcohol") -> Alcohol | D89: =IFERROR(__xludf.DUMMYFUNCTION("""COMPUTED_VALUE"""),1284.0) -> 1284 | E89: =IFERROR(__xludf.DUMMYFUNCTION("""COMPUTED_VALUE"""),"Thai Watsadu") -> Thai Watsadu | F89: =IFERROR(__xludf.DUMMYFUNCTION("""COMPUTED_VALUE"""),"เบียร์ + ตี๋น้อย") -> เบียร์ + ตี๋น้อย
A90: =IFERROR(__xludf.DUMMYFUNCTION("""COMPUTED_VALUE"""),45946.0) -> 45946 | B90: =IFERROR(__xludf.DUMMYFUNCTION("""COMPUTED_VALUE"""),"Others") -> Others | C90: =IFERROR(__xludf.DUMMYFUNCTION("""COMPUTED_VALUE"""),"Others") -> Others | D90: =IFERROR(__xludf.DUMMYFUNCTION("""COMPUTED_VALUE"""),12.0) -> 12 | F90: =IFERROR(__xludf.DUMMYFUNCTION("""COMPUTED_VALUE"""),"ถ่ายเอกสารทำบัตรเครดิต") -> ถ่ายเอกสารทำบัตรเครดิต
A91: =IFERROR(__xludf.DUMMYFUNCTION("""COMPUTED_VALUE"""),45946.0) -> 45946 | B91: =IFERROR(__xludf.DUMMYFUNCTION("""COMPUTED_VALUE"""),"Food & Drink") -> Food & Drink | C91: =IFERROR(__xludf.DUMMYFUNCTION("""COMPUTED_VALUE"""),"Main meals") -> Main meals | D91: =IFERROR(__xludf.DUMMYFUNCTION("""COMPUTED_VALUE"""),85.0) -> 85 | F91: =IFERROR(__xludf.DUMMYFUNCTION("""COMPUTED_VALUE"""),"กะเพรา") -> กะเพรา
A92: =IFERROR(__xludf.DUMMYFUNCTION("""COMPUTED_VALUE"""),45946.0) -> 45946 | B92: =IFERROR(__xludf.DUMMYFUNCTION("""COMPUTED_VALUE"""),"Food & Drink") -> Food & Drink | C92: =IFERROR(__xludf.DUMMYFUNCTION("""COMPUTED_VALUE"""),"Groceries") -> Groceries | D92: =IFERROR(__xludf.DUMMYFUNCTION("""COMPUTED_VALUE"""),60.0) -> 60 | F92: =IFERROR(__xludf.DUMMYFUNCTION("""COMPUTED_VALUE"""),"มะพร้าว") -> มะพร้าว
A93: =IFERROR(__xludf.DUMMYFUNCTION("""COMPUTED_VALUE"""),45946.0) -> 45946 | B93: =IFERROR(__xludf.DUMMYFUNCTION("""COMPUTED_VALUE"""),"Service") -> Service | C93: =IFERROR(__xludf.DUMMYFUNCTION("""COMPUTED_VALUE"""),"Haircut") -> Haircut | D93: =IFERROR(__xludf.DUMMYFUNCTION("""COMPUTED_VALUE"""),200.0) -> 200
A94: =IFERROR(__xludf.DUMMYFUNCTION("""COMPUTED_VALUE"""),45946.0) -> 45946 | B94: =IFERROR(__xludf.DUMMYFUNCTION("""COMPUTED_VALUE"""),"Food & Drink") -> Food & Drink | C94: =IFERROR(__xludf.DUMMYFUNCTION("""COMPUTED_VALUE"""),"Drinks") -> Drinks | D94: =IFERROR(__xludf.DUMMYFUNCTION("""COMPUTED_VALUE"""),40.0) -> 40 | F94: =IFERROR(__xludf.DUMMYFUNCTION("""COMPUTED_VALUE"""),"ชานม") -> ชานม
A95: =IFERROR(__xludf.DUMMYFUNCTION("""COMPUTED_VALUE"""),45946.0) -> 45946 | B95: =IFERROR(__xludf.DUMMYFUNCTION("""COMPUTED_VALUE"""),"Food & Drink") -> Food & Drink | C95: =IFERROR(__xludf.DUMMYFUNCTION("""COMPUTED_VALUE"""),"Main meals") -> Main meals | D95: =IFERROR(__xludf.DUMMYFUNCTION("""COMPUTED_VALUE"""),50.0) -> 50 | E95: =IFERROR(__xludf.DUMMYFUNCTION("""COMPUTED_VALUE"""),"Hainanese chicken rice") -> Hainanese chicken rice
A96: =IFERROR(__xludf.DUMMYFUNCTION("""COMPUTED_VALUE"""),45946.0) -> 45946 | B96: =IFERROR(__xludf.DUMMYFUNCTION("""COMPUTED_VALUE"""),"Food & Drink") -> Food & Drink | C96: =IFERROR(__xludf.DUMMYFUNCTION("""COMPUTED_VALUE"""),"Snacks") -> Snacks | D96: =IFERROR(__xludf.DUMMYFUNCTION("""COMPUTED_VALUE"""),58.0) -> 58 | E96: =IFERROR(__xludf.DUMMYFUNCTION("""COMPUTED_VALUE"""),"Lotus") -> Lotus | F96: =IFERROR(__xludf.DUMMYFUNCTION("""COMPUTED_VALUE"""),"ขนมปัง") -> ขนมปัง
A97: =IFERROR(__xludf.DUMMYFUNCTION("""COMPUTED_VALUE"""),45946.0) -> 45946 | B97: =IFERROR(__xludf.DUMMYFUNCTION("""COMPUTED_VALUE"""),"Food & Drink") -> Food & Drink | C97: =IFERROR(__xludf.DUMMYFUNCTION("""COMPUTED_VALUE"""),"Groceries") -> Groceries | D97: =IFERROR(__xludf.DUMMYFUNCTION("""COMPUTED_VALUE"""),206.0) -> 206 | E97: =IFERROR(__xludf.DUMMYFUNCTION("""COMPUTED_VALUE"""),"Lotus") -> Lotus | F97: =IFERROR(__xludf.DUMMYFUNCTION("""COMPUTED_VALUE"""),"ผัก") -> ผัก
A98: =IFERROR(__xludf.DUMMYFUNCTION("""COMPUTED_VALUE"""),45945.0) -> 45945 | B98: =IFERROR(__xludf.DUMMYFUNCTION("""COMPUTED_VALUE"""),"Food & Drink") -> Food & Drink | C98: =IFERROR(__xludf.DUMMYFUNCTION("""COMPUTED_VALUE"""),"Main meals") -> Main meals | D98: =IFERROR(__xludf.DUMMYFUNCTION("""COMPUTED_VALUE"""),98.0) -> 98 | E98: =IFERROR(__xludf.DUMMYFUNCTION("""COMPUTED_VALUE"""),"KFC") -> KFC
A99: =IFERROR(__xludf.DUMMYFUNCTION("""COMPUTED_VALUE"""),45944.0) -> 45944 | B99: =IFERROR(__xludf.DUMMYFUNCTION("""COMPUTED_VALUE"""),"Food & Drink") -> Food & Drink | C99: =IFERROR(__xludf.DUMMYFUNCTION("""COMPUTED_VALUE"""),"Main meals") -> Main meals | D99: =IFERROR(__xludf.DUMMYFUNCTION("""COMPUTED_VALUE"""),50.0) -> 50 | E99: =IFERROR(__xludf.DUMMYFUNCTION("""COMPUTED_VALUE"""),"Noodle") -> Noodle
A100: =IFERROR(__xludf.DUMMYFUNCTION("""COMPUTED_VALUE"""),45944.0) -> 45944 | B100: =IFERROR(__xludf.DUMMYFUNCTION("""COMPUTED_VALUE"""),"Transportation") -> Transportation | C100: =IFERROR(__xludf.DUMMYFUNCTION("""COMPUTED_VALUE"""),"Fee") -> Fee | D100: =IFERROR(__xludf.DUMMYFUNCTION("""COMPUTED_VALUE"""),30.0) -> 30 | F100: =IFERROR(__xludf.DUMMYFUNCTION("""COMPUTED_VALUE"""),"mflow") -> mflow
A101: =IFERROR(__xludf.DUMMYFUNCTION("""COMPUTED_VALUE"""),45944.0) -> 45944 | B101: =IFERROR(__xludf.DUMMYFUNCTION("""COMPUTED_VALUE"""),"Food & Drink") -> Food & Drink | C101: =IFERROR(__xludf.DUMMYFUNCTION("""COMPUTED_VALUE"""),"Drinks") -> Drinks | D101: =IFERROR(__xludf.DUMMYFUNCTION("""COMPUTED_VALUE"""),28.0) -> 28 | E101: =IFERROR(__xludf.DUMMYFUNCTION("""COMPUTED_VALUE"""),"7-Eleven") -> 7-Eleven | F101: =IFERROR(__xludf.DUMMYFUNCTION("""COMPUTED_VALUE"""),"pepsi") -> pepsi
A102: =IFERROR(__xludf.DUMMYFUNCTION("""COMPUTED_VALUE"""),45943.0) -> 45943 | B102: =IFERROR(__xludf.DUMMYFUNCTION("""COMPUTED_VALUE"""),"Health") -> Health | C102: =IFERROR(__xludf.DUMMYFUNCTION("""COMPUTED_VALUE"""),"Exercise Equipment") -> Exercise Equipment | D102: =IFERROR(__xludf.DUMMYFUNCTION("""COMPUTED_VALUE"""),200.0) -> 200 | E102: =IFERROR(__xludf.DUMMYFUNCTION("""COMPUTED_VALUE"""),"Decathlon") -> Decathlon | F102: =IFERROR(__xludf.DUMMYFUNCTION("""COMPUTED_VALUE"""),"Resistance Band") -> Resistance Band
A103: =IFERROR(__xludf.DUMMYFUNCTION("""COMPUTED_VALUE"""),45943.0) -> 45943 | B103: =IFERROR(__xludf.DUMMYFUNCTION("""COMPUTED_VALUE"""),"Transportation") -> Transportation | C103: =IFERROR(__xludf.DUMMYFUNCTION("""COMPUTED_VALUE"""),"Fuel") -> Fuel | D103: =IFERROR(__xludf.DUMMYFUNCTION("""COMPUTED_VALUE"""),750.0) -> 750 | E103: =IFERROR(__xludf.DUMMYFUNCTION("""COMPUTED_VALUE"""),"Caltex") -> Caltex
A104: =IFERROR(__xludf.DUMMYFUNCTION("""COMPUTED_VALUE"""),45943.0) -> 45943 | B104: =IFERROR(__xludf.DUMMYFUNCTION("""COMPUTED_VALUE"""),"Food & Drink") -> Food & Drink | C104: =IFERROR(__xludf.DUMMYFUNCTION("""COMPUTED_VALUE"""),"Main meals") -> Main meals | D104: =IFERROR(__xludf.DUMMYFUNCTION("""COMPUTED_VALUE"""),149.0) -> 149 | E104: =IFERROR(__xludf.DUMMYFUNCTION("""COMPUTED_VALUE"""),"Subway") -> Subway | F104: =IFERROR(__xludf.DUMMYFUNCTION("""COMPUTED_VALUE"""),"ข้าวหน้าเนื้อ") -> ข้าวหน้าเนื้อ
A105: =IFERROR(__xludf.DUMMYFUNCTION("""COMPUTED_VALUE"""),45943.0) -> 45943 | B105: =IFERROR(__xludf.DUMMYFUNCTION("""COMPUTED_VALUE"""),"Service") -> Service | C105: =IFERROR(__xludf.DUMMYFUNCTION("""COMPUTED_VALUE"""),"Subscription") -> Subscription | D105: =IFERROR(__xludf.DUMMYFUNCTION("""COMPUTED_VALUE"""),36.0) -> 36 | E105: =IFERROR(__xludf.DUMMYFUNCTION("""COMPUTED_VALUE"""),"YT Premium") -> YT Premium
A106: =IFERROR(__xludf.DUMMYFUNCTION("""COMPUTED_VALUE"""),45943.0) -> 45943 | B106: =IFERROR(__xludf.DUMMYFUNCTION("""COMPUTED_VALUE"""),"Food & Drink") -> Food & Drink | C106: =IFERROR(__xludf.DUMMYFUNCTION("""COMPUTED_VALUE"""),"Main meals") -> Main meals | D106: =IFERROR(__xludf.DUMMYFUNCTION("""COMPUTED_VALUE"""),60.0) -> 60 | F106: =IFERROR(__xludf.DUMMYFUNCTION("""COMPUTED_VALUE"""),"กะเพรา") -> กะเพรา
A107: =IFERROR(__xludf.DUMMYFUNCTION("""COMPUTED_VALUE"""),45943.0) -> 45943 | B107: =IFERROR(__xludf.DUMMYFUNCTION("""COMPUTED_VALUE"""),"Residence") -> Residence | C107: =IFERROR(__xludf.DUMMYFUNCTION("""COMPUTED_VALUE"""),"Electricity Bill-A") -> Electricity Bill-A | D107: =IFERROR(__xludf.DUMMYFUNCTION("""COMPUTED_VALUE"""),2670.31) -> 2670.31
A108: =IFERROR(__xludf.DUMMYFUNCTION("""COMPUTED_VALUE"""),45942.0) -> 45942 | B108: =IFERROR(__xludf.DUMMYFUNCTION("""COMPUTED_VALUE"""),"Food & Drink") -> Food & Drink | C108: =IFERROR(__xludf.DUMMYFUNCTION("""COMPUTED_VALUE"""),"Snacks") -> Snacks | D108: =IFERROR(__xludf.DUMMYFUNCTION("""COMPUTED_VALUE"""),72.0) -> 72 | F108: =IFERROR(__xludf.DUMMYFUNCTION("""COMPUTED_VALUE"""),"icream, น้ำเปล่า") -> icream, น้ำเปล่า
A109: =IFERROR(__xludf.DUMMYFUNCTION("""COMPUTED_VALUE"""),45942.0) -> 45942 | B109: =IFERROR(__xludf.DUMMYFUNCTION("""COMPUTED_VALUE"""),"Food & Drink") -> Food & Drink | C109: =IFERROR(__xludf.DUMMYFUNCTION("""COMPUTED_VALUE"""),"Snacks") -> Snacks | D109: =IFERROR(__xludf.DUMMYFUNCTION("""COMPUTED_VALUE"""),140.0) -> 140 | E109: =IFERROR(__xludf.DUMMYFUNCTION("""COMPUTED_VALUE"""),"7-Eleven") -> 7-Eleven | F109: =IFERROR(__xludf.DUMMYFUNCTION("""COMPUTED_VALUE"""),"ขนมตอนไป outing") -> ขนมตอนไป outing
A110: =IFERROR(__xludf.DUMMYFUNCTION("""COMPUTED_VALUE"""),45941.0) -> 45941 | B110: =IFERROR(__xludf.DUMMYFUNCTION("""COMPUTED_VALUE"""),"Food & Drink") -> Food & Drink | C110: =IFERROR(__xludf.DUMMYFUNCTION("""COMPUTED_VALUE"""),"Drinks") -> Drinks | D110: =IFERROR(__xludf.DUMMYFUNCTION("""COMPUTED_VALUE"""),95.0) -> 95 | E110: =IFERROR(__xludf.DUMMYFUNCTION("""COMPUTED_VALUE"""),"Amazon") -> Amazon
A111: =IFERROR(__xludf.DUMMYFUNCTION("""COMPUTED_VALUE"""),45941.0) -> 45941 | B111: =IFERROR(__xludf.DUMMYFUNCTION("""COMPUTED_VALUE"""),"Items") -> Items | C111: =IFERROR(__xludf.DUMMYFUNCTION("""COMPUTED_VALUE"""),"Skincare") -> Skincare | D111: =IFERROR(__xludf.DUMMYFUNCTION("""COMPUTED_VALUE"""),69.0) -> 69 | E111: =IFERROR(__xludf.DUMMYFUNCTION("""COMPUTED_VALUE"""),"7-Eleven") -> 7-Eleven | F111: =IFERROR(__xludf.DUMMYFUNCTION("""COMPUTED_VALUE"""),"moiturizer") -> moiturizer
A112: =IFERROR(__xludf.DUMMYFUNCTION("""COMPUTED_VALUE"""),45940.0) -> 45940 | B112: =IFERROR(__xludf.DUMMYFUNCTION("""COMPUTED_VALUE"""),"Transportation") -> Transportation | C112: =IFERROR(__xludf.DUMMYFUNCTION("""COMPUTED_VALUE"""),"Fuel") -> Fuel | D112: =IFERROR(__xludf.DUMMYFUNCTION("""COMPUTED_VALUE"""),750.0) -> 750 | E112: =IFERROR(__xludf.DUMMYFUNCTION("""COMPUTED_VALUE"""),"Caltex") -> Caltex
A113: =IFERROR(__xludf.DUMMYFUNCTION("""COMPUTED_VALUE"""),45940.0) -> 45940 | B113: =IFERROR(__xludf.DUMMYFUNCTION("""COMPUTED_VALUE"""),"Food & Drink") -> Food & Drink | C113: =IFERROR(__xludf.DUMMYFUNCTION("""COMPUTED_VALUE"""),"Main meals") -> Main meals | D113: =IFERROR(__xludf.DUMMYFUNCTION("""COMPUTED_VALUE"""),95.0) -> 95 | F113: =IFERROR(__xludf.DUMMYFUNCTION("""COMPUTED_VALUE"""),"กะเพรา") -> กะเพรา
A114: =IFERROR(__xludf.DUMMYFUNCTION("""COMPUTED_VALUE"""),45939.0) -> 45939 | B114: =IFERROR(__xludf.DUMMYFUNCTION("""COMPUTED_VALUE"""),"Food & Drink") -> Food & Drink | C114: =IFERROR(__xludf.DUMMYFUNCTION("""COMPUTED_VALUE"""),"Groceries") -> Groceries | D114: =IFERROR(__xludf.DUMMYFUNCTION("""COMPUTED_VALUE"""),179.0) -> 179 | F114: =IFERROR(__xludf.DUMMYFUNCTION("""COMPUTED_VALUE"""),"ผัก, กระดูกหมู, ข้าวโพด") -> ผัก, กระดูกหมู, ข้าวโพด
A115: =IFERROR(__xludf.DUMMYFUNCTION("""COMPUTED_VALUE"""),45939.0) -> 45939 | B115: =IFERROR(__xludf.DUMMYFUNCTION("""COMPUTED_VALUE"""),"Food & Drink") -> Food & Drink | C115: =IFERROR(__xludf.DUMMYFUNCTION("""COMPUTED_VALUE"""),"Main meals") -> Main meals | D115: =IFERROR(__xludf.DUMMYFUNCTION("""COMPUTED_VALUE"""),125.0) -> 125 | F115: =IFERROR(__xludf.DUMMYFUNCTION("""COMPUTED_VALUE"""),"ไส้กรอก, หมูกรอบ") -> ไส้กรอก, หมูกรอบ
A116: =IFERROR(__xludf.DUMMYFUNCTION("""COMPUTED_VALUE"""),45938.0) -> 45938 | B116: =IFERROR(__xludf.DUMMYFUNCTION("""COMPUTED_VALUE"""),"Food & Drink") -> Food & Drink | C116: =IFERROR(__xludf.DUMMYFUNCTION("""COMPUTED_VALUE"""),"Snacks") -> Snacks | D116: =IFERROR(__xludf.DUMMYFUNCTION("""COMPUTED_VALUE"""),80.0) -> 80 | F116: =IFERROR(__xludf.DUMMYFUNCTION("""COMPUTED_VALUE"""),"ขนมจีบซาลาเปา") -> ขนมจีบซาลาเปา
A117: =IFERROR(__xludf.DUMMYFUNCTION("""COMPUTED_VALUE"""),45938.0) -> 45938 | B117: =IFERROR(__xludf.DUMMYFUNCTION("""COMPUTED_VALUE"""),"Food & Drink") -> Food & Drink | C117: =IFERROR(__xludf.DUMMYFUNCTION("""COMPUTED_VALUE"""),"Drinks") -> Drinks | D117: =IFERROR(__xludf.DUMMYFUNCTION("""COMPUTED_VALUE"""),113.0) -> 113 | E117: =IFERROR(__xludf.DUMMYFUNCTION("""COMPUTED_VALUE"""),"7-Eleven") -> 7-Eleven | F117: =IFERROR(__xludf.DUMMYFUNCTION("""COMPUTED_VALUE"""),"pepsi, นม") -> pepsi, นม
A118: =IFERROR(__xludf.DUMMYFUNCTION("""COMPUTED_VALUE"""),45938.0) -> 45938 | B118: =IFERROR(__xludf.DUMMYFUNCTION("""COMPUTED_VALUE"""),"Food & Drink") -> Food & Drink | C118: =IFERROR(__xludf.DUMMYFUNCTION("""COMPUTED_VALUE"""),"Main meals") -> Main meals | D118: =IFERROR(__xludf.DUMMYFUNCTION("""COMPUTED_VALUE"""),106.0) -> 106 | E118: =IFERROR(__xludf.DUMMYFUNCTION("""COMPUTED_VALUE"""),"7-Eleven") -> 7-Eleven | F118: =IFERROR(__xludf.DUMMYFUNCTION("""COMPUTED_VALUE"""),"ไส้กรอก, สลัดอกไก่") -> ไส้กรอก, สลัดอกไก่
A119: =IFERROR(__xludf.DUMMYFUNCTION("""COMPUTED_VALUE"""),45937.0) -> 45937 | B119: =IFERROR(__xludf.DUMMYFUNCTION("""COMPUTED_VALUE"""),"Food & Drink") -> Food & Drink | C119: =IFERROR(__xludf.DUMMYFUNCTION("""COMPUTED_VALUE"""),"Drinks") -> Drinks | D119: =IFERROR(__xludf.DUMMYFUNCTION("""COMPUTED_VALUE"""),85.0) -> 85 | F119: =IFERROR(__xludf.DUMMYFUNCTION("""COMPUTED_VALUE"""),"ชานม Koi") -> ชานม Koi
A120: =IFERROR(__xludf.DUMMYFUNCTION("""COMPUTED_VALUE"""),45937.0) -> 45937 | B120: =IFERROR(__xludf.DUMMYFUNCTION("""COMPUTED_VALUE"""),"Food & Drink") -> Food & Drink | C120: =IFERROR(__xludf.DUMMYFUNCTION("""COMPUTED_VALUE"""),"Main meals") -> Main meals | D120: =IFERROR(__xludf.DUMMYFUNCTION("""COMPUTED_VALUE"""),219.0) -> 219 | F120: =IFERROR(__xludf.DUMMYFUNCTION("""COMPUTED_VALUE"""),"Babigon") -> Babigon
A121: =IFERROR(__xludf.DUMMYFUNCTION("""COMPUTED_VALUE"""),45937.0) -> 45937 | B121: =IFERROR(__xludf.DUMMYFUNCTION("""COMPUTED_VALUE"""),"Items") -> Items | C121: =IFERROR(__xludf.DUMMYFUNCTION("""COMPUTED_VALUE"""),"Personal Items") -> Personal Items | D121: =IFERROR(__xludf.DUMMYFUNCTION("""COMPUTED_VALUE"""),250.0) -> 250 | F121: =IFERROR(__xludf.DUMMYFUNCTION("""COMPUTED_VALUE"""),"น้ำหอม kamakkamen") -> น้ำหอม kamakkamen
A122: =IFERROR(__xludf.DUMMYFUNCTION("""COMPUTED_VALUE"""),45937.0) -> 45937 | B122: =IFERROR(__xludf.DUMMYFUNCTION("""COMPUTED_VALUE"""),"Health") -> Health | C122: =IFERROR(__xludf.DUMMYFUNCTION("""COMPUTED_VALUE"""),"Others") -> Others | D122: =IFERROR(__xludf.DUMMYFUNCTION("""COMPUTED_VALUE"""),40.0) -> 40 | E122: =IFERROR(__xludf.DUMMYFUNCTION("""COMPUTED_VALUE"""),"7-Eleven") -> 7-Eleven | F122: =IFERROR(__xludf.DUMMYFUNCTION("""COMPUTED_VALUE"""),"ยาลดกรด") -> ยาลดกรด
A123: =IFERROR(__xludf.DUMMYFUNCTION("""COMPUTED_VALUE"""),45936.0) -> 45936 | B123: =IFERROR(__xludf.DUMMYFUNCTION("""COMPUTED_VALUE"""),"Food & Drink") -> Food & Drink | C123: =IFERROR(__xludf.DUMMYFUNCTION("""COMPUTED_VALUE"""),"Main meals") -> Main meals | D123: =IFERROR(__xludf.DUMMYFUNCTION("""COMPUTED_VALUE"""),169.0) -> 169 | E123: =IFERROR(__xludf.DUMMYFUNCTION("""COMPUTED_VALUE"""),"Noodle") -> Noodle
A124: =IFERROR(__xludf.DUMMYFUNCTION("""COMPUTED_VALUE"""),45936.0) -> 45936 | B124: =IFERROR(__xludf.DUMMYFUNCTION("""COMPUTED_VALUE"""),"Service") -> Service | C124: =IFERROR(__xludf.DUMMYFUNCTION("""COMPUTED_VALUE"""),"Subscription") -> Subscription | D124: =IFERROR(__xludf.DUMMYFUNCTION("""COMPUTED_VALUE"""),19.0) -> 19 | F124: =IFERROR(__xludf.DUMMYFUNCTION("""COMPUTED_VALUE"""),"Subscribe K.Earthh Evans") -> Subscribe K.Earthh Evans
A125: =IFERROR(__xludf.DUMMYFUNCTION("""COMPUTED_VALUE"""),45936.0) -> 45936 | B125: =IFERROR(__xludf.DUMMYFUNCTION("""COMPUTED_VALUE"""),"Food & Drink") -> Food & Drink | C125: =IFERROR(__xludf.DUMMYFUNCTION("""COMPUTED_VALUE"""),"Snacks") -> Snacks | D125: =IFERROR(__xludf.DUMMYFUNCTION("""COMPUTED_VALUE"""),40.0) -> 40 | F125: =IFERROR(__xludf.DUMMYFUNCTION("""COMPUTED_VALUE"""),"ลูกชิ้น") -> ลูกชิ้น
A126: =IFERROR(__xludf.DUMMYFUNCTION("""COMPUTED_VALUE"""),45936.0) -> 45936 | B126: =IFERROR(__xludf.DUMMYFUNCTION("""COMPUTED_VALUE"""),"Food & Drink") -> Food & Drink | C126: =IFERROR(__xludf.DUMMYFUNCTION("""COMPUTED_VALUE"""),"Main meals") -> Main meals | D126: =IFERROR(__xludf.DUMMYFUNCTION("""COMPUTED_VALUE"""),50.0) -> 50 | E126: =IFERROR(__xludf.DUMMYFUNCTION("""COMPUTED_VALUE"""),"Hainanese chicken rice") -> Hainanese chicken rice
A127: =IFERROR(__xludf.DUMMYFUNCTION("""COMPUTED_VALUE"""),45936.0) -> 45936 | B127: =IFERROR(__xludf.DUMMYFUNCTION("""COMPUTED_VALUE"""),"Food & Drink") -> Food & Drink | C127: =IFERROR(__xludf.DUMMYFUNCTION("""COMPUTED_VALUE"""),"Alcohol") -> Alcohol | D127: =IFERROR(__xludf.DUMMYFUNCTION("""COMPUTED_VALUE"""),62.0) -> 62 | E127: =IFERROR(__xludf.DUMMYFUNCTION("""COMPUTED_VALUE"""),"7-Eleven") -> 7-Eleven
A128: =IFERROR(__xludf.DUMMYFUNCTION("""COMPUTED_VALUE"""),45935.0) -> 45935 | B128: =IFERROR(__xludf.DUMMYFUNCTION("""COMPUTED_VALUE"""),"Food & Drink") -> Food & Drink | C128: =IFERROR(__xludf.DUMMYFUNCTION("""COMPUTED_VALUE"""),"Groceries") -> Groceries | D128: =IFERROR(__xludf.DUMMYFUNCTION("""COMPUTED_VALUE"""),60.0) -> 60 | F128: =IFERROR(__xludf.DUMMYFUNCTION("""COMPUTED_VALUE"""),"มะพร้าว") -> มะพร้าว
A129: =IFERROR(__xludf.DUMMYFUNCTION("""COMPUTED_VALUE"""),45935.0) -> 45935 | B129: =IFERROR(__xludf.DUMMYFUNCTION("""COMPUTED_VALUE"""),"Food & Drink") -> Food & Drink | C129: =IFERROR(__xludf.DUMMYFUNCTION("""COMPUTED_VALUE"""),"Main meals") -> Main meals | D129: =IFERROR(__xludf.DUMMYFUNCTION("""COMPUTED_VALUE"""),25.0) -> 25 | F129: =IFERROR(__xludf.DUMMYFUNCTION("""COMPUTED_VALUE"""),"ข้าวผัด") -> ข้าวผัด
A130: =IFERROR(__xludf.DUMMYFUNCTION("""COMPUTED_VALUE"""),45935.0) -> 45935 | B130: =IFERROR(__xludf.DUMMYFUNCTION("""COMPUTED_VALUE"""),"Food & Drink") -> Food & Drink | C130: =IFERROR(__xludf.DUMMYFUNCTION("""COMPUTED_VALUE"""),"Main meals") -> Main meals | D130: =IFERROR(__xludf.DUMMYFUNCTION("""COMPUTED_VALUE"""),284.0) -> 284 | F130: =IFERROR(__xludf.DUMMYFUNCTION("""COMPUTED_VALUE"""),"หมูกะทะ") -> หมูกะทะ
A131: =IFERROR(__xludf.DUMMYFUNCTION("""COMPUTED_VALUE"""),45934.0) -> 45934 | B131: =IFERROR(__xludf.DUMMYFUNCTION("""COMPUTED_VALUE"""),"Transportation") -> Transportation | C131: =IFERROR(__xludf.DUMMYFUNCTION("""COMPUTED_VALUE"""),"Fuel") -> Fuel | D131: =IFERROR(__xludf.DUMMYFUNCTION("""COMPUTED_VALUE"""),750.0) -> 750 | E131: =IFERROR(__xludf.DUMMYFUNCTION("""COMPUTED_VALUE"""),"Caltex") -> Caltex
A132: =IFERROR(__xludf.DUMMYFUNCTION("""COMPUTED_VALUE"""),45934.0) -> 45934 | B132: =IFERROR(__xludf.DUMMYFUNCTION("""COMPUTED_VALUE"""),"Food & Drink") -> Food & Drink | C132: =IFERROR(__xludf.DUMMYFUNCTION("""COMPUTED_VALUE"""),"Main meals") -> Main meals | D132: =IFERROR(__xludf.DUMMYFUNCTION("""COMPUTED_VALUE"""),169.0) -> 169 | F132: =IFERROR(__xludf.DUMMYFUNCTION("""COMPUTED_VALUE"""),"Taco Bell") -> Taco Bell
A133: =IFERROR(__xludf.DUMMYFUNCTION("""COMPUTED_VALUE"""),45933.0) -> 45933 | B133: =IFERROR(__xludf.DUMMYFUNCTION("""COMPUTED_VALUE"""),"Food & Drink") -> Food & Drink | C133: =IFERROR(__xludf.DUMMYFUNCTION("""COMPUTED_VALUE"""),"Drinks") -> Drinks | D133: =IFERROR(__xludf.DUMMYFUNCTION("""COMPUTED_VALUE"""),35.0) -> 35 | F133: =IFERROR(__xludf.DUMMYFUNCTION("""COMPUTED_VALUE"""),"ชานม") -> ชานม
A134: =IFERROR(__xludf.DUMMYFUNCTION("""COMPUTED_VALUE"""),45933.0) -> 45933 | B134: =IFERROR(__xludf.DUMMYFUNCTION("""COMPUTED_VALUE"""),"Food & Drink") -> Food & Drink | C134: =IFERROR(__xludf.DUMMYFUNCTION("""COMPUTED_VALUE"""),"Groceries") -> Groceries | D134: =IFERROR(__xludf.DUMMYFUNCTION("""COMPUTED_VALUE"""),41.0) -> 41 | E134: =IFERROR(__xludf.DUMMYFUNCTION("""COMPUTED_VALUE"""),"Lotus") -> Lotus | F134: =IFERROR(__xludf.DUMMYFUNCTION("""COMPUTED_VALUE"""),"หมู") -> หมู
A135: =IFERROR(__xludf.DUMMYFUNCTION("""COMPUTED_VALUE"""),45933.0) -> 45933 | B135: =IFERROR(__xludf.DUMMYFUNCTION("""COMPUTED_VALUE"""),"Food & Drink") -> Food & Drink | C135: =IFERROR(__xludf.DUMMYFUNCTION("""COMPUTED_VALUE"""),"Snacks") -> Snacks | D135: =IFERROR(__xludf.DUMMYFUNCTION("""COMPUTED_VALUE"""),39.0) -> 39 | E135: =IFERROR(__xludf.DUMMYFUNCTION("""COMPUTED_VALUE"""),"Lotus") -> Lotus | F135: =IFERROR(__xludf.DUMMYFUNCTION("""COMPUTED_VALUE"""),"ขนมปัง") -> ขนมปัง
A136: =IFERROR(__xludf.DUMMYFUNCTION("""COMPUTED_VALUE"""),45933.0) -> 45933 | B136: =IFERROR(__xludf.DUMMYFUNCTION("""COMPUTED_VALUE"""),"Food & Drink") -> Food & Drink | C136: =IFERROR(__xludf.DUMMYFUNCTION("""COMPUTED_VALUE"""),"Snacks") -> Snacks | D136: =IFERROR(__xludf.DUMMYFUNCTION("""COMPUTED_VALUE"""),66.0) -> 66 | E136: =IFERROR(__xludf.DUMMYFUNCTION("""COMPUTED_VALUE"""),"7-Eleven") -> 7-Eleven
A137: =IFERROR(__xludf.DUMMYFUNCTION("""COMPUTED_VALUE"""),45933.0) -> 45933 | B137: =IFERROR(__xludf.DUMMYFUNCTION("""COMPUTED_VALUE"""),"Transportation") -> Transportation | C137: =IFERROR(__xludf.DUMMYFUNCTION("""COMPUTED_VALUE"""),"Maintenance") -> Maintenance | D137: =IFERROR(__xludf.DUMMYFUNCTION("""COMPUTED_VALUE"""),1456.0) -> 1456 | E137: =IFERROR(__xludf.DUMMYFUNCTION("""COMPUTED_VALUE"""),"Auto 1") -> Auto 1 | F137: =IFERROR(__xludf.DUMMYFUNCTION("""COMPUTED_VALUE"""),"ผ่อนยางรถ 6/10") -> ผ่อนยางรถ 6/10
A138: =IFERROR(__xludf.DUMMYFUNCTION("""COMPUTED_VALUE"""),45932.0) -> 45932 | B138: =IFERROR(__xludf.DUMMYFUNCTION("""COMPUTED_VALUE"""),"Food & Drink") -> Food & Drink | C138: =IFERROR(__xludf.DUMMYFUNCTION("""COMPUTED_VALUE"""),"Main meals") -> Main meals | D138: =IFERROR(__xludf.DUMMYFUNCTION("""COMPUTED_VALUE"""),59.0) -> 59 | E138: =IFERROR(__xludf.DUMMYFUNCTION("""COMPUTED_VALUE"""),"KFC") -> KFC
A139: =IFERROR(__xludf.DUMMYFUNCTION("""COMPUTED_VALUE"""),45931.0) -> 45931 | B139: =IFERROR(__xludf.DUMMYFUNCTION("""COMPUTED_VALUE"""),"Food & Drink") -> Food & Drink | C139: =IFERROR(__xludf.DUMMYFUNCTION("""COMPUTED_VALUE"""),"Snacks") -> Snacks | D139: =IFERROR(__xludf.DUMMYFUNCTION("""COMPUTED_VALUE"""),118.0) -> 118 | E139: =IFERROR(__xludf.DUMMYFUNCTION("""COMPUTED_VALUE"""),"7-Eleven") -> 7-Eleven

Sheet Credit Installment
A1: ID | B1: Start Date | C1: Card | D1: Item | E1: Amount | F1: Installments | G1: Paid Months | H1: Monthly Pay | I1: Remaining | J1: End Date | K1: Note
A2: =IF(B2<>"", IFERROR(A1+1, 1),"") -> 1 | B2: 45780 | C2: KTC Bangchak | D2: ยาง BS_Turanza_6 (53,200km) | E2: 14560 | F2: 10 | G2: 10 | H2: =E2/F2 -> 1456 | I2: =E2-(G2*H2) -> 0 | J2: =EDATE(B2,F2-1) -> 46056 | K2: จ่ายครั้งที่ 10 - 09/02/2026
A3: =IF(B3<>"", IFERROR(A2+1, 1),"") -> 2 | B3: 45870 | C3: TTB So Smart | D3: Googl One AI | E3: 7500 | F3: 3 | G3: 3 | H3: =E3/F3 -> 2500 | I3: =E3-(G3*H3) -> 0 | J3: =EDATE(B3,F3-1) -> 45931 | K3: จ่ายครั้งที่ 3 - 02/10/2025
A4: =IF(B4<>"", IFERROR(A3+1, 1),"") -> 3 | B4: 46062 | C4: KTC Bangchak | D4: แว่นตา Owndays | E4: 15560 | F4: 4 | G4: 4 | H4: =E4/F4 -> 3890 | I4: =E4-(G4*H4) -> 0 | J4: =EDATE(B4,F4-1) -> 46151 | K4: จ่ายครั้งที่ 4 - 07/05/2026
A5: =IF(B5<>"", IFERROR(A4+1, 1),"") -> 4 | B5: 46056 | C5: TTB So Smart | D5: IPhone 17 Pro | E5: 38800 | F5: 10 | G5: 4 | H5: =E5/F5 -> 3880 | I5: =E5-(G5*H5) -> 23280 | J5: =EDATE(B5,F5-1) -> 46329 | K5: จ่ายครั้งที่ 4 - 01/06/2026
A6: =IF(B6<>"", IFERROR(A5+1, 1),"") -> 5 | B6: 46145 | C6: UOB One | D6: ช่วงล่าง Mu-X ที Auto 1 | E6: 24725.25 | F6: 10 | G6: 1 | H6: =E6/F6 -> 2472.525 | I6: =E6-(G6*H6) -> 22252.725 | J6: =EDATE(B6,F6-1) -> 46421 | K6: จ่ายครั้งที่ 1 - 18/05/2026
A7: =IF(B7<>"", IFERROR(A6+1, 1),"")
A8: =IF(B8<>"", IFERROR(A7+1, 1),"")
A9: =IF(B9<>"", IFERROR(A8+1, 1),"")
A10: =IF(B10<>"", IFERROR(A9+1, 1),"")
A11: =IF(B11<>"", IFERROR(A10+1, 1),"")
A12: =IF(B12<>"", IFERROR(A11+1, 1),"")
A13: =IF(B13<>"", IFERROR(A12+1, 1),"")
A14: =IF(B14<>"", IFERROR(A13+1, 1),"")
A15: =IF(B15<>"", IFERROR(A14+1, 1),"")
A16: =IF(B16<>"", IFERROR(A15+1, 1),"")
A17: =IF(B17<>"", IFERROR(A16+1, 1),"")
A18: =IF(B18<>"", IFERROR(A17+1, 1),"")
... A120: =IF(B120<>"", IFERROR(A119+1, 1),"")

Sheet Monthly Plan
A1: กิน | B1: 8400 | C1: 8400 | D1: 8400 | E1: 8400 | F1: Income | G1: หมายเหตุ
F2: =sum(26000+10000+4950+2657+1600+6332)-(2562.14+689-657)-125-1026.64 -> 47793.22
A3: ค่าของเข้าห้อง/บ้าน mbk | B3: 250 | C3: 250 | D3: 250 | E3: 250
G4: หัก Tax 900 -> 1,000
A5: ค่าน้ำมัน(เดินทาง) mbk | B5: 3000 | C5: 3000 | D5: 3000 | E5: 3000 | G5: เป้าหมายเงินฉุกเฉิน 25,000*6=150,000
A7: น้ำไฟ mbk | B7: 1500 | C7: 1500 | D7: 1500 | E7: 1500
A9: ค่ารถ nombk | B9: 8251 | C9: 8251 | D9: 8251 | E9: 8251
A11: skincare mbk | B11: 700 | C11: 700 | D11: 700 | E11: 700
A13: ค่าเน็ต AIS | B13: 1100 | C13: 1100 | D13: 1100 | E13: 1100
A14: YT Premium | B14: 50 | C14: 50 | D14: 50 | E14: 50
A15: SUM | B15: =SUM(B1:B14) -> 23251 | C15: =SUM(C1:C14) -> 23251 | D15: =SUM(D1:D14) -> 23251 | E15: =SUM(E1:E14) -> 23251
B17: Current case | C17: July | D17: Nov | E17: ปี 2027
B18: =SUM(F2-B15) -> 24542.22 | C18: =SUM(F2-C15) -> 24542.22 | D18: =SUM(F2-D15) -> 24542.22 | E18: =SUM(F2-E15) -> 24542.22
A20: เงินที่เหลือจากข้างบน | B20: =B18 -> 24542.22 | C20: =C18 -> 24542.22 | D20: =D18 -> 24542.22 | E20: =E18 -> 24542.22 | G20: ของเข้าบ้านเดี๋ยวใส่เพิ่มเดือน 4/2026
A21: free เอาไปใส่ได้หมด | B21: =SUM(B22:B32)-B20 -> 0 | C21: =SUM(C22:C32)-C20 -> 0 | D21: =SUM(D22:D32)-D20 -> 0 | E21: =SUM(E22:E32)-E20 -> 0
A22: ผ่อน IP 17Pro | B22: 3880 | C22: 3880 | H22: เช่นเก็บ 3,000 แต่เงินถึง 30k แล้วให้หักไป 2k ไปจ่าย กยศ
A23: เที่ยว, กิน kept | B23: 7112.22 | C23: 5000 | D23: 2000 | E23: 4000
A24: ภาษี kept | B24: 800 | C24: 500 | D24: 500 | E24: 600
A25: เงินฉุกเฉิน kept | B25: 5000 | C25: 10412.22 | D25: 17292.22 | E25: 15192.22
A26: กยศ dime | B26: 3000 | C26: 0 | D26: 0 | E26: 0 | G26: เดือนกรกฎาเก็บไว้ใน kept จนกว่าจะครบยอดผ่อนปี 2670
A27: รถยนต์ kept | B27: 2000 | C27: 2000 | D27: 2000 | E27: 2000
A28: รอเทรดหุ้น dime | B28: 0 | E28: 0
A29: Gemini kept | B29: 750 | C29: 750 | D29: 750 | E29: 750
A30: ประกันรวม kept | B30: 2000 | C30: 2000 | D30: 2000 | E30: 2000
A33: รวม | B33: =SUM(B22:B32) -> 24542.22 | C33: =SUM(C22:C32) -> 24542.22 | D33: =SUM(D22:D32) -> 24542.22 | E33: =SUM(E22:E32) -> 24542.22
G34: ถ้าเงินเก็บ > 100k เอามาผ่อน กยศ
A37: ยอด OT | B37: ฉุกเฉิน 25% | C37: ไว้เทรด 30% | D37: ภาษี 15% | E37: อะไรก็ได้ 30%
A38: 1000 | B38: =A38*25% -> 250 | C38: =A38*30% -> 300 | D38: =A38*15% -> 150 | E38: =A38*30% -> 300
A44: แผน Bonus ปี 2027
A45: รถ
A46: เติม us stock | C46: ดูว่าเหลืออีกเท่าไหร่ก็หักออกไปได้เลย
A47: เงินฉุกเฉิน | B47: 20000
A48: เปย์ตัวเอง | B48: 30000 | C48: ถ้าเงิน travel ไม่ถึง 30k ก็เติมเข้าไป
A49: ซื้อของเข้าบ้าน | B49: 16000 | C49: รวมจ่ายค่าส่วนกลางหมู่บ้าน
A50: กยศ | B50: 30000 | C50: รอจ่ายตอนยอดของปีขึ้นมา
A51: กยศ จ่ายเลย | B51: 9000
A52: ซื้อของใหญ่ | B52: 15000
A54: รวม | B54: =SUM(B45:B52) -> 120000
A55: Bonus | B55: 120000
A56: คงเหลือ | B56: =B55-B54 -> 0 | C56: ให้ย่า
A61: ไอเดียทำเว็บ | B61: บัตรเครดิตจะมีหน้ากรอกแยกและ ให้ใส่เงินรวมก่อน และให้แยกออกเป็น transaction ของแต่ละอย่างที่ซื้อ

Sheet Overall
A1: Summary
A2: List | B2: 2024 | C2: =C19 -> 95572.28 | D2: 2026 | E2: 2027 | F2: 2028 | G2: 2029 | H2: 2030
A3: Contigency reserve | B3: =B19 -> 83753.74 | C3: =C19 -> 95572.28 | D3: =D19 -> 109380.12
A4: Hold for pay | B4: =B34 -> 121535.29 | C4: =C34 -> 129744.98 | D4: =D34 -> 70404.37
A7: Sum only KEPT | B7: =B14+B34 -> 193968.77 | C7: =C14 + C34 -> 219375.57 | D7: =D14 + D34 -> 168784.49
A8: All Networth | B8: =SUM(B3:B5) -> 205289.03 | C8: =SUM(C3:C5) -> 225317.26 | D8: =SUM(D3:D5) -> 179784.49
A11: Contigency Reserve
A12: Contigency | B12: 2024(50k) | C12: 2025 (80k) | D12: 2026 (100k) | E12: 2027 (120k) | F12: 2028 (140k) | G12: 2029 (160k) | H12: 2030 (200K)
A13: Make by kbank | B13: 262.27 | C13: 1000 | D13: =SUM(C13, SUMIF('Contigency Reserve'!C:C, "mbk_2026", 'Contigency Reserve'!D:D) - SUMIF('Contigency Reserve'!C:C, "mbk_2026", 'Contigency Reserve'!E:E) + SUMIF('Contigency Reserve'!C:C, "mbk_2026", 'Contigency Reserve'!F:F)) -> 1000
A14: Kept by krungsri | B14: 72433.48 | C14: 89630.59 | D14: =SUM(C14, SUMIF('Contigency Reserve'!C:C, "kept_2026", 'Contigency Reserve'!D:D) - SUMIF('Contigency Reserve'!C:C, "kept_2026", 'Contigency Reserve'!E:E) + SUMIF('Contigency Reserve'!C:C, "kept_2026", 'Contigency Reserve'!F:F)) -> 98380.12
A15: Bualuang bank (balance) | B15: 1057.99 | C15: =SUM(B15, SUMIF('Contigency Reserve'!C:D, "blb_2025", 'Contigency Reserve'!D:D) - SUMIF('Contigency Reserve'!C:D, "blb_2025", 'Contigency Reserve'!E:E) + SUMIF('Contigency Reserve'!C:D, "blb_2025", 'Contigency Reserve'!F:F)) -> 1000 | D15: =SUM(C15, SUMIF('Contigency Reserve'!C:C, "blb_2026", 'Contigency Reserve'!D:D) - SUMIF('Contigency Reserve'!C:C, "blb_2026", 'Contigency Reserve'!E:E) + SUMIF('Contigency Reserve'!C:C, "blb_2026", 'Contigency Reserve'!F:F)) -> 0
A16: Dime | B16: 10000 | C16: 3941.69 | D16: =SUM(C16, SUMIF('Contigency Reserve'!C:C, "dime_2026", 'Contigency Reserve'!D:D) - SUMIF('Contigency Reserve'!C:C, "dime_2026", 'Contigency Reserve'!E:E) + SUMIF('Contigency Reserve'!C:C, "dime_2026", 'Contigency Reserve'!F:F)) -> 10000
A19: Sum | B19: =SUM(B13:B18) -> 83753.74 | C19: =SUM(C13:C18) -> 95572.28 | D19: =SUM(D13:D18) -> 109380.12
A22: Hold for pay
A23: Hold for pay (kept) | B23: 2024 | C23: 2025 | D23: 2026 | E23: 2027 | F23: 2028 | G23: 2029 | H23: 2030
A24: Tax | B24: 22260.01 | C24: 17340.06 | D24: =SUM(C24,SUMIF('Hold for pay'!C:C, "tax_2026", 'Hold for pay'!D:D)-SUMIF('Hold for pay'!C:C, "tax_2026", 'Hold for pay'!E:E)) -> 13008.06
A25: Studentloan | B25: 6000 | C25: 8000 | D25: =SUM(C25,SUMIF('Hold for pay'!C:C, "sl_2026", 'Hold for pay'!D:D)-SUMIF('Hold for pay'!C:C, "sl_2026", 'Hold for pay'!E:E)) -> 8000 | I25: ปิดหนี้ กรอ เดือน 1 ปี 2028
A26: Travel | B26: 32084.6 | C26: 30736.87 | D26: =SUM(C26,SUMIF('Hold for pay'!C:C, "travel_2026", 'Hold for pay'!D:D)-SUMIF('Hold for pay'!C:C, "travel_2026", 'Hold for pay'!E:E)) -> 11364.81
A27: Car | B27: 35665.17 | C27: 24601.97 | D27: =SUM(C27,SUMIF('Hold for pay'!C:C, "car_2026", 'Hold for pay'!D:D)-SUMIF('Hold for pay'!C:C, "car_2026", 'Hold for pay'!E:E)) -> 14789.32
A28: Buy big thing | B28: 25525.51 | C28: 43068.08 | D28: =SUM(C28,SUMIF('Hold for pay'!C:C, "bigthin_2026", 'Hold for pay'!D:D)-SUMIF('Hold for pay'!C:C, "bigthin_2026", 'Hold for pay'!E:E)) -> 3494.18 | I28: เดือน august เอาเงินนี้ไปผ่อน
A29: Learn | B29: 0 | C29: 284 | D29: =SUM(C29,SUMIF('Hold for pay'!C:C, "learn_2026", 'Hold for pay'!D:D)-SUMIF('Hold for pay'!C:C, "learn_2026", 'Hold for pay'!E:E)) -> 284
A30: Insure | B30: 0 | C30: 1964 | D30: =SUM(C30,SUMIF('Hold for pay'!C:C, "insure_2026", 'Hold for pay'!D:D)-SUMIF('Hold for pay'!C:C, "insure_2026", 'Hold for pay'!E:E)) -> 11964
A31: Subscribe | B31: 0 | C31: 3750 | D31: =SUM(C31,SUMIF('Hold for pay'!C:C, "sub_2026", 'Hold for pay'!D:D)-SUMIF('Hold for pay'!C:C, "sub_2026", 'Hold for pay'!E:E)) -> 7500
A34: Sum | B34: =SUM(B24:B33) -> 121535.29 | C34: =SUM(C24:C33) -> 129744.98 | D34: =SUM(D24:D33) -> 70404.37

Sheet Hold for pay
A1: List | B1: Date | C1: To | D1: Deposit | E1: Withdraw | G1: Card
A6: case, phone gear | B6: 46186 | C6: travel_2026 | F6: 354 | G6: uob
A7: ประกันรถยนต์ | B7: 46187 | C7: car_2026 | E7: 12808
A8: pepsi can, milk, yogurt | B8: 46183 | C8: travel_2026 | E8: 429 | F8: 429 | G8: uob
A9: wheyprotein, honey, ไขควง | B9: 46183 | C9: travel_2026 | F9: 792 | G9: ttb
A10: Davinci course for video editing. | B10: 46179 | C10: travel_2026 | E10: 509 | F10: 509 | G10: uob
A11: case ip17pro, whey protein, doll, fragrance | B11: 46178 | C11: travel_2026 | F11: 1379 | G11: ttb
A12: แคปหมู, film ip, pepsi, phone strap | B12: 46176 | C12: travel_2026 | E12: 1074.91 | F12: 1074.91 | G12: uob
A13: ยาสีฟัน, case ip17pro, phone holder, shokubutsu | B13: 46176 | C13: travel_2026 | E13: 1153 | F13: 1153 | G13: uob
A14: พักรอจ่ายค่าซ่อมรถแม่(จ่าย) | B14: 46176 | C14: travel_2026 | D14: 2000 | E14: 2000
A15: ภาษี | B15: 46176 | C15: tax_2026 | D15: 427
A16: กาแฟ | B16: 46176 | C16: travel_2026 | E16: 145
A17: ข้าวเที่ยงกับไอเก๋า | B17: 46176 | C17: travel_2026 | E17: 225
A18: เบียร์ลาดพร้าว | B18: 46176 | C18: travel_2026 | E18: 557
A19: จ่ายภาษี 3/3 | B19: 46174 | C19: tax_2026 | E19: 4388
A20: ภาษี | B20: 46168 | C20: tax_2026 | D20: 570
A21: รอจ่ายของเข้าบ้าน | B21: 46168 | C21: travel_2026 | D21: 2222 | F21: 2222 ถึงวันค่อยหัก | G21: ttb
A22: health insure | B22: 46167 | C22: insure_2026 | D22: 2000
A23: google one ai | B23: 46167 | C23: sub_2026 | D23: 750
A24: รถยนต์ | B24: 46167 | C24: car_2026 | D24: 2000
A25: ภาษีี | B25: 46167 | C25: tax_2026 | D25: 800
A26: กินเที่ยว | B26: 46167 | C26: travel_2026 | D26: 7112.22
A27: ซื้อของฝากปั๊มเท่ง | B27: 46163 | C27: travel_2026 | E27: 389
A28: ค่าเที่ี่ยว | B28: 46164 | C28: travel_2026 | E28: 1000
A29: เติมน้ำมัันเพชรบุรี | B29: 46163 | C29: travel_2026 | E29: 1000
A30: เติมน้ำมันละแม ชุมพร | B30: 46162 | C30: travel_2026 | E30: 1000
A31: เติมน้ำมันที่สุราษ | B31: 46160 | C31: travel_2026 | E31: 1000
A32: ค่าน้ำมันขากลับ | B32: 46162 | C32: travel_2026 | E32: 1000
A33: Old spice & Ulanzi SC-02, ตาข่าย Mu-X | B33: 46163 | C33: travel_2026 | F33: 2232 มียกเลิกไป 351 = 1881 | G33: ttb
A34: ค่ากิินเที่ยว | B34: 46163 | C34: travel_2026 | E34: 1000
A35: ค่าไข่เค็มของฝาก | B35: 46162 | C35: travel_2026 | E35: 300
A36: ค่าเบียร์ร้านพี่มน | B36: 46162 | C36: travel_2026 | E36: 370
A37: ค่าเหล้าวิถี On Tap | B37: 46161 | C37: travel_2026 | E37: 770
A38: ค่าห้องพัก | B38: 46161 | C38: travel_2026 | E38: 420
A39: จ่ายค่าซ่อมรถแม่เพิ่ม | B39: 46160 | C39: travel_2026 | E39: =236.89+110 -> 346.89
A40: ค่าเน็ต ais | B40: 46160 | C40: travel_2026 | E40: 900
A41: ค่ากินเที่ยว | B41: 46159 | C41: travel_2026 | E41: 2000
A42: ค่าแคมป์วังปริง+เข้า อทย | B42: 46158 | C42: travel_2026 | E42: 250
A43: ค่าที่ี่พัก smile resort ทุ่งสง | B43: 46153 | C43: travel_2026 | E43: 590
A44: น้ำมันก่อนเข้าทุ่งสง | B44: 46153 | C44: travel_2026 | E44: 1000
A45: กินเบียร์ bloom urt | B45: 46153 | C45: travel_2026 | E45: 2014
A46: craftbeer วิถี On Tap | B46: 46150 | C46: travel_2026 | E46: =980+520 -> 1500
A47: ค่าแว่น 4/4 | B47: 46149 | C47: bigthin_2026 | E47: 3890
A48: ที่พัก me home surat | B48: 46150 | C48: travel_2026 | E48: 690
A49: ถุงซักผ้ามีซิ๊ป | B49: 46145 | C49: travel_2026 | E49: 67.08
A50: เปลี่่ยนกันสาด Mu-X | B50: 46144 | C50: bigthin_2026 | E50: 1400
A51: จ่ายภาษี 2/3 | B51: 46144 | C51: tax_2026 | E51: 4388
A52: ซื้อของรอไปเที่ยว | B52: 46141 | C52: travel_2026 | E52: 1942
A53: google one ai | B53: 46139 | C53: sub_2026 | D53: 750
A54: รอเที่ยว | B54: 46139 | C54: travel_2026 | D54: 2112.22
A55: health insure | B55: 46139 | C55: insure_2026 | D55: 2000
A56: รถยนต์ | B56: 46139 | C56: car_2026 | D56: 2000
A57: ภาษี | B57: 46139 | C57: tax_2026 | D57: 800
A58: ค่าเที่ยวจันทร์ | B58: 46138 | C58: travel_2026 | E58: 1174
A59: เลี้ยงข้าวที่บ้าน | B59: 46131 | C59: bigthin_2026 | E59: 2058
A60: ให้ย่า | B60: 46128 | C60: bigthin_2026 | E60: 1000
A61: อาหารหมาและของกินเล่น | B61: 46127 | C61: bigthin_2026 | E61: 425.25
A62: หมวยช่วยค่า lotus kalasin | B62: 46127 | C62: bigthin_2026 | D62: 500
A63: น้ำหอม, ผ้าเช็ดในรถ | B63: 46126 | C63: bigthin_2026 | E63: 359
A64: ไมค์, cleansing, ถุงใส่ vitamin | B64: 46126 | C64: bigthin_2026 | E64: 1778
A65: ซื้อของ lotus kalasin | B65: 46125 | C65: bigthin_2026 | E65: 1433
A66: ใส่บาตรพระหนุน | B66: 46116 | C66: travel_2026 | E66: 300
A67: ค่าแว่่น 3/4 | B67: 46122 | C67: bigthin_2026 | E67: 3890
A68: จ่าย tax 1/3 | B68: 46113 | C68: tax_2026 | E68: 4388
A69: Lofree flow lite | B69: 46115 | C69: bigthin_2026 | E69: 2663
A70: ภาษี | B70: 46113 | C70: tax_2026 | D70: 210
A71: ภาษี | B71: 46106 | C71: tax_2026 | D71: 1200
A72: รอเที่ยว | B72: 46106 | C72: travel_2026 | D72: 706.86
A73: google one ai | B73: 46106 | C73: sub_2026 | D73: 750
A74: health insure | B74: 46106 | C74: insure_2026 | D74: 2000
A75: รถยนต์ | B75: 46106 | C75: car_2026 | D75: 2000
A76: มัดจำค่าเที่ยว | B76: 46104 | C76: travel_2026 | E76: 2700
A77: รองเท้าวิ่ง | B77: 46103 | C77: bigthin_2026 | E77: 2160
A78: ค่าแบตรถยนต์ | B78: 46093 | C78: car_2026 | E78: 3100
A79: เช็คระยะ 70,000km | B79: 46093 | C79: car_2026 | E79: 1492.65
A80: ซื้อ decathlon | B80: 46096 | C80: travel_2026 | E80: 740
A81: ซื้อของ shopee | B81: 46096 | C81: travel_2026 | E81: 843
A82: prime video | B82: 46094 | C82: travel_2026 | E82: 149
A83: เบียร์ ลาดพร้าว | B83: 46093 | C83: travel_2026 | E83: 1100
A84: ค่าแว่่น 2/4 | B84: 46090 | C84: bigthin_2026 | E84: 3890
A85: กินเบียร์ | B85: 46089 | C85: travel_2026 | E85: =1500+832 -> 2332
A86: ภาษี | B86: 46086 | C86: tax_2026 | D86: 900
A87: จ่าย IP 17 Pro | B87: 46083 | C87: bigthin_2026 | E87: 3880
A88: บัตร ttb ss ขาด | B88: 46083 | C88: bigthin_2026 | E88: 1197
A89: smarttag, mcsafe, miror mcsafe | B89: 46081 | C89: travel_2026 | E89: 1099.2
A90: health insure | B90: 46078 | C90: insure_2026 | D90: 2000
A91: google one ai | B91: 46078 | C91: sub_2026 | D91: 750
A92: รถยนต์ | B92: 46078 | C92: car_2026 | D92: 2000
A93: ภาษี | B93: 46078 | C93: tax_2026 | D93: 1250
A94: รอจ่าย IP 17 Pro | B94: 46078 | C94: bigthin_2026 | D94: 3880
A95: รอเที่ยว | B95: 46078 | C95: travel_2026 | D95: 656.86
A96: bento ข้าวเที่ยง | B96: 46077 | C96: travel_2026 | E96: 199
A97: ซื้อของ Lotus | B97: 46075 | C97: travel_2026 | E97: 667
A98: ภาษี | B98: 46070 | C98: tax_2026 | D98: 143
A99: เบียร์เพื่อนจิ๊-ไทเกอร์ | B99: 46073 | C99: travel_2026 | E99: 640
A100: case ipad | B100: 46067 | C100: bigthin_2026 | E100: 188.99
A101: สมัคร Prime | B101: 46065 | C101: bigthin_2026 | E101: 149
A102: ภาษี | B102: 46063 | C102: tax_2026 | D102: 712
A103: หมวยโอนค่าแว่น | B103: 46061 | C103: bigthin_2026 | D103: 5840
A104: ค่าแว่น 1/4 | B104: 46062 | C104: bigthin_2026 | E104: 3890
...

Sheet Contigency Reserve
A1: List | B1: Date | C1: To | D1: Deposit | E1: Withdraw | F1: Interest
A6: เติมหุ้น | B6: 46185 | C6: kept_2026 | E6: 10000
A7: ฝากเงิน | B7: 46174 | C7: kept_2026 | D7: 1508.6
A8: ดอกเบี้ย kept | B8: 46170 | C8: kept_2026 | F8: 248.91
A9: ttb ss cashback | B9: 46167 | C9: kept_2026 | D9: 72.96
A10: ฝาก kept | B10: 46167 | C10: kept_2026 | D10: 5000
A11: คืนเงินเข้า kept | B11: 46141 | C11: kept_2026 | D11: 554
A12: ttb ss cashback | B12: 46141 | C12: kept_2026 | D12: 67.43
A13: ฝาก kept | B13: 46141 | C13: kept_2026 | D13: 375.06
A14: ดอกเบี้ย kept | B14: 46140 | C14: kept_2026 | F14: 261.53
A15: เอาไปจ่าย UOB เพราะจ่ายยอดผิดเดือน | B15: 46131 | C15: kept_2026 | E15: =2160+103.5 -> 2263.5
A16: เอาเงินกลับจาก crypto | B16: 46131 | C16: kept_2026 | D16: 20174.27
A17: ซื้อ crypto | B17: 46114 | C17: kept_2026 | E17: 15000
A18: เงินเหลืือจาก ttb sosmart | B18: 46111 | C18: kept_2026 | D18: 2242
A19: ดอกเบี้ย kept | B19: 46109 | C19: kept_2026 | F19: 279.63
A20: to kept | B20: 46111 | C20: kept_2026 | D20: 3583.57
A21: swap dime | B21: 46111 | C21: dime_2026 | E21: 3583.57
A22: เบียร์ @บางพระ | B22: 46109 | C22: dime_2026 | E22: 868.5
A23: รร hobb-in บางพระ | B23: 46109 | C23: dime_2026 | E23: 500
A24: ฝาก dime | B24: 46108 | C24: dime_2026 | D24: 2853
A25: ฝาก kept | B25: 46106 | C25: kept_2026 | D25: 11005.36
A26: ttb ss cashback | B26: 46104 | C26: kept_2026 | D26: 124.87
A27: ซื้อ crypto | B27: 46104 | C27: kept_2026 | E27: 15000
A28: ซองงานแต่งพี่อัด | B28: 46088 | C28: mbk_2026 | E28: 500
A29: TTB ss cashback | B29: 46083 | C29: kept_2026 | D29: 242.65
A30: ดอกเบี้ย kept | B30: 46081 | C30: kept_2026 | F30: 323.67
A31: ฝาก kept | B31: 46078 | C31: kept_2026 | D31: 700
A32: ฝาก dime | B32: 46078 | C32: dime_2026 | D32: 1088.36
A33: ดอกเบี้ย kept | B33: 46050 | C33: kept_2026 | F33: 315.89
A34: cashback so smart and เงินเหลือ | B34: 46047 | C34: kept_2026 | D34: 232.63
A35: ฝาก kept | B35: 46045 | C35: kept_2026 | D35: 3000
A36: ฝาก dime | B36: 46045 | C36: dime_2026 | D36: 1200
A37: ฝาก kept | B37: 46045 | C37: kept_2026 | D37: 700
A38: ฝาก dime | B38: 46045 | C38: dime_2026 | D38: 5600
A39: ฝาก mbk | B39: 46045 | C39: mbk_2026 | D39: 500
A40: ฝาก | B40: 46028 | C40: dime_2026 | D40: 269.02
A41: ย้ายออก | B41: 46024 | C41: blb_2026 | E41: 1000
A42: เอาเงิินไปเติม port | B42: 46017 | C42: dime_2025 | E42: 7059.63
A43: ดอกเบีีี้ย kept | B43: 46019 | C43: kept_2025 | F43: =177.87+0.09 -> 177.96
A44: ฝาก kept | B44: 46016 | C44: kept_2025 | D44: 25000
A45: ฝาก kept | B45: 46016 | C45: kept_2025 | D45: 1000
A46: TTB ss cashback | B46: 46014 | C46: kept_2025 | D46: 30.05
A47: ดอกเบี้ย mbk | B47: 46013 | C47: kept_2025 | D47: 223.36
A48: ดอกเบี้ย kept | B48: 45989 | C48: kept_2025 | D48: 162.03
A49: เสื้อกันหนาว decathlon, ขวดน้ำนิ่ม, ถุงเท้า | B49: 45992 | C49: kept_2025 | E49: 1079
A50: ฝาก kept | B50: 45986 | C50: kept_2025 | D50: 700
A51: ttb ss cashback | B51: 45986 | C51: kept_2025 | D51: 62.07
A52: ดอกเบี้ย kept | B52: 45958 | C52: kept_2025 | F52: 184.02
A53: ttb ss cashback | B53: 45954 | C53: kept_2025 | D53: 64.69
A54: แลกเงินรอซื้อหุ้น | B54: 45954 | C54: kept_2025 | E54: 2000
A55: ฝาก kept | B55: 45954 | C55: kept_2025 | D55: 2000
A56: ประกันสุขภาพ จ่ายส่วนต่างเพื่ออนาคต | B56: 45950 | C56: kept_2025 | E56: 10000
A57: ดอกเบี้ย kept | B57: 45928 | C57: kept_2025 | F57: 174.6
A58: TTB ss cashback | B58: 45924 | C58: kept_2025 | D58: 82.62
A59: ดอกเบี้ย kept | B59: 45897 | C59: kept_2025 | F59: 171.03
A60: ฝาก dime | B60: 45893 | C60: dime_2025 | D60: 10000
A61: ttb ss cashback | B61: 45893 | C61: kept_2025 | D61: 54.43
A62: เอาเงิิินออกจากหุ้นมาไว้ | B62: 45893 | C62: kept_2025 | D62: =26989.07-10000-10000 -> 6989.07
A63: UOB Cashback | B63: 45885 | C63: kept_2025 | D63: 47.96
A64: ถอนไปแลกเงินรอเทรด 2 เดือน Nov ต้องฝากเงินคืนครบ | B64: 45882 | C64: kept_2025 | E64: 10000
A65: จ่ายภาษีย้อนหลัง | B65: 45877 | C65: kept_2025 | E65: 1889
A66: ดอกเบี้ย | B66: 45866 | C66: kept_2025 | F66: 175.81
A67: ฝากคืนเดือน Aug | B67: 45863 | C67: kept_2025 | D67: 5573.36
A68: TTB ss cashback | B68: 45862 | C68: kept_2025 | D68: 17.55
A69: เช่ากล้อง ​DJI | B69: 45862 | C69: kept_2025 | D69: 500
A70: ดอกเบี้ยกรุงเทพ, กรุงไทย | B70: 45839 | C70: kept_2025 | F70: =0.09+1.98 -> 2.07
A71: ดอกเบี้ย | B71: 45836 | C71: kept_2025 | F71: 194.69
A72: ฝากคืืนเดือน July | B72: 45833 | C72: kept_2025 | D72: 5020
A73: ttb ss cashback | B73: 45831 | C73: kept_2025 | D73: 56.75
A74: ดอกเบี้ย mbk | B74: 45828 | C74: kept_2025 | F74: 180.03
A75: ดอกเบี้ย kept | B75: 45805 | C75: kept_2025 | F75: 196.23
A76: ttb ss cashback เดือนก่อนและของปั๊ม 54 บาท | B76: 45800 | C76: kept_2025 | D76: =37.2+54 -> 91.2
A77: เช่ากล้อง ​DJI | B77: 45800 | C77: kept_2025 | D77: 500
A78: ฝากคืน June | B78: 45800 | C78: kept_2025 | D78: 5089
A79: ถอนไปแลกเงินรอเทรด 2 เดือน Sept ต้องฝากเงินคืนครบ | B79: 45798 | C79: kept_2025 | E79: 10000
A80: เงินเหลือจากไหนไม่รู้ | B80: 45792 | C80: kept_2025 | D80: 582.9
A81: UOB Cashback | B81: 45792 | C81: kept_2025 | D81: =77.67+19 -> 96.67
A82: เช่ากล้อง ​DJI | B82: 45784 | C82: kept_2025 | D82: 500
A83: ถอนไปแลกเงินรอเทรด 2 เดือน July ต้องฝากเงินคืนครบ | B83: 45779 | C83: kept_2025 | E83: 10000
A84: ดอกเบี้ย kept | B84: 45775 | C84: kept_2025 | F84: 217.6
A85: ฝาก kept | B85: 45772 | C85: kept_2025 | D85: 800
A86: TTB ss cashback, เงินค้าง (57.05 + 36) + 0.67 | B86: 45770 | C86: kept_2025 | D86: =57.05+36+0.67 -> 93.72
A87: ดอกเบี้ย kept | B87: 45744 | C87: kept_2025 | F87: 202.81
A88: เก็บเงิน | B88: 45741 | C88: kept_2025 | D88: 750
A89: ฝาก kept | B89: 45741 | C89: kept_2025 | D89: 305.5
A90: ttb ss cashback | B90: 45740 | C90: kept_2025 | D90: 328.85
A91: ttb ss cashback | B91: 45720 | C91: kept_2025 | D91: 17.75
A92: ดอกเบี้ย kept | B92: 45716 | C92: kept_2025 | F92: 279.26
A93: เก็บเงิน | B93: 45713 | C93: kept_2025 | D93: 1000
A94: UOB Cashback | B94: 45700 | C94: kept_2025 | D94: 263.96
A95: เช่ากล้อง ​DJI | B95: 45700 | C95: blb_2025 | D95: 500
A96: เก็บเงิน | B96: 45700 | C96: mbk_2025 | D96: 200
A97: เอาเงิินออกไว้รอเทรด | B97: 45697 | C97: dime_2025 | E97: 10000
A98: ดอกเบี้ย kept | B98: 45685 | C98: kept_2025 | F98: 294.49
A99: ค่าล้างรถแม่ | B99: 45683 | C99: blb_2025 | E99: 500
A100: ถอนเงินจาก Radar Point | B100: 45683 | C100: kept_2025 | D100: 343.23
A101: ฝาก mbk | B101: 45681 | C101: mbk_2025 | D101: 300
A102: ฝาก kept + OT | B102: 45681 | C102: kept_2025 | D102: =700+286.75 -> 986.75
A103: cashback so smart | B103: 45680 | C103: kept_2025 | D103: 169.64
A104: ย้ายบัวหลวงไป kept | B104: 45678 | C104: blb_2025 | E104: 57.99
...

Sheet Memo
A1: Date | B1: Event Details
A3: 46106 | B3: ปรัับเงินขึ้น 6,332 บาท
A5: 45741 | B5: ปรับเงินเดือนขึ้น 2,657 บาท

Sheet Studentloan
A1: Date | B1: Amount | D1: Total Debt | E1: Total Pay | G1: Outstanding
A2: 45111 | B2: 1169.25 | D2: 177950 | E2: =SUM(B2:B1000) -> 71594.41 | G2: =D2-E2 -> 106355.59
A3: 45169 | B3: 517
A4: 45199 | B4: 517
A5: 45230 | B5: 517
A6: 45260 | B6: 517
A7: 45285 | B7: 4716.07
A8: 45291 | B8: 517
A9: 45349 | B9: 1100
A10: 45475 | B10: 2575
A11: 45480 | B11: 7072.66
A12: 45504 | B12: 588
A13: 45741 | B13: 1439
A14: 45772 | B14: 1643.86
... A30: 46167 | B30: 3000

Sheet Categories Wide
A1: Monthly Pay | B1: Food & Drink | C1: Transportation | D1: Service | E1: Health | F1: Items | G1: Investing | H1: Residence | I1: Travel | J1: Hobby | K1: Reimbursement | L1: Insurance | M1: Others | O1: Shop
A2: Salary | B2: อาหารหลัก (Main meals) | C2: Maintenance | D2: Subscription | E2: Activewear | F2: Household Items | G2: US Stock | H2: ค่าส่วนกลางหมู่บ้าน (Community Fees) | I2: Accommodation | J2: Tree | K2: Reimbursement | L2: Car Insurance | M2: Tax | O2: Thai Watsadu
A3: OT | B3: ของว่าง (Snacks) | C3: Toll Fee | D3: Haircut | E3: Exercise Equipment | F3: Personal Items | G3: TH Stock | H3: Home Renovation | I3: Food & Drink | J3: Camping | L3: Accident insurance | M3: Donation | O3: Auto 1
A4: Bonus | B4: เครื่องดื่ม (Drinks) | C4: Fuel | D4: Movie | E4: Sick | F4: Skincare | G4: TH Fund | H4: Electricity Bill-A | I4: Alcohol | J4: Computer | L4: Health Insurance | M4: Fine | O4: Major
A5: Freelance | B5: อาหารปรุงเอง (Groceries) | C5: ค่าที่จอดรถ, ค่าธรรมเนียมต่างๆ (Fee) | D5: Home Internet | E5: Accident | F5: Outfit | G5: Contigency | H5: Electricity Bill-B | I5: Fuel | J5: Education | M5: Lotto | O5: SF
A6: OT | B6: อาหารนอกบ้าน (Dine-out) | D6: Mobile Internet | F6: ของที่ใช้กับรถ (Vehicle) | H6: Water Bill | I6: ค่าที่จอดรถ (Fee) | J6: ของที่ใช้กับรถ (Vehicle) | M6: Dept | O6: Caltex
A7: Cashback | B7: อาหารเสริม (Supplement) | D7: Wash&Dry | I7: ค่่าบริการสถานที่ต่างๆ (Fee) | M7: Family | O7: Bangchak
A8: Dividend | B8: เครื่องดื่มแอลกอฮอล์ (Alcohol) | M8: Souvenirs | O8: PT Gas Station
A9: Interest | M9: Alcohol | O9: Watsons
M10: Fee | O10: Eve'nBoy
M11: Fuel | O11: 7-Eleven
M12: Vehicle | O12: Lotus
M13: Others | O13: Mc Donald
O14: Webtoon
O15: YT Premium
O16: Noodle
O17: Hainanese chicken rice
O18: Amazon
O19: KFC
O20: Subway
O21: Pad Kapow
O22: Pizza
O23: Bonchon
O24: Lucky Suki
O25: Ikea
... O34: Other

Sheet Payment Method
A1: Payment Method | B1: Reconciliation Day | C1: Credit Limit | D1: Benefits
A2: UOB One | B2: 7 | C2: 157000 | D2: Cashback: 10% -> MRT, Amazon 5% -> 7-11, Grab, Watson 1% -> other Get movie ticket 1 free 1 - ใช้ได้ 2ครั้ง/เดือน คุ้มครองอุบัติเหตุระหว่างการเดินทางสูงสุด 10,000,000 บาท ต่อบัตร เมื่อชำระค่าโดยสารผ่านบัตรเครดิต UOB One ค่าธรรมเนียม - ฟรีปีแรก - ปีถัดไป 2,000 บาท ยกเว้นใช้จ่ายไม่ต่ำกว่า 60,000 ภายใน 12 รอบบิล
A3: TTB So Smart | B3: 22 | C3: 56000 | D3: Cashback: 3% -> Bangchak (เติมแค่ 620), Caltex (เติมแค่ 720) 1% -> other (ร้านค้าในไทย) ผ่อน 0% นานสูงสุด 3 เดือน ยอด 1,000 ขึ้นไป ประกันอุบัติเหตุเมื่อชําระค่าโดยสารยานพาหนะสาธารณะผ่านบัตรเครดิต ฟรีค่าธรรมเนียมรายปี
A4: KTC Bangchak | B4: 5 | C4: 100000 | D4: Cashback: 1% -> Bangchak ไม่เกิน 3,000/เซลส์สลิป รับ 1 คะแนนทุก 25 บาท ผ่อน 0% นานสูงสุด 10 เดือน ประกันอุบัติเหตุการเดินทางทั้งในและต่างประเทศ และประกันกระเป๋าเดินทางสูญเสีย หรือเสียหายจากการเดินทาง ***เมื่อจ่ายค่าเดินทางด้วยบัตรนี้ ฟรีค่าธรรมเนียมรายปี
A5: Mobile Banking
A6: Cash

Sheet LongFormat
A1: Category | B1: Subcategory
A2: Monthly Pay | B2: Salary
A3: Monthly Pay | B3: Devidend
A4: Monthly Pay | B4: Interest
A5: Monthly Pay | B5: OT
A6: Monthly Pay | B6: Cashback
A7: Monthly Pay | B7: Bonus
A8: Monthly Pay | B8: Freelance
A9: Food & Drink | B9: Main meals
A10: Food & Drink | B10: Snacks
A11: Food & Drink | B11: Drinks
A12: Food & Drink | B12: Groceries
... A60: Items | B60: Vehicle
A61: Hobby
A62: Reimbursement | B62: Reimbursement

Sheet Background-Data
A1: Year | B1: Month | C1: Filter Category | E1: =IFERROR(__xludf.DUMMYFUNCTION("QUERY(Transaction!A1:J200, ""SELECT A, B, C, D, E, F, G, H WHERE B != 'Monthly Pay' AND B != 'Investment' AND B != 'Reimbursement' ""&IF('Monthly Dashboard'!C2<>""All"", ""AND B = '"" &'Monthly Dashboard'!C2& ""'"", """")&"" AND I = '""&'Monthly Dashboard"&"'!A2&""' AND J = '""&'Monthly Dashboard'!B2&""' ORDER BY A DESC"", 1)"),"Date") -> Date | F1: =IFERROR(__xludf.DUMMYFUNCTION("""COMPUTED_VALUE"""),"Category") -> Category | G1: =IFERROR(__xludf.DUMMYFUNCTION("""COMPUTED_VALUE"""),"Sub-Category") -> Sub-Category | H1: =IFERROR(__xludf.DUMMYFUNCTION("""COMPUTED_VALUE"""),"Amount") -> Amount | I1: =IFERROR(__xludf.DUMMYFUNCTION("""COMPUTED_VALUE"""),"Pay Medthod") -> Pay Medthod | J1: =IFERROR(__xludf.DUMMYFUNCTION("""COMPUTED_VALUE"""),"Status") -> Status | K1: =IFERROR(__xludf.DUMMYFUNCTION("""COMPUTED_VALUE"""),"Shop") -> Shop | L1: =IFERROR(__xludf.DUMMYFUNCTION("""COMPUTED_VALUE"""),"Note") -> Note
A2: {=SORT(UNIQUE(Transaction!I2:I200), 1, false)} -> _2025_ | B2: {=SORT(UNIQUE(Transaction!J2:J200), 1, false)} -> _9_ | C2: All | E2: =IFERROR(__xludf.DUMMYFUNCTION("""COMPUTED_VALUE"""),45960.0) -> 45960 | F2: =IFERROR(__xludf.DUMMYFUNCTION("""COMPUTED_VALUE"""),"Food & Drink") -> Food & Drink | G2: =IFERROR(__xludf.DUMMYFUNCTION("""COMPUTED_VALUE"""),"Main meals") -> Main meals | H2: =IFERROR(__xludf.DUMMYFUNCTION("""COMPUTED_VALUE"""),372.0) -> 372 | I2: =IFERROR(__xludf.DUMMYFUNCTION("""COMPUTED_VALUE"""),"UOB One") -> UOB One | J2: =IFERROR(__xludf.DUMMYFUNCTION("""COMPUTED_VALUE"""),"Credit Spending") -> Credit Spending | K2: =IFERROR(__xludf.DUMMYFUNCTION("""COMPUTED_VALUE"""),"Pizza") -> Pizza
B3: _8_ | C3: =IFERROR(__xludf.DUMMYFUNCTION("UNIQUE(QUERY(Transaction!A1:J200, ""SELECT B WHERE B != 'Monthly Pay' AND B != 'Reimbursement' AND B != 'Investment' AND I = '""&'Monthly Dashboard'!A2&""' AND J = '""&'Monthly Dashboard'!B2&""' ORDER BY A DESC"", 0))"),"Food & Drink") -> Food & Drink | E3: =IFERROR(__xludf.DUMMYFUNCTION("""COMPUTED_VALUE"""),45959.0) -> 45959 | F3: =IFERROR(__xludf.DUMMYFUNCTION("""COMPUTED_VALUE"""),"Hobby") -> Hobby | G3: =IFERROR(__xludf.DUMMYFUNCTION("""COMPUTED_VALUE"""),"Education") -> Education | H3: =IFERROR(__xludf.DUMMYFUNCTION("""COMPUTED_VALUE"""),719.0) -> 719 | I3: =IFERROR(__xludf.DUMMYFUNCTION("""COMPUTED_VALUE"""),"UOB One") -> UOB One | J3: =IFERROR(__xludf.DUMMYFUNCTION("""COMPUTED_VALUE"""),"Credit Spending") -> Credit Spending
B4: _7_ | C4: =IFERROR(__xludf.DUMMYFUNCTION("""COMPUTED_VALUE"""),"Hobby") -> Hobby | E4: =IFERROR(__xludf.DUMMYFUNCTION("""COMPUTED_VALUE"""),45959.0) -> 45959 | F4: =IFERROR(__xludf.DUMMYFUNCTION("""COMPUTED_VALUE"""),"Food & Drink") -> Food & Drink | G4: =IFERROR(__xludf.DUMMYFUNCTION("""COMPUTED_VALUE"""),"Main meals") -> Main meals | H4: =IFERROR(__xludf.DUMMYFUNCTION("""COMPUTED_VALUE"""),50.0) -> 50 | I4: =IFERROR(__xludf.DUMMYFUNCTION("""COMPUTED_VALUE"""),"Mobile Banking") -> Mobile Banking | K4: =IFERROR(__xludf.DUMMYFUNCTION("""COMPUTED_VALUE"""),"Hainanese chicken rice") -> Hainanese chicken rice
B5: _6_ | C5: =IFERROR(__xludf.DUMMYFUNCTION("""COMPUTED_VALUE"""),"Transportation") -> Transportation | E5: =IFERROR(__xludf.DUMMYFUNCTION("""COMPUTED_VALUE"""),45959.0) -> 45959 | F5: =IFERROR(__xludf.DUMMYFUNCTION("""COMPUTED_VALUE"""),"Food & Drink") -> Food & Drink | G5: =IFERROR(__xludf.DUMMYFUNCTION("""COMPUTED_VALUE"""),"Snacks") -> Snacks | H5: =IFERROR(__xludf.DUMMYFUNCTION("""COMPUTED_VALUE"""),36.0) -> 36 | I5: =IFERROR(__xludf.DUMMYFUNCTION("""COMPUTED_VALUE"""),"Mobile Banking") -> Mobile Banking | K5: =IFERROR(__xludf.DUMMYFUNCTION("""COMPUTED_VALUE"""),"CJ") -> CJ
B6: _5_ | C6: =IFERROR(__xludf.DUMMYFUNCTION("""COMPUTED_VALUE"""),"Others") -> Others | E6: =IFERROR(__xludf.DUMMYFUNCTION("""COMPUTED_VALUE"""),45957.0) -> 45957 | F6: =IFERROR(__xludf.DUMMYFUNCTION("""COMPUTED_VALUE"""),"Transportation") -> Transportation | G6: =IFERROR(__xludf.DUMMYFUNCTION("""COMPUTED_VALUE"""),"Maintenance") -> Maintenance | H6: =IFERROR(__xludf.DUMMYFUNCTION("""COMPUTED_VALUE"""),1883.2) -> 1883.2 | I6: =IFERROR(__xludf.DUMMYFUNCTION("""COMPUTED_VALUE"""),"Mobile Banking") -> Mobile Banking | J6: =IFERROR(__xludf.DUMMYFUNCTION("""COMPUTED_VALUE"""),"Credit Spending") -> Credit Spending | L6: =IFERROR(__xludf.DUMMYFUNCTION("""COMPUTED_VALUE"""),"เข้าเช็คระยะ 63,000 km") -> เข้าเช็คระยะ 63,000 km
B7: _4_ | C7: =IFERROR(__xludf.DUMMYFUNCTION("""COMPUTED_VALUE"""),"Items") -> Items | E7: =IFERROR(__xludf.DUMMYFUNCTION("""COMPUTED_VALUE"""),45957.0) -> 45957 | F7: =IFERROR(__xludf.DUMMYFUNCTION("""COMPUTED_VALUE"""),"Transportation") -> Transportation | G7: =IFERROR(__xludf.DUMMYFUNCTION("""COMPUTED_VALUE"""),"Fee") -> Fee | H7: =IFERROR(__xludf.DUMMYFUNCTION("""COMPUTED_VALUE"""),50.0) -> 50 | I7: =IFERROR(__xludf.DUMMYFUNCTION("""COMPUTED_VALUE"""),"Mobile Banking") -> Mobile Banking | L7: =IFERROR(__xludf.DUMMYFUNCTION("""COMPUTED_VALUE"""),"ค่าจอดรถสนามบินส่งมิ้น") -> ค่าจอดรถสนามบินส่งมิ้น
B8: _3_ | C8: =IFERROR(__xludf.DUMMYFUNCTION("""COMPUTED_VALUE"""),"Service") -> Service | E8: =IFERROR(__xludf.DUMMYFUNCTION("""COMPUTED_VALUE"""),45957.0) -> 45957 | F8: =IFERROR(__xludf.DUMMYFUNCTION("""COMPUTED_VALUE"""),"Food & Drink") -> Food & Drink | G8: =IFERROR(__xludf.DUMMYFUNCTION("""COMPUTED_VALUE"""),"Snacks") -> Snacks | H8: =IFERROR(__xludf.DUMMYFUNCTION("""COMPUTED_VALUE"""),204.0) -> 204 | I8: =IFERROR(__xludf.DUMMYFUNCTION("""COMPUTED_VALUE"""),"Mobile Banking") -> Mobile Banking | K8: =IFERROR(__xludf.DUMMYFUNCTION("""COMPUTED_VALUE"""),"7-Eleven") -> 7-Eleven | L8: =IFERROR(__xludf.DUMMYFUNCTION("""COMPUTED_VALUE"""),"ตั้งแต่วันที่ 27-29") -> ตั้งแต่วันที่ 27-29
B9: _2_ | C9: =IFERROR(__xludf.DUMMYFUNCTION("""COMPUTED_VALUE"""),"Residence") -> Residence | E9: =IFERROR(__xludf.DUMMYFUNCTION("""COMPUTED_VALUE"""),45956.0) -> 45956 | F9: =IFERROR(__xludf.DUMMYFUNCTION("""COMPUTED_VALUE"""),"Others") -> Others | G9: =IFERROR(__xludf.DUMMYFUNCTION("""COMPUTED_VALUE"""),"Others") -> Others | H9: =IFERROR(__xludf.DUMMYFUNCTION("""COMPUTED_VALUE"""),27.0) -> 27 | I9: =IFERROR(__xludf.DUMMYFUNCTION("""COMPUTED_VALUE"""),"Mobile Banking") -> Mobile Banking | L9: =IFERROR(__xludf.DUMMYFUNCTION("""COMPUTED_VALUE"""),"ค่าส่งหูฟัง soundcore") -> ค่าส่งหูฟัง soundcore
B10: _10_ | C10: =IFERROR(__xludf.DUMMYFUNCTION("""COMPUTED_VALUE"""),"Health") -> Health | E10: =IFERROR(__xludf.DUMMYFUNCTION("""COMPUTED_VALUE"""),45956.0) -> 45956 | F10: =IFERROR(__xludf.DUMMYFUNCTION("""COMPUTED_VALUE"""),"Food & Drink") -> Food & Drink | G10: =IFERROR(__xludf.DUMMYFUNCTION("""COMPUTED_VALUE"""),"Main meals") -> Main meals | H10: =IFERROR(__xludf.DUMMYFUNCTION("""COMPUTED_VALUE"""),85.0) -> 85 | I10: =IFERROR(__xludf.DUMMYFUNCTION("""COMPUTED_VALUE"""),"Mobile Banking") -> Mobile Banking | K10: =IFERROR(__xludf.DUMMYFUNCTION("""COMPUTED_VALUE"""),"Noodle") -> Noodle
B11: _1_ | E11: =IFERROR(__xludf.DUMMYFUNCTION("""COMPUTED_VALUE"""),45956.0) -> 45956 | F11: =IFERROR(__xludf.DUMMYFUNCTION("""COMPUTED_VALUE"""),"Food & Drink") -> Food & Drink | G11: =IFERROR(__xludf.DUMMYFUNCTION("""COMPUTED_VALUE"""),"Drinks") -> Drinks | H11: =IFERROR(__xludf.DUMMYFUNCTION("""COMPUTED_VALUE"""),40.0) -> 40 | I11: =IFERROR(__xludf.DUMMYFUNCTION("""COMPUTED_VALUE"""),"Mobile Banking") -> Mobile Banking | K11: =IFERROR(__xludf.DUMMYFUNCTION("""COMPUTED_VALUE"""),"CJ") -> CJ | L11: =IFERROR(__xludf.DUMMYFUNCTION("""COMPUTED_VALUE"""),"ชาไทย") -> ชาไทย
E12: =IFERROR(__xludf.DUMMYFUNCTION("""COMPUTED_VALUE"""),45956.0) -> 45956 | F12: =IFERROR(__xludf.DUMMYFUNCTION("""COMPUTED_VALUE"""),"Food & Drink") -> Food & Drink | G12: =IFERROR(__xludf.DUMMYFUNCTION("""COMPUTED_VALUE"""),"Groceries") -> Groceries | H12: =IFERROR(__xludf.DUMMYFUNCTION("""COMPUTED_VALUE"""),120.0) -> 120 | I12: =IFERROR(__xludf.DUMMYFUNCTION("""COMPUTED_VALUE"""),"Mobile Banking") -> Mobile Banking | L12: =IFERROR(__xludf.DUMMYFUNCTION("""COMPUTED_VALUE"""),"ผัก") -> ผัก
E13: =IFERROR(__xludf.DUMMYFUNCTION("""COMPUTED_VALUE"""),45956.0) -> 45956 | F13: =IFERROR(__xludf.DUMMYFUNCTION("""COMPUTED_VALUE"""),"Transportation") -> Transportation | G13: =IFERROR(__xludf.DUMMYFUNCTION("""COMPUTED_VALUE"""),"Maintenance") -> Maintenance | H13: =IFERROR(__xludf.DUMMYFUNCTION("""COMPUTED_VALUE"""),1000.0) -> 1000 | I13: =IFERROR(__xludf.DUMMYFUNCTION("""COMPUTED_VALUE"""),"Mobile Banking") -> Mobile Banking | J13: =IFERROR(__xludf.DUMMYFUNCTION("""COMPUTED_VALUE"""),"Credit Spending") -> Credit Spending | L13: =IFERROR(__xludf.DUMMYFUNCTION("""COMPUTED_VALUE"""),"เปลี่ยนคิ้วรถ") -> เปลี่ยนคิ้วรถ
E14: =IFERROR(__xludf.DUMMYFUNCTION("""COMPUTED_VALUE"""),45955.0) -> 45955 | F14: =IFERROR(__xludf.DUMMYFUNCTION("""COMPUTED_VALUE"""),"Food & Drink") -> Food & Drink | G14: =IFERROR(__xludf.DUMMYFUNCTION("""COMPUTED_VALUE"""),"Main meals") -> Main meals | H14: =IFERROR(__xludf.DUMMYFUNCTION("""COMPUTED_VALUE"""),80.0) -> 80 | I14: =IFERROR(__xludf.DUMMYFUNCTION("""COMPUTED_VALUE"""),"Mobile Banking") -> Mobile Banking | L14: =IFERROR(__xludf.DUMMYFUNCTION("""COMPUTED_VALUE"""),"กะเพรา") -> กะเพรา
E15: =IFERROR(__xludf.DUMMYFUNCTION("""COMPUTED_VALUE"""),45955.0) -> 45955 | F15: =IFERROR(__xludf.DUMMYFUNCTION("""COMPUTED_VALUE"""),"Food & Drink") -> Food & Drink | G15: =IFERROR(__xludf.DUMMYFUNCTION("""COMPUTED_VALUE"""),"Groceries") -> Groceries | H15: =IFERROR(__xludf.DUMMYFUNCTION("""COMPUTED_VALUE"""),162.0) -> 162 | I15: =IFERROR(__xludf.DUMMYFUNCTION("""COMPUTED_VALUE"""),"Mobile Banking") -> Mobile Banking | L15: =IFERROR(__xludf.DUMMYFUNCTION("""COMPUTED_VALUE"""),"ผัก") -> ผัก
E16: =IFERROR(__xludf.DUMMYFUNCTION("""COMPUTED_VALUE"""),45955.0) -> 45955 | F16: =IFERROR(__xludf.DUMMYFUNCTION("""COMPUTED_VALUE"""),"Food & Drink") -> Food & Drink | G16: =IFERROR(__xludf.DUMMYFUNCTION("""COMPUTED_VALUE"""),"Drinks") -> Drinks | H16: =IFERROR(__xludf.DUMMYFUNCTION("""COMPUTED_VALUE"""),40.0) -> 40 | I16: =IFERROR(__xludf.DUMMYFUNCTION("""COMPUTED_VALUE"""),"Mobile Banking") -> Mobile Banking | K16: =IFERROR(__xludf.DUMMYFUNCTION("""COMPUTED_VALUE"""),"CJ") -> CJ | L16: =IFERROR(__xludf.DUMMYFUNCTION("""COMPUTED_VALUE"""),"ชาไทย") -> ชาไทย
E17: =IFERROR(__xludf.DUMMYFUNCTION("""COMPUTED_VALUE"""),45955.0) -> 45955 | F17: =IFERROR(__xludf.DUMMYFUNCTION("""COMPUTED_VALUE"""),"Items") -> Items | G17: =IFERROR(__xludf.DUMMYFUNCTION("""COMPUTED_VALUE"""),"Household Items") -> Household Items | H17: =IFERROR(__xludf.DUMMYFUNCTION("""COMPUTED_VALUE"""),142.0) -> 142 | I17: =IFERROR(__xludf.DUMMYFUNCTION("""COMPUTED_VALUE"""),"TTB So Smart") -> TTB So Smart | J17: =IFERROR(__xludf.DUMMYFUNCTION("""COMPUTED_VALUE"""),"Credit Spending") -> Credit Spending | K17: =IFERROR(__xludf.DUMMYFUNCTION("""COMPUTED_VALUE"""),"Lotus") -> Lotus | L17: =IFERROR(__xludf.DUMMYFUNCTION("""COMPUTED_VALUE"""),"สำลี ครีมอาบน้ำไ") -> สำลี ครีมอาบน้ำไ
E18: =IFERROR(__xludf.DUMMYFUNCTION("""COMPUTED_VALUE"""),45955.0) -> 45955 | F18: =IFERROR(__xludf.DUMMYFUNCTION("""COMPUTED_VALUE"""),"Food & Drink") -> Food & Drink | G18: =IFERROR(__xludf.DUMMYFUNCTION("""COMPUTED_VALUE"""),"Groceries") -> Groceries | H18: =IFERROR(__xludf.DUMMYFUNCTION("""COMPUTED_VALUE"""),381.25) -> 381.25 | I18: =IFERROR(__xludf.DUMMYFUNCTION("""COMPUTED_VALUE"""),"TTB So Smart") -> TTB So Smart | J18: =IFERROR(__xludf.DUMMYFUNCTION("""COMPUTED_VALUE"""),"Credit Spending") -> Credit Spending | K18: =IFERROR(__xludf.DUMMYFUNCTION("""COMPUTED_VALUE"""),"Lotus") -> Lotus
E19: =IFERROR(__xludf.DUMMYFUNCTION("""COMPUTED_VALUE"""),45954.0) -> 45954 | F19: =IFERROR(__xludf.DUMMYFUNCTION("""COMPUTED_VALUE"""),"Others") -> Others | G19: =IFERROR(__xludf.DUMMYFUNCTION("""COMPUTED_VALUE"""),"Debt") -> Debt | H19: =IFERROR(__xludf.DUMMYFUNCTION("""COMPUTED_VALUE"""),8521.0) -> 8521 | I19: =IFERROR(__xludf.DUMMYFUNCTION("""COMPUTED_VALUE"""),"Mobile Banking") -> Mobile Banking | L19: =IFERROR(__xludf.DUMMYFUNCTION("""COMPUTED_VALUE"""),"ค่ารถงวด 39") -> ค่ารถงวด 39
E20: =IFERROR(__xludf.DUMMYFUNCTION("""COMPUTED_VALUE"""),45954.0) -> 45954 | F20: =IFERROR(__xludf.DUMMYFUNCTION("""COMPUTED_VALUE"""),"Others") -> Others | G20: =IFERROR(__xludf.DUMMYFUNCTION("""COMPUTED_VALUE"""),"Devidend") -> Devidend | H20: =IFERROR(__xludf.DUMMYFUNCTION("""COMPUTED_VALUE"""),2000.0) -> 2000 | I20: =IFERROR(__xludf.DUMMYFUNCTION("""COMPUTED_VALUE"""),"Mobile Banking") -> Mobile Banking | K20: =IFERROR(__xludf.DUMMYFUNCTION("""COMPUTED_VALUE"""),"Studentloan Debt") -> Studentloan Debt | L20: =IFERROR(__xludf.DUMMYFUNCTION("""COMPUTED_VALUE"""),"กยศ") -> กยศ
E21: =IFERROR(__xludf.DUMMYFUNCTION("""COMPUTED_VALUE"""),45954.0) -> 45954 | F21: =IFERROR(__xludf.DUMMYFUNCTION("""COMPUTED_VALUE"""),"Service") -> Service | G21: =IFERROR(__xludf.DUMMYFUNCTION("""COMPUTED_VALUE"""),"Home Internet") -> Home Internet | H21: =IFERROR(__xludf.DUMMYFUNCTION("""COMPUTED_VALUE"""),650.0) -> 650 | I21: =IFERROR(__xludf.DUMMYFUNCTION("""COMPUTED_VALUE"""),"Mobile Banking") -> Mobile Banking | L21: =IFERROR(__xludf.DUMMYFUNCTION("""COMPUTED_VALUE"""),"เน็ตบ้าน") -> เน็ตบ้าน
E22: =IFERROR(__xludf.DUMMYFUNCTION("""COMPUTED_VALUE"""),45954.0) -> 45954 | F22: =IFERROR(__xludf.DUMMYFUNCTION("""COMPUTED_VALUE"""),"Service") -> Service | G22: =IFERROR(__xludf.DUMMYFUNCTION("""COMPUTED_VALUE"""),"Mobile Internet") -> Mobile Internet | H22: =IFERROR(__xludf.DUMMYFUNCTION("""COMPUTED_VALUE"""),450.0) -> 450 | I22: =IFERROR(__xludf.DUMMYFUNCTION("""COMPUTED_VALUE"""),"Mobile Banking") -> Mobile Banking | L22: =IFERROR(__xludf.DUMMYFUNCTION("""COMPUTED_VALUE"""),"เน็็ตมือถือ") -> เน็็ตมือถือ
E23: =IFERROR(__xludf.DUMMYFUNCTION("""COMPUTED_VALUE"""),45954.0) -> 45954 | F23: =IFERROR(__xludf.DUMMYFUNCTION("""COMPUTED_VALUE"""),"Food & Drink") -> Food & Drink | G23: =IFERROR(__xludf.DUMMYFUNCTION("""COMPUTED_VALUE"""),"Main meals") -> Main meals | H23: =IFERROR(__xludf.DUMMYFUNCTION("""COMPUTED_VALUE"""),80.0) -> 80 | I23: =IFERROR(__xludf.DUMMYFUNCTION("""COMPUTED_VALUE"""),"Mobile Banking") -> Mobile Banking | L23: =IFERROR(__xludf.DUMMYFUNCTION("""COMPUTED_VALUE"""),"ข้าวมันไก่, ลูกชิ้น") -> ข้าวมันไก่, ลูกชิ้น
E24: =IFERROR(__xludf.DUMMYFUNCTION("""COMPUTED_VALUE"""),45954.0) -> 45954 | F24: =IFERROR(__xludf.DUMMYFUNCTION("""COMPUTED_VALUE"""),"Food & Drink") -> Food & Drink | G24: =IFERROR(__xludf.DUMMYFUNCTION("""COMPUTED_VALUE"""),"Main meals") -> Main meals | H24: =IFERROR(__xludf.DUMMYFUNCTION("""COMPUTED_VALUE"""),190.0) -> 190 | I24: =IFERROR(__xludf.DUMMYFUNCTION("""COMPUTED_VALUE"""),"UOB One") -> UOB One | J24: =IFERROR(__xludf.DUMMYFUNCTION("""COMPUTED_VALUE"""),"Credit Spending") -> Credit Spending | K24: =IFERROR(__xludf.DUMMYFUNCTION("""COMPUTED_VALUE"""),"Bonchon") -> Bonchon
E25: =IFERROR(__xludf.DUMMYFUNCTION("""COMPUTED_VALUE"""),45953.0) -> 45953 | F25: =IFERROR(__xludf.DUMMYFUNCTION("""COMPUTED_VALUE"""),"Food & Drink") -> Food & Drink | G25: =IFERROR(__xludf.DUMMYFUNCTION("""COMPUTED_VALUE"""),"Snacks") -> Snacks | H25: =IFERROR(__xludf.DUMMYFUNCTION("""COMPUTED_VALUE"""),37.0) -> 37 | I25: =IFERROR(__xludf.DUMMYFUNCTION("""COMPUTED_VALUE"""),"Mobile Banking") -> Mobile Banking | L25: =IFERROR(__xludf.DUMMYFUNCTION("""COMPUTED_VALUE"""),"โตเกียว") -> โตเกียว
E26: =IFERROR(__xludf.DUMMYFUNCTION("""COMPUTED_VALUE"""),45952.0) -> 45952 | F26: =IFERROR(__xludf.DUMMYFUNCTION("""COMPUTED_VALUE"""),"Food & Drink") -> Food & Drink | G26: =IFERROR(__xludf.DUMMYFUNCTION("""COMPUTED_VALUE"""),"Main meals") -> Main meals | H26: =IFERROR(__xludf.DUMMYFUNCTION("""COMPUTED_VALUE"""),153.0) -> 153 | I26: =IFERROR(__xludf.DUMMYFUNCTION("""COMPUTED_VALUE"""),"UOB One") -> UOB One | J26: =IFERROR(__xludf.DUMMYFUNCTION("""COMPUTED_VALUE"""),"Credit Spending") -> Credit Spending | K26: =IFERROR(__xludf.DUMMYFUNCTION("""COMPUTED_VALUE"""),"KFC") -> KFC
E27: =IFERROR(__xludf.DUMMYFUNCTION("""COMPUTED_VALUE"""),45952.0) -> 45952 | F27: =IFERROR(__xludf.DUMMYFUNCTION("""COMPUTED_VALUE"""),"Others") -> Others | G27: =IFERROR(__xludf.DUMMYFUNCTION("""COMPUTED_VALUE"""),"Others") -> Others | H27: =IFERROR(__xludf.DUMMYFUNCTION("""COMPUTED_VALUE"""),100.0) -> 100 | I27: =IFERROR(__xludf.DUMMYFUNCTION("""COMPUTED_VALUE"""),"Mobile Banking") -> Mobile Banking | L27: =IFERROR(__xludf.DUMMYFUNCTION("""COMPUTED_VALUE"""),"ให้พาย") -> ให้พาย
E28: =IFERROR(__xludf.DUMMYFUNCTION("""COMPUTED_VALUE"""),45951.0) -> 45951 | F28: =IFERROR(__xludf.DUMMYFUNCTION("""COMPUTED_VALUE"""),"Food & Drink") -> Food & Drink | G28: =IFERROR(__xludf.DUMMYFUNCTION("""COMPUTED_VALUE"""),"Main meals") -> Main meals | H28: =IFERROR(__xludf.DUMMYFUNCTION("""COMPUTED_VALUE"""),139.0) -> 139 | I28: =IFERROR(__xludf.DUMMYFUNCTION("""COMPUTED_VALUE"""),"TTB So Smart") -> TTB So Smart | J28: =IFERROR(__xludf.DUMMYFUNCTION("""COMPUTED_VALUE"""),"Credit Payment") -> Credit Payment | K28: =IFERROR(__xludf.DUMMYFUNCTION("""COMPUTED_VALUE"""),"Noodle") -> Noodle | L28: =IFERROR(__xludf.DUMMYFUNCTION("""COMPUTED_VALUE"""),"เตี๋ยวไก่") -> เตี๋ยวไก่
E29: =IFERROR(__xludf.DUMMYFUNCTION("""COMPUTED_VALUE"""),45950.0) -> 45950 | F29: =IFERROR(__xludf.DUMMYFUNCTION("""COMPUTED_VALUE"""),"Food & Drink") -> Food & Drink | G29: =IFERROR(__xludf.DUMMYFUNCTION("""COMPUTED_VALUE"""),"Main meals") -> Main meals | H29: =IFERROR(__xludf.DUMMYFUNCTION("""COMPUTED_VALUE"""),85.0) -> 85 | I29: =IFERROR(__xludf.DUMMYFUNCTION("""COMPUTED_VALUE"""),"Mobile Banking") -> Mobile Banking | L29: =IFERROR(__xludf.DUMMYFUNCTION("""COMPUTED_VALUE"""),"กะเพรา") -> กะเพรา
E30: =IFERROR(__xludf.DUMMYFUNCTION("""COMPUTED_VALUE"""),45950.0) -> 45950 | F30: =IFERROR(__xludf.DUMMYFUNCTION("""COMPUTED_VALUE"""),"Food & Drink") -> Food & Drink | G30: =IFERROR(__xludf.DUMMYFUNCTION("""COMPUTED_VALUE"""),"Dine-out") -> Dine-out | H30: =IFERROR(__xludf.DUMMYFUNCTION("""COMPUTED_VALUE"""),534.0) -> 534 | I30: =IFERROR(__xludf.DUMMYFUNCTION("""COMPUTED_VALUE"""),"Mobile Banking") -> Mobile Banking | L30: =IFERROR(__xludf.DUMMYFUNCTION("""COMPUTED_VALUE"""),"BBQ Plaza") -> BBQ Plaza
E31: =IFERROR(__xludf.DUMMYFUNCTION("""COMPUTED_VALUE"""),45950.0) -> 45950 | F31: =IFERROR(__xludf.DUMMYFUNCTION("""COMPUTED_VALUE"""),"Food & Drink") -> Food & Drink | G31: =IFERROR(__xludf.DUMMYFUNCTION("""COMPUTED_VALUE"""),"Snacks") -> Snacks | H31: =IFERROR(__xludf.DUMMYFUNCTION("""COMPUTED_VALUE"""),10.0) -> 10 | I31: =IFERROR(__xludf.DUMMYFUNCTION("""COMPUTED_VALUE"""),"Mobile Banking") -> Mobile Banking | L31: =IFERROR(__xludf.DUMMYFUNCTION("""COMPUTED_VALUE"""),"ถั่ว") -> ถั่ว
E32: =IFERROR(__xludf.DUMMYFUNCTION("""COMPUTED_VALUE"""),45950.0) -> 45950 | F32: =IFERROR(__xludf.DUMMYFUNCTION("""COMPUTED_VALUE"""),"Residence") -> Residence | G32: =IFERROR(__xludf.DUMMYFUNCTION("""COMPUTED_VALUE"""),"Water Bill") -> Water Bill | H32: =IFERROR(__xludf.DUMMYFUNCTION("""COMPUTED_VALUE"""),184.07) -> 184.07 | I32: =IFERROR(__xludf.DUMMYFUNCTION("""COMPUTED_VALUE"""),"Mobile Banking") -> Mobile Banking | L32: =IFERROR(__xludf.DUMMYFUNCTION("""COMPUTED_VALUE"""),"ค่าน้ำ") -> ค่าน้ำ
E33: =IFERROR(__xludf.DUMMYFUNCTION("""COMPUTED_VALUE"""),45950.0) -> 45950 | F33: =IFERROR(__xludf.DUMMYFUNCTION("""COMPUTED_VALUE"""),"Food & Drink") -> Food & Drink | G33: =IFERROR(__xludf.DUMMYFUNCTION("""COMPUTED_VALUE"""),"Snacks") -> Snacks | H33: =IFERROR(__xludf.DUMMYFUNCTION("""COMPUTED_VALUE"""),278.0) -> 278 | I33: =IFERROR(__xludf.DUMMYFUNCTION("""COMPUTED_VALUE"""),"Mobile Banking") -> Mobile Banking | K33: =IFERROR(__xludf.DUMMYFUNCTION("""COMPUTED_VALUE"""),"7-Eleven") -> 7-Eleven | L33: =IFERROR(__xludf.DUMMYFUNCTION("""COMPUTED_VALUE"""),"ตั้งแต่วันที่ 20-24") -> ตั้งแต่วันที่ 20-24
E34: =IFERROR(__xludf.DUMMYFUNCTION("""COMPUTED_VALUE"""),45949.0) -> 45949 | F34: =IFERROR(__xludf.DUMMYFUNCTION("""COMPUTED_VALUE"""),"Service") -> Service | G34: =IFERROR(__xludf.DUMMYFUNCTION("""COMPUTED_VALUE"""),"Subscription") -> Subscription | H34: =IFERROR(__xludf.DUMMYFUNCTION("""COMPUTED_VALUE"""),1200.0) -> 1200 | I34: =IFERROR(__xludf.DUMMYFUNCTION("""COMPUTED_VALUE"""),"Mobile Banking") -> Mobile Banking | L34: =IFERROR(__xludf.DUMMYFUNCTION("""COMPUTED_VALUE"""),"เข้ากลุ่มลิงเล่นหุ้นรายปี") -> เข้ากลุ่มลิงเล่นหุ้นรายปี
E35: =IFERROR(__xludf.DUMMYFUNCTION("""COMPUTED_VALUE"""),45949.0) -> 45949 | F35: =IFERROR(__xludf.DUMMYFUNCTION("""COMPUTED_VALUE"""),"Food & Drink") -> Food & Drink | G35: =IFERROR(__xludf.DUMMYFUNCTION("""COMPUTED_VALUE"""),"Groceries") -> Groceries | H35: =IFERROR(__xludf.DUMMYFUNCTION("""COMPUTED_VALUE"""),60.0) -> 60 | I35: =IFERROR(__xludf.DUMMYFUNCTION("""COMPUTED_VALUE"""),"Mobile Banking") -> Mobile Banking | L35: =IFERROR(__xludf.DUMMYFUNCTION("""COMPUTED_VALUE"""),"ผักตลาด") -> ผักตลาด
E36: =IFERROR(__xludf.DUMMYFUNCTION("""COMPUTED_VALUE"""),45949.0) -> 45949 | F36: =IFERROR(__xludf.DUMMYFUNCTION("""COMPUTED_VALUE"""),"Food & Drink") -> Food & Drink | G36: =IFERROR(__xludf.DUMMYFUNCTION("""COMPUTED_VALUE"""),"Snacks") -> Snacks | H36: =IFERROR(__xludf.DUMMYFUNCTION("""COMPUTED_VALUE"""),99.0) -> 99 | I36: =IFERROR(__xludf.DUMMYFUNCTION("""COMPUTED_VALUE"""),"Mobile Banking") -> Mobile Banking | L36: =IFERROR(__xludf.DUMMYFUNCTION("""COMPUTED_VALUE"""),"bing su") -> bing su
E37: =IFERROR(__xludf.DUMMYFUNCTION("""COMPUTED_VALUE"""),45949.0) -> 45949 | F37: =IFERROR(__xludf.DUMMYFUNCTION("""COMPUTED_VALUE"""),"Food & Drink") -> Food & Drink | G37: =IFERROR(__xludf.DUMMYFUNCTION("""COMPUTED_VALUE"""),"Main meals") -> Main meals | H37: =IFERROR(__xludf.DUMMYFUNCTION("""COMPUTED_VALUE"""),110.0) -> 110 | I37: =IFERROR(__xludf.DUMMYFUNCTION("""COMPUTED_VALUE"""),"Mobile Banking") -> Mobile Banking | L37: =IFERROR(__xludf.DUMMYFUNCTION("""COMPUTED_VALUE"""),"กะเพรา") -> กะเพรา
E38: =IFERROR(__xludf.DUMMYFUNCTION("""COMPUTED_VALUE"""),45949.0) -> 45949 | F38: =IFERROR(__xludf.DUMMYFUNCTION("""COMPUTED_VALUE"""),"Items") -> Items | G38: =IFERROR(__xludf.DUMMYFUNCTION("""COMPUTED_VALUE"""),"Others") -> Others | H38: =IFERROR(__xludf.DUMMYFUNCTION("""COMPUTED_VALUE"""),30.0) -> 30 | I38: =IFERROR(__xludf.DUMMYFUNCTION("""COMPUTED_VALUE"""),"Mobile Banking") -> Mobile Banking | L38: =IFERROR(__xludf.DUMMYFUNCTION("""COMPUTED_VALUE"""),"พวกกุจแจของญี่ปุ่น") -> พวกกุจแจของญี่ปุ่น
E39: =IFERROR(__xludf.DUMMYFUNCTION("""COMPUTED_VALUE"""),45949.0) -> 45949 | F39: =IFERROR(__xludf.DUMMYFUNCTION("""COMPUTED_VALUE"""),"Items") -> Items | G39: =IFERROR(__xludf.DUMMYFUNCTION("""COMPUTED_VALUE"""),"Personal Items") -> Personal Items | H39: =IFERROR(__xludf.DUMMYFUNCTION("""COMPUTED_VALUE"""),157.0) -> 157 | I39: =IFERROR(__xludf.DUMMYFUNCTION("""COMPUTED_VALUE"""),"TTB So Smart") -> TTB So Smart | J39: =IFERROR(__xludf.DUMMYFUNCTION("""COMPUTED_VALUE"""),"Credit Payment") -> Credit Payment | L39: =IFERROR(__xludf.DUMMYFUNCTION("""COMPUTED_VALUE"""),"น้ำหอมรถยนต์") -> น้ำหอมรถยนต์
E40: =IFERROR(__xludf.DUMMYFUNCTION("""COMPUTED_VALUE"""),45949.0) -> 45949 | F40: =IFERROR(__xludf.DUMMYFUNCTION("""COMPUTED_VALUE"""),"Hobby") -> Hobby | G40: =IFERROR(__xludf.DUMMYFUNCTION("""COMPUTED_VALUE"""),"Computer") -> Computer | H40: =IFERROR(__xludf.DUMMYFUNCTION("""COMPUTED_VALUE"""),1017.0) -> 1017 | I40: =IFERROR(__xludf.DUMMYFUNCTION("""COMPUTED_VALUE"""),"TTB So Smart") -> TTB So Smart | J40: =IFERROR(__xludf.DUMMYFUNCTION("""COMPUTED_VALUE"""),"Credit Payment") -> Credit Payment | L40: =IFERROR(__xludf.DUMMYFUNCTION("""COMPUTED_VALUE"""),"ขาจับไมค์, แผ่นรองเม้า") -> ขาจับไมค์, แผ่นรองเม้า
E41: =IFERROR(__xludf.DUMMYFUNCTION("""COMPUTED_VALUE"""),45948.0) -> 45948 | F41: =IFERROR(__xludf.DUMMYFUNCTION("""COMPUTED_VALUE"""),"Transportation") -> Transportation | G41: =IFERROR(__xludf.DUMMYFUNCTION("""COMPUTED_VALUE"""),"Others") -> Others | H41: =IFERROR(__xludf.DUMMYFUNCTION("""COMPUTED_VALUE"""),337.0) -> 337 | I41: =IFERROR(__xludf.DUMMYFUNCTION("""COMPUTED_VALUE"""),"UOB One") -> UOB One | J41: =IFERROR(__xludf.DUMMYFUNCTION("""COMPUTED_VALUE"""),"Credit Spending") -> Credit Spending | L41: =IFERROR(__xludf.DUMMYFUNCTION("""COMPUTED_VALUE"""),"นั่ง grab กลับบ้าน") -> นั่ง grab กลับบ้าน
E42: =IFERROR(__xludf.DUMMYFUNCTION("""COMPUTED_VALUE"""),45948.0) -> 45948 | F42: =IFERROR(__xludf.DUMMYFUNCTION("""COMPUTED_VALUE"""),"Food & Drink") -> Food & Drink | G42: =IFERROR(__xludf.DUMMYFUNCTION("""COMPUTED_VALUE"""),"Main meals") -> Main meals | H42: =IFERROR(__xludf.DUMMYFUNCTION("""COMPUTED_VALUE"""),205.6) -> 205.6 | I42: =IFERROR(__xludf.DUMMYFUNCTION("""COMPUTED_VALUE"""),"UOB One") -> UOB One | J42: =IFERROR(__xludf.DUMMYFUNCTION("""COMPUTED_VALUE"""),"Credit Spending") -> Credit Spending | L42: =IFERROR(__xludf.DUMMYFUNCTION("""COMPUTED_VALUE"""),"ข้าวเที่ยง") -> ข้าวเที่ยง
E43: =IFERROR(__xludf.DUMMYFUNCTION("""COMPUTED_VALUE"""),45947.0) -> 45947 | F43: =IFERROR(__xludf.DUMMYFUNCTION("""COMPUTED_VALUE"""),"Items") -> Items | G43: =IFERROR(__xludf.DUMMYFUNCTION("""COMPUTED_VALUE"""),"Household Items") -> Household Items | H43: =IFERROR(__xludf.DUMMYFUNCTION("""COMPUTED_VALUE"""),432.0) -> 432 | I43: =IFERROR(__xludf.DUMMYFUNCTION("""COMPUTED_VALUE"""),"TTB So Smart") -> TTB So Smart | J43: =IFERROR(__xludf.DUMMYFUNCTION("""COMPUTED_VALUE"""),"Credit Payment") -> Credit Payment | L43: =IFERROR(__xludf.DUMMYFUNCTION("""COMPUTED_VALUE"""),"แปรงสีฟัน, ยาสระผม") -> แปรงสีฟัน, ยาสระผม
E44: =IFERROR(__xludf.DUMMYFUNCTION("""COMPUTED_VALUE"""),45947.0) -> 45947 | F44: =IFERROR(__xludf.DUMMYFUNCTION("""COMPUTED_VALUE"""),"Items") -> Items | G44: =IFERROR(__xludf.DUMMYFUNCTION("""COMPUTED_VALUE"""),"Skincare") -> Skincare | H44: =IFERROR(__xludf.DUMMYFUNCTION("""COMPUTED_VALUE"""),1927.0) -> 1927 | I44: =IFERROR(__xludf.DUMMYFUNCTION("""COMPUTED_VALUE"""),"TTB So Smart") -> TTB So Smart | J44: =IFERROR(__xludf.DUMMYFUNCTION("""COMPUTED_VALUE"""),"Credit Payment") -> Credit Payment | L44: =IFERROR(__xludf.DUMMYFUNCTION("""COMPUTED_VALUE"""),"น้ำหอม CK, ครีม verite, มีดโกนหนวด") -> น้ำหอม CK, ครีม verite, มีดโกนหนวด
E45: =IFERROR(__xludf.DUMMYFUNCTION("""COMPUTED_VALUE"""),45947.0) -> 45947 | F45: =IFERROR(__xludf.DUMMYFUNCTION("""COMPUTED_VALUE"""),"Food & Drink") -> Food & Drink | G45: =IFERROR(__xludf.DUMMYFUNCTION("""COMPUTED_VALUE"""),"Alcohol") -> Alcohol | H45: =IFERROR(__xludf.DUMMYFUNCTION("""COMPUTED_VALUE"""),1284.0) -> 1284 | I45: =IFERROR(__xludf.DUMMYFUNCTION("""COMPUTED_VALUE"""),"Mobile Banking") -> Mobile Banking | K45: =IFERROR(__xludf.DUMMYFUNCTION("""COMPUTED_VALUE"""),"Thai Watsadu") -> Thai Watsadu | L45: =IFERROR(__xludf.DUMMYFUNCTION("""COMPUTED_VALUE"""),"เบียร์ + ตี๋น้อย") -> เบียร์ + ตี๋น้อย
E46: =IFERROR(__xludf.DUMMYFUNCTION("""COMPUTED_VALUE"""),45946.0) -> 45946 | F46: =IFERROR(__xludf.DUMMYFUNCTION("""COMPUTED_VALUE"""),"Others") -> Others | G46: =IFERROR(__xludf.DUMMYFUNCTION("""COMPUTED_VALUE"""),"Others") -> Others | H46: =IFERROR(__xludf.DUMMYFUNCTION("""COMPUTED_VALUE"""),12.0) -> 12 | I46: =IFERROR(__xludf.DUMMYFUNCTION("""COMPUTED_VALUE"""),"Cash") -> Cash | L46: =IFERROR(__xludf.DUMMYFUNCTION("""COMPUTED_VALUE"""),"ถ่ายเอกสารทำบัตรเครดิต") -> ถ่ายเอกสารทำบัตรเครดิต
E47: =IFERROR(__xludf.DUMMYFUNCTION("""COMPUTED_VALUE"""),45946.0) -> 45946 | F47: =IFERROR(__xludf.DUMMYFUNCTION("""COMPUTED_VALUE"""),"Food & Drink") -> Food & Drink | G47: =IFERROR(__xludf.DUMMYFUNCTION("""COMPUTED_VALUE"""),"Main meals") -> Main meals | H47: =IFERROR(__xludf.DUMMYFUNCTION("""COMPUTED_VALUE"""),85.0) -> 85 | I47: =IFERROR(__xludf.DUMMYFUNCTION("""COMPUTED_VALUE"""),"Mobile Banking") -> Mobile Banking | L47: =IFERROR(__xludf.DUMMYFUNCTION("""COMPUTED_VALUE"""),"กะเพรา") -> กะเพรา
E48: =IFERROR(__xludf.DUMMYFUNCTION("""COMPUTED_VALUE"""),45946.0) -> 45946 | F48: =IFERROR(__xludf.DUMMYFUNCTION("""COMPUTED_VALUE"""),"Food & Drink") -> Food & Drink | G48: =IFERROR(__xludf.DUMMYFUNCTION("""COMPUTED_VALUE"""),"Groceries") -> Groceries | H48: =IFERROR(__xludf.DUMMYFUNCTION("""COMPUTED_VALUE"""),60.0) -> 60 | I48: =IFERROR(__xludf.DUMMYFUNCTION("""COMPUTED_VALUE"""),"Mobile Banking") -> Mobile Banking | L48: =IFERROR(__xludf.DUMMYFUNCTION("""COMPUTED_VALUE"""),"มะพร้าว") -> มะพร้าว
E49: =IFERROR(__xludf.DUMMYFUNCTION("""COMPUTED_VALUE"""),45946.0) -> 45946 | F49: =IFERROR(__xludf.DUMMYFUNCTION("""COMPUTED_VALUE"""),"Service") -> Service | G49: =IFERROR(__xludf.DUMMYFUNCTION("""COMPUTED_VALUE"""),"Haircut") -> Haircut | H49: =IFERROR(__xludf.DUMMYFUNCTION("""COMPUTED_VALUE"""),200.0) -> 200 | I49: =IFERROR(__xludf.DUMMYFUNCTION("""COMPUTED_VALUE"""),"Mobile Banking") -> Mobile Banking
E50: =IFERROR(__xludf.DUMMYFUNCTION("""COMPUTED_VALUE"""),45946.0) -> 45946 | F50: =IFERROR(__xludf.DUMMYFUNCTION("""COMPUTED_VALUE"""),"Food & Drink") -> Food & Drink | G50: =IFERROR(__xludf.DUMMYFUNCTION("""COMPUTED_VALUE"""),"Drinks") -> Drinks | H50: =IFERROR(__xludf.DUMMYFUNCTION("""COMPUTED_VALUE"""),40.0) -> 40 | I50: =IFERROR(__xludf.DUMMYFUNCTION("""COMPUTED_VALUE"""),"Mobile Banking") -> Mobile Banking | L50: =IFERROR(__xludf.DUMMYFUNCTION("""COMPUTED_VALUE"""),"ชานม") -> ชานม
E51: =IFERROR(__xludf.DUMMYFUNCTION("""COMPUTED_VALUE"""),45946.0) -> 45946 | F51: =IFERROR(__xludf.DUMMYFUNCTION("""COMPUTED_VALUE"""),"Food & Drink") -> Food & Drink | G51: =IFERROR(__xludf.DUMMYFUNCTION("""COMPUTED_VALUE"""),"Main meals") -> Main meals | H51: =IFERROR(__xludf.DUMMYFUNCTION("""COMPUTED_VALUE"""),50.0) -> 50 | I51: =IFERROR(__xludf.DUMMYFUNCTION("""COMPUTED_VALUE"""),"Mobile Banking") -> Mobile Banking | K51: =IFERROR(__xludf.DUMMYFUNCTION("""COMPUTED_VALUE"""),"Hainanese chicken rice") -> Hainanese chicken rice
E52: =IFERROR(__xludf.DUMMYFUNCTION("""COMPUTED_VALUE"""),45946.0) -> 45946 | F52: =IFERROR(__xludf.DUMMYFUNCTION("""COMPUTED_VALUE"""),"Food & Drink") -> Food & Drink | G52: =IFERROR(__xludf.DUMMYFUNCTION("""COMPUTED_VALUE"""),"Snacks") -> Snacks | H52: =IFERROR(__xludf.DUMMYFUNCTION("""COMPUTED_VALUE"""),58.0) -> 58 | I52: =IFERROR(__xludf.DUMMYFUNCTION("""COMPUTED_VALUE"""),"TTB So Smart") -> TTB So Smart | J52: =IFERROR(__xludf.DUMMYFUNCTION("""COMPUTED_VALUE"""),"Credit Payment") -> Credit Payment | K52: =IFERROR(__xludf.DUMMYFUNCTION("""COMPUTED_VALUE"""),"Lotus") -> Lotus | L52: =IFERROR(__xludf.DUMMYFUNCTION("""COMPUTED_VALUE"""),"ขนมปัง") -> ขนมปัง
E53: =IFERROR(__xludf.DUMMYFUNCTION("""COMPUTED_VALUE"""),45946.0) -> 45946 | F53: =IFERROR(__xludf.DUMMYFUNCTION("""COMPUTED_VALUE"""),"Food & Drink") -> Food & Drink | G53: =IFERROR(__xludf.DUMMYFUNCTION("""COMPUTED_VALUE"""),"Groceries") -> Groceries | H53: =IFERROR(__xludf.DUMMYFUNCTION("""COMPUTED_VALUE"""),206.0) -> 206 | I53: =IFERROR(__xludf.DUMMYFUNCTION("""COMPUTED_VALUE"""),"TTB So Smart") -> TTB So Smart | J53: =IFERROR(__xludf.DUMMYFUNCTION("""COMPUTED_VALUE"""),"Credit Payment") -> Credit Payment | K53: =IFERROR(__xludf.DUMMYFUNCTION("""COMPUTED_VALUE"""),"Lotus") -> Lotus | L53: =IFERROR(__xludf.DUMMYFUNCTION("""COMPUTED_VALUE"""),"ผัก") -> ผัก
E54: =IFERROR(__xludf.DUMMYFUNCTION("""COMPUTED_VALUE"""),45945.0) -> 45945 | F54: =IFERROR(__xludf.DUMMYFUNCTION("""COMPUTED_VALUE"""),"Food & Drink") -> Food & Drink | G54: =IFERROR(__xludf.DUMMYFUNCTION("""COMPUTED_VALUE"""),"Main meals") -> Main meals | H54: =IFERROR(__xludf.DUMMYFUNCTION("""COMPUTED_VALUE"""),98.0) -> 98 | I54: =IFERROR(__xludf.DUMMYFUNCTION("""COMPUTED_VALUE"""),"UOB One") -> UOB One | J54: =IFERROR(__xludf.DUMMYFUNCTION("""COMPUTED_VALUE"""),"Credit Spending") -> Credit Spending | K54: =IFERROR(__xludf.DUMMYFUNCTION("""COMPUTED_VALUE"""),"KFC") -> KFC
E55: =IFERROR(__xludf.DUMMYFUNCTION("""COMPUTED_VALUE"""),45944.0) -> 45944 | F55: =IFERROR(__xludf.DUMMYFUNCTION("""COMPUTED_VALUE"""),"Food & Drink") -> Food & Drink | G55: =IFERROR(__xludf.DUMMYFUNCTION("""COMPUTED_VALUE"""),"Main meals") -> Main meals | H55: =IFERROR(__xludf.DUMMYFUNCTION("""COMPUTED_VALUE"""),50.0) -> 50 | I55: =IFERROR(__xludf.DUMMYFUNCTION("""COMPUTED_VALUE"""),"Mobile Banking") -> Mobile Banking | K55: =IFERROR(__xludf.DUMMYFUNCTION("""COMPUTED_VALUE"""),"Noodle") -> Noodle
E56: =IFERROR(__xludf.DUMMYFUNCTION("""COMPUTED_VALUE"""),45944.0) -> 45944 | F56: =IFERROR(__xludf.DUMMYFUNCTION("""COMPUTED_VALUE"""),"Transportation") -> Transportation | G56: =IFERROR(__xludf.DUMMYFUNCTION("""COMPUTED_VALUE"""),"Fee") -> Fee | H56: =IFERROR(__xludf.DUMMYFUNCTION("""COMPUTED_VALUE"""),30.0) -> 30 | I56: =IFERROR(__xludf.DUMMYFUNCTION("""COMPUTED_VALUE"""),"Mobile Banking") -> Mobile Banking | L56: =IFERROR(__xludf.DUMMYFUNCTION("""COMPUTED_VALUE"""),"mflow") -> mflow
E57: =IFERROR(__xludf.DUMMYFUNCTION("""COMPUTED_VALUE"""),45944.0) -> 45944 | F57: =IFERROR(__xludf.DUMMYFUNCTION("""COMPUTED_VALUE"""),"Food & Drink") -> Food & Drink | G57: =IFERROR(__xludf.DUMMYFUNCTION("""COMPUTED_VALUE"""),"Drinks") -> Drinks | H57: =IFERROR(__xludf.DUMMYFUNCTION("""COMPUTED_VALUE"""),28.0) -> 28 | I57: =IFERROR(__xludf.DUMMYFUNCTION("""COMPUTED_VALUE"""),"Mobile Banking") -> Mobile Banking | K57: =IFERROR(__xludf.DUMMYFUNCTION("""COMPUTED_VALUE"""),"7-Eleven") -> 7-Eleven | L57: =IFERROR(__xludf.DUMMYFUNCTION("""COMPUTED_VALUE"""),"pepsi") -> pepsi
E58: =IFERROR(__xludf.DUMMYFUNCTION("""COMPUTED_VALUE"""),45943.0) -> 45943 | F58: =IFERROR(__xludf.DUMMYFUNCTION("""COMPUTED_VALUE"""),"Health") -> Health | G58: =IFERROR(__xludf.DUMMYFUNCTION("""COMPUTED_VALUE"""),"Exercise Equipment") -> Exercise Equipment | H58: =IFERROR(__xludf.DUMMYFUNCTION("""COMPUTED_VALUE"""),200.0) -> 200 | I58: =IFERROR(__xludf.DUMMYFUNCTION("""COMPUTED_VALUE"""),"UOB One") -> UOB One | J58: =IFERROR(__xludf.DUMMYFUNCTION("""COMPUTED_VALUE"""),"Credit Spending") -> Credit Spending | K58: =IFERROR(__xludf.DUMMYFUNCTION("""COMPUTED_VALUE"""),"Decathlon") -> Decathlon | L58: =IFERROR(__xludf.DUMMYFUNCTION("""COMPUTED_VALUE"""),"Resistance Band") -> Resistance Band
E59: =IFERROR(__xludf.DUMMYFUNCTION("""COMPUTED_VALUE"""),45943.0) -> 45943 | F59: =IFERROR(__xludf.DUMMYFUNCTION("""COMPUTED_VALUE"""),"Transportation") -> Transportation | G59: =IFERROR(__xludf.DUMMYFUNCTION("""COMPUTED_VALUE"""),"Fuel") -> Fuel | H59: =IFERROR(__xludf.DUMMYFUNCTION("""COMPUTED_VALUE"""),750.0) -> 750 | I59: =IFERROR(__xludf.DUMMYFUNCTION("""COMPUTED_VALUE"""),"TTB So Smart") -> TTB So Smart | J59: =IFERROR(__xludf.DUMMYFUNCTION("""COMPUTED_VALUE"""),"Credit Payment") -> Credit Payment | K59: =IFERROR(__xludf.DUMMYFUNCTION("""COMPUTED_VALUE"""),"Caltex") -> Caltex
E60: =IFERROR(__xludf.DUMMYFUNCTION("""COMPUTED_VALUE"""),45943.0) -> 45943 | F60: =IFERROR(__xludf.DUMMYFUNCTION("""COMPUTED_VALUE"""),"Food & Drink") -> Food & Drink | G60: =IFERROR(__xludf.DUMMYFUNCTION("""COMPUTED_VALUE"""),"Main meals") -> Main meals | H60: =IFERROR(__xludf.DUMMYFUNCTION("""COMPUTED_VALUE"""),149.0) -> 149 | I60: =IFERROR(__xludf.DUMMYFUNCTION("""COMPUTED_VALUE"""),"UOB One") -> UOB One | J60: =IFERROR(__xludf.DUMMYFUNCTION("""COMPUTED_VALUE"""),"Credit Spending") -> Credit Spending | K60: =IFERROR(__xludf.DUMMYFUNCTION("""COMPUTED_VALUE"""),"Subway") -> Subway | L60: =IFERROR(__xludf.DUMMYFUNCTION("""COMPUTED_VALUE"""),"ข้าวหน้าเนื้อ") -> ข้าวหน้าเนื้อ
E61: =IFERROR(__xludf.DUMMYFUNCTION("""COMPUTED_VALUE"""),45943.0) -> 45943 | F61: =IFERROR(__xludf.DUMMYFUNCTION("""COMPUTED_VALUE"""),"Service") -> Service | G61: =IFERROR(__xludf.DUMMYFUNCTION("""COMPUTED_VALUE"""),"Subscription") -> Subscription | H61: =IFERROR(__xludf.DUMMYFUNCTION("""COMPUTED_VALUE"""),36.0) -> 36 | I61: =IFERROR(__xludf.DUMMYFUNCTION("""COMPUTED_VALUE"""),"UOB One") -> UOB One | J61: =IFERROR(__xludf.DUMMYFUNCTION("""COMPUTED_VALUE"""),"Credit Spending") -> Credit Spending | K61: =IFERROR(__xludf.DUMMYFUNCTION("""COMPUTED_VALUE"""),"YT Premium") -> YT Premium
E62: =IFERROR(__xludf.DUMMYFUNCTION("""COMPUTED_VALUE"""),45943.0) -> 45943 | F62: =IFERROR(__xludf.DUMMYFUNCTION("""COMPUTED_VALUE"""),"Food & Drink") -> Food & Drink | G62: =IFERROR(__xludf.DUMMYFUNCTION("""COMPUTED_VALUE"""),"Main meals") -> Main meals | H62: =IFERROR(__xludf.DUMMYFUNCTION("""COMPUTED_VALUE"""),60.0) -> 60 | I62: =IFERROR(__xludf.DUMMYFUNCTION("""COMPUTED_VALUE"""),"Mobile Banking") -> Mobile Banking | L62: =IFERROR(__xludf.DUMMYFUNCTION("""COMPUTED_VALUE"""),"กะเพรา") -> กะเพรา
E63: =IFERROR(__xludf.DUMMYFUNCTION("""COMPUTED_VALUE"""),45943.0) -> 45943 | F63: =IFERROR(__xludf.DUMMYFUNCTION("""COMPUTED_VALUE"""),"Residence") -> Residence | G63: =IFERROR(__xludf.DUMMYFUNCTION("""COMPUTED_VALUE"""),"Electricity Bill-A") -> Electricity Bill-A | H63: =IFERROR(__xludf.DUMMYFUNCTION("""COMPUTED_VALUE"""),2670.31) -> 2670.31 | I63: =IFERROR(__xludf.DUMMYFUNCTION("""COMPUTED_VALUE"""),"Mobile Banking") -> Mobile Banking
E64: =IFERROR(__xludf.DUMMYFUNCTION("""COMPUTED_VALUE"""),45942.0) -> 45942 | F64: =IFERROR(__xludf.DUMMYFUNCTION("""COMPUTED_VALUE"""),"Food & Drink") -> Food & Drink | G64: =IFERROR(__xludf.DUMMYFUNCTION("""COMPUTED_VALUE"""),"Snacks") -> Snacks | H64: =IFERROR(__xludf.DUMMYFUNCTION("""COMPUTED_VALUE"""),72.0) -> 72 | I64: =IFERROR(__xludf.DUMMYFUNCTION("""COMPUTED_VALUE"""),"Mobile Banking") -> Mobile Banking | L64: =IFERROR(__xludf.DUMMYFUNCTION("""COMPUTED_VALUE"""),"icream, น้ำเปล่า") -> icream, น้ำเปล่า
E65: =IFERROR(__xludf.DUMMYFUNCTION("""COMPUTED_VALUE"""),45942.0) -> 45942 | F65: =IFERROR(__xludf.DUMMYFUNCTION("""COMPUTED_VALUE"""),"Food & Drink") -> Food & Drink | G65: =IFERROR(__xludf.DUMMYFUNCTION("""COMPUTED_VALUE"""),"Snacks") -> Snacks | H65: =IFERROR(__xludf.DUMMYFUNCTION("""COMPUTED_VALUE"""),140.0) -> 140 | I65: =IFERROR(__xludf.DUMMYFUNCTION("""COMPUTED_VALUE"""),"Mobile Banking") -> Mobile Banking | K65: =IFERROR(__xludf.DUMMYFUNCTION("""COMPUTED_VALUE"""),"7-Eleven") -> 7-Eleven | L65: =IFERROR(__xludf.DUMMYFUNCTION("""COMPUTED_VALUE"""),"ขนมตอนไป outing") -> ขนมตอนไป outing
E66: =IFERROR(__xludf.DUMMYFUNCTION("""COMPUTED_VALUE"""),45941.0) -> 45941 | F66: =IFERROR(__xludf.DUMMYFUNCTION("""COMPUTED_VALUE"""),"Food & Drink") -> Food & Drink | G66: =IFERROR(__xludf.DUMMYFUNCTION("""COMPUTED_VALUE"""),"Drinks") -> Drinks | H66: =IFERROR(__xludf.DUMMYFUNCTION("""COMPUTED_VALUE"""),95.0) -> 95 | I66: =IFERROR(__xludf.DUMMYFUNCTION("""COMPUTED_VALUE"""),"UOB One") -> UOB One | J66: =IFERROR(__xludf.DUMMYFUNCTION("""COMPUTED_VALUE"""),"Credit Spending") -> Credit Spending | K66: =IFERROR(__xludf.DUMMYFUNCTION("""COMPUTED_VALUE"""),"Amazon") -> Amazon
E67: =IFERROR(__xludf.DUMMYFUNCTION("""COMPUTED_VALUE"""),45941.0) -> 45941 | F67: =IFERROR(__xludf.DUMMYFUNCTION("""COMPUTED_VALUE"""),"Items") -> Items | G67: =IFERROR(__xludf.DUMMYFUNCTION("""COMPUTED_VALUE"""),"Skincare") -> Skincare | H67: =IFERROR(__xludf.DUMMYFUNCTION("""COMPUTED_VALUE"""),69.0) -> 69 | I67: =IFERROR(__xludf.DUMMYFUNCTION("""COMPUTED_VALUE"""),"Mobile Banking") -> Mobile Banking | K67: =IFERROR(__xludf.DUMMYFUNCTION("""COMPUTED_VALUE"""),"7-Eleven") -> 7-Eleven | L67: =IFERROR(__xludf.DUMMYFUNCTION("""COMPUTED_VALUE"""),"moiturizer") -> moiturizer
E68: =IFERROR(__xludf.DUMMYFUNCTION("""COMPUTED_VALUE"""),45940.0) -> 45940 | F68: =IFERROR(__xludf.DUMMYFUNCTION("""COMPUTED_VALUE"""),"Transportation") -> Transportation | G68: =IFERROR(__xludf.DUMMYFUNCTION("""COMPUTED_VALUE"""),"Fuel") -> Fuel | H68: =IFERROR(__xludf.DUMMYFUNCTION("""COMPUTED_VALUE"""),750.0) -> 750 | I68: =IFERROR(__xludf.DUMMYFUNCTION("""COMPUTED_VALUE"""),"TTB So Smart") -> TTB So Smart | J68: =IFERROR(__xludf.DUMMYFUNCTION("""COMPUTED_VALUE"""),"Credit Payment") -> Credit Payment | K68: =IFERROR(__xludf.DUMMYFUNCTION("""COMPUTED_VALUE"""),"Caltex") -> Caltex
E69: =IFERROR(__xludf.DUMMYFUNCTION("""COMPUTED_VALUE"""),45940.0) -> 45940 | F69: =IFERROR(__xludf.DUMMYFUNCTION("""COMPUTED_VALUE"""),"Food & Drink") -> Food & Drink | G69: =IFERROR(__xludf.DUMMYFUNCTION("""COMPUTED_VALUE"""),"Main meals") -> Main meals | H69: =IFERROR(__xludf.DUMMYFUNCTION("""COMPUTED_VALUE"""),95.0) -> 95 | I69: =IFERROR(__xludf.DUMMYFUNCTION("""COMPUTED_VALUE"""),"Mobile Banking") -> Mobile Banking | L69: =IFERROR(__xludf.DUMMYFUNCTION("""COMPUTED_VALUE"""),"กะเพรา") -> กะเพรา
E70: =IFERROR(__xludf.DUMMYFUNCTION("""COMPUTED_VALUE"""),45939.0) -> 45939 | F70: =IFERROR(__xludf.DUMMYFUNCTION("""COMPUTED_VALUE"""),"Food & Drink") -> Food & Drink | G70: =IFERROR(__xludf.DUMMYFUNCTION("""COMPUTED_VALUE"""),"Groceries") -> Groceries | H70: =IFERROR(__xludf.DUMMYFUNCTION("""COMPUTED_VALUE"""),179.0) -> 179 | I70: =IFERROR(__xludf.DUMMYFUNCTION("""COMPUTED_VALUE"""),"Mobile Banking") -> Mobile Banking | L70: =IFERROR(__xludf.DUMMYFUNCTION("""COMPUTED_VALUE"""),"ผัก, กระดูกหมู, ข้าวโพด") -> ผัก, กระดูกหมู, ข้าวโพด
E71: =IFERROR(__xludf.DUMMYFUNCTION("""COMPUTED_VALUE"""),45939.0) -> 45939 | F71: =IFERROR(__xludf.DUMMYFUNCTION("""COMPUTED_VALUE"""),"Food & Drink") -> Food & Drink | G71: =IFERROR(__xludf.DUMMYFUNCTION("""COMPUTED_VALUE"""),"Main meals") -> Main meals | H71: =IFERROR(__xludf.DUMMYFUNCTION("""COMPUTED_VALUE"""),125.0) -> 125 | I71: =IFERROR(__xludf.DUMMYFUNCTION("""COMPUTED_VALUE"""),"Mobile Banking") -> Mobile Banking | L71: =IFERROR(__xludf.DUMMYFUNCTION("""COMPUTED_VALUE"""),"ไส้กรอก, หมูกรอบ") -> ไส้กรอก, หมูกรอบ
E72: =IFERROR(__xludf.DUMMYFUNCTION("""COMPUTED_VALUE"""),45938.0) -> 45938 | F72: =IFERROR(__xludf.DUMMYFUNCTION("""COMPUTED_VALUE"""),"Food & Drink") -> Food & Drink | G72: =IFERROR(__xludf.DUMMYFUNCTION("""COMPUTED_VALUE"""),"Snacks") -> Snacks | H72: =IFERROR(__xludf.DUMMYFUNCTION("""COMPUTED_VALUE"""),80.0) -> 80 | I72: =IFERROR(__xludf.DUMMYFUNCTION("""COMPUTED_VALUE"""),"Mobile Banking") -> Mobile Banking | L72: =IFERROR(__xludf.DUMMYFUNCTION("""COMPUTED_VALUE"""),"ขนมจีบซาลาเปา") -> ขนมจีบซาลาเปา
E73: =IFERROR(__xludf.DUMMYFUNCTION("""COMPUTED_VALUE"""),45938.0) -> 45938 | F73: =IFERROR(__xludf.DUMMYFUNCTION("""COMPUTED_VALUE"""),"Food & Drink") -> Food & Drink | G73: =IFERROR(__xludf.DUMMYFUNCTION("""COMPUTED_VALUE"""),"Drinks") -> Drinks | H73: =IFERROR(__xludf.DUMMYFUNCTION("""COMPUTED_VALUE"""),113.0) -> 113 | I73: =IFERROR(__xludf.DUMMYFUNCTION("""COMPUTED_VALUE"""),"Mobile Banking") -> Mobile Banking | K73: =IFERROR(__xludf.DUMMYFUNCTION("""COMPUTED_VALUE"""),"7-Eleven") -> 7-Eleven | L73: =IFERROR(__xludf.DUMMYFUNCTION("""COMPUTED_VALUE"""),"pepsi, นม") -> pepsi, นม
E74: =IFERROR(__xludf.DUMMYFUNCTION("""COMPUTED_VALUE"""),45938.0) -> 45938 | F74: =IFERROR(__xludf.DUMMYFUNCTION("""COMPUTED_VALUE"""),"Food & Drink") -> Food & Drink | G74: =IFERROR(__xludf.DUMMYFUNCTION("""COMPUTED_VALUE"""),"Main meals") -> Main meals | H74: =IFERROR(__xludf.DUMMYFUNCTION("""COMPUTED_VALUE"""),106.0) -> 106 | I74: =IFERROR(__xludf.DUMMYFUNCTION("""COMPUTED_VALUE"""),"Mobile Banking") -> Mobile Banking | K74: =IFERROR(__xludf.DUMMYFUNCTION("""COMPUTED_VALUE"""),"7-Eleven") -> 7-Eleven | L74: =IFERROR(__xludf.DUMMYFUNCTION("""COMPUTED_VALUE"""),"ไส้กรอก, สลัดอกไก่") -> ไส้กรอก, สลัดอกไก่
E75: =IFERROR(__xludf.DUMMYFUNCTION("""COMPUTED_VALUE"""),45937.0) -> 45937 | F75: =IFERROR(__xludf.DUMMYFUNCTION("""COMPUTED_VALUE"""),"Food & Drink") -> Food & Drink | G75: =IFERROR(__xludf.DUMMYFUNCTION("""COMPUTED_VALUE"""),"Drinks") -> Drinks | H75: =IFERROR(__xludf.DUMMYFUNCTION("""COMPUTED_VALUE"""),85.0) -> 85 | I75: =IFERROR(__xludf.DUMMYFUNCTION("""COMPUTED_VALUE"""),"UOB One") -> UOB One | J75: =IFERROR(__xludf.DUMMYFUNCTION("""COMPUTED_VALUE"""),"Credit Spending") -> Credit Spending | L75: =IFERROR(__xludf.DUMMYFUNCTION("""COMPUTED_VALUE"""),"ชานม Koi") -> ชานม Koi
E76: =IFERROR(__xludf.DUMMYFUNCTION("""COMPUTED_VALUE"""),45937.0) -> 45937 | F76: =IFERROR(__xludf.DUMMYFUNCTION("""COMPUTED_VALUE"""),"Food & Drink") -> Food & Drink | G76: =IFERROR(__xludf.DUMMYFUNCTION("""COMPUTED_VALUE"""),"Main meals") -> Main meals | H76: =IFERROR(__xludf.DUMMYFUNCTION("""COMPUTED_VALUE"""),219.0) -> 219 | I76: =IFERROR(__xludf.DUMMYFUNCTION("""COMPUTED_VALUE"""),"Mobile Banking") -> Mobile Banking | L76: =IFERROR(__xludf.DUMMYFUNCTION("""COMPUTED_VALUE"""),"Babigon") -> Babigon
E77: =IFERROR(__xludf.DUMMYFUNCTION("""COMPUTED_VALUE"""),45937.0) -> 45937 | F77: =IFERROR(__xludf.DUMMYFUNCTION("""COMPUTED_VALUE"""),"Items") -> Items | G77: =IFERROR(__xludf.DUMMYFUNCTION("""COMPUTED_VALUE"""),"Personal Items") -> Personal Items | H77: =IFERROR(__xludf.DUMMYFUNCTION("""COMPUTED_VALUE"""),250.0) -> 250 | I77: =IFERROR(__xludf.DUMMYFUNCTION("""COMPUTED_VALUE"""),"Mobile Banking") -> Mobile Banking | L77: =IFERROR(__xludf.DUMMYFUNCTION("""COMPUTED_VALUE"""),"น้ำหอม kamakkamen") -> น้ำหอม kamakkamen
E78: =IFERROR(__xludf.DUMMYFUNCTION("""COMPUTED_VALUE"""),45937.0) -> 45937 | F78: =IFERROR(__xludf.DUMMYFUNCTION("""COMPUTED_VALUE"""),"Health") -> Health | G78: =IFERROR(__xludf.DUMMYFUNCTION("""COMPUTED_VALUE"""),"Others") -> Others | H78: =IFERROR(__xludf.DUMMYFUNCTION("""COMPUTED_VALUE"""),40.0) -> 40 | I78: =IFERROR(__xludf.DUMMYFUNCTION("""COMPUTED_VALUE"""),"Mobile Banking") -> Mobile Banking | K78: =IFERROR(__xludf.DUMMYFUNCTION("""COMPUTED_VALUE"""),"7-Eleven") -> 7-Eleven | L78: =IFERROR(__xludf.DUMMYFUNCTION("""COMPUTED_VALUE"""),"ยาลดกรด") -> ยาลดกรด
E79: =IFERROR(__xludf.DUMMYFUNCTION("""COMPUTED_VALUE"""),45936.0) -> 45936 | F79: =IFERROR(__xludf.DUMMYFUNCTION("""COMPUTED_VALUE"""),"Food & Drink") -> Food & Drink | G79: =IFERROR(__xludf.DUMMYFUNCTION("""COMPUTED_VALUE"""),"Main meals") -> Main meals | H79: =IFERROR(__xludf.DUMMYFUNCTION("""COMPUTED_VALUE"""),169.0) -> 169 | I79: =IFERROR(__xludf.DUMMYFUNCTION("""COMPUTED_VALUE"""),"TTB So Smart") -> TTB So Smart | J79: =IFERROR(__xludf.DUMMYFUNCTION("""COMPUTED_VALUE"""),"Credit Payment") -> Credit Payment | K79: =IFERROR(__xludf.DUMMYFUNCTION("""COMPUTED_VALUE"""),"Noodle") -> Noodle
E80: =IFERROR(__xludf.DUMMYFUNCTION("""COMPUTED_VALUE"""),45936.0) -> 45936 | F80: =IFERROR(__xludf.DUMMYFUNCTION("""COMPUTED_VALUE"""),"Service") -> Service | G80: =IFERROR(__xludf.DUMMYFUNCTION("""COMPUTED_VALUE"""),"Subscription") -> Subscription | H80: =IFERROR(__xludf.DUMMYFUNCTION("""COMPUTED_VALUE"""),19.0) -> 19 | I80: =IFERROR(__xludf.DUMMYFUNCTION("""COMPUTED_VALUE"""),"UOB One") -> UOB One | J80: =IFERROR(__xludf.DUMMYFUNCTION("""COMPUTED_VALUE"""),"Credit Spending") -> Credit Spending | L80: =IFERROR(__xludf.DUMMYFUNCTION("""COMPUTED_VALUE"""),"Subscribe K.Earthh Evans") -> Subscribe K.Earthh Evans
E81: =IFERROR(__xludf.DUMMYFUNCTION("""COMPUTED_VALUE"""),45936.0) -> 45936 | F81: =IFERROR(__xludf.DUMMYFUNCTION("""COMPUTED_VALUE"""),"Food & Drink") -> Food & Drink | G81: =IFERROR(__xludf.DUMMYFUNCTION("""COMPUTED_VALUE"""),"Snacks") -> Snacks | H81: =IFERROR(__xludf.DUMMYFUNCTION("""COMPUTED_VALUE"""),40.0) -> 40 | I81: =IFERROR(__xludf.DUMMYFUNCTION("""COMPUTED_VALUE"""),"Mobile Banking") -> Mobile Banking | L81: =IFERROR(__xludf.DUMMYFUNCTION("""COMPUTED_VALUE"""),"ลูกชิ้น") -> ลูกชิ้น
E82: =IFERROR(__xludf.DUMMYFUNCTION("""COMPUTED_VALUE"""),45936.0) -> 45936 | F82: =IFERROR(__xludf.DUMMYFUNCTION("""COMPUTED_VALUE"""),"Food & Drink") -> Food & Drink | G82: =IFERROR(__xludf.DUMMYFUNCTION("""COMPUTED_VALUE"""),"Main meals") -> Main meals | H82: =IFERROR(__xludf.DUMMYFUNCTION("""COMPUTED_VALUE"""),50.0) -> 50 | I82: =IFERROR(__xludf.DUMMYFUNCTION("""COMPUTED_VALUE"""),"Mobile Banking") -> Mobile Banking | K82: =IFERROR(__xludf.DUMMYFUNCTION("""COMPUTED_VALUE"""),"Hainanese chicken rice") -> Hainanese chicken rice
E83: =IFERROR(__xludf.DUMMYFUNCTION("""COMPUTED_VALUE"""),45936.0) -> 45936 | F83: =IFERROR(__xludf.DUMMYFUNCTION("""COMPUTED_VALUE"""),"Food & Drink") -> Food & Drink | G83: =IFERROR(__xludf.DUMMYFUNCTION("""COMPUTED_VALUE"""),"Alcohol") -> Alcohol | H83: =IFERROR(__xludf.DUMMYFUNCTION("""COMPUTED_VALUE"""),62.0) -> 62 | I83: =IFERROR(__xludf.DUMMYFUNCTION("""COMPUTED_VALUE"""),"Mobile Banking") -> Mobile Banking | K83: =IFERROR(__xludf.DUMMYFUNCTION("""COMPUTED_VALUE"""),"7-Eleven") -> 7-Eleven
E84: =IFERROR(__xludf.DUMMYFUNCTION("""COMPUTED_VALUE"""),45935.0) -> 45935 | F84: =IFERROR(__xludf.DUMMYFUNCTION("""COMPUTED_VALUE"""),"Food & Drink") -> Food & Drink | G84: =IFERROR(__xludf.DUMMYFUNCTION("""COMPUTED_VALUE"""),"Groceries") -> Groceries | H84: =IFERROR(__xludf.DUMMYFUNCTION("""COMPUTED_VALUE"""),60.0) -> 60 | I84: =IFERROR(__xludf.DUMMYFUNCTION("""COMPUTED_VALUE"""),"Mobile Banking") -> Mobile Banking | L84: =IFERROR(__xludf.DUMMYFUNCTION("""COMPUTED_VALUE"""),"มะพร้าว") -> มะพร้าว
E85: =IFERROR(__xludf.DUMMYFUNCTION("""COMPUTED_VALUE"""),45935.0) -> 45935 | F85: =IFERROR(__xludf.DUMMYFUNCTION("""COMPUTED_VALUE"""),"Food & Drink") -> Food & Drink | G85: =IFERROR(__xludf.DUMMYFUNCTION("""COMPUTED_VALUE"""),"Main meals") -> Main meals | H85: =IFERROR(__xludf.DUMMYFUNCTION("""COMPUTED_VALUE"""),25.0) -> 25 | I85: =IFERROR(__xludf.DUMMYFUNCTION("""COMPUTED_VALUE"""),"Mobile Banking") -> Mobile Banking | L85: =IFERROR(__xludf.DUMMYFUNCTION("""COMPUTED_VALUE"""),"ข้าวผัด") -> ข้าวผัด
E86: =IFERROR(__xludf.DUMMYFUNCTION("""COMPUTED_VALUE"""),45935.0) -> 45935 | F86: =IFERROR(__xludf.DUMMYFUNCTION("""COMPUTED_VALUE"""),"Food & Drink") -> Food & Drink | G86: =IFERROR(__xludf.DUMMYFUNCTION("""COMPUTED_VALUE"""),"Main meals") -> Main meals | H86: =IFERROR(__xludf.DUMMYFUNCTION("""COMPUTED_VALUE"""),284.0) -> 284 | I86: =IFERROR(__xludf.DUMMYFUNCTION("""COMPUTED_VALUE"""),"Mobile Banking") -> Mobile Banking | L86: =IFERROR(__xludf.DUMMYFUNCTION("""COMPUTED_VALUE"""),"หมูกะทะ") -> หมูกะทะ
E87: =IFERROR(__xludf.DUMMYFUNCTION("""COMPUTED_VALUE"""),45934.0) -> 45934 | F87: =IFERROR(__xludf.DUMMYFUNCTION("""COMPUTED_VALUE"""),"Transportation") -> Transportation | G87: =IFERROR(__xludf.DUMMYFUNCTION("""COMPUTED_VALUE"""),"Fuel") -> Fuel | H87: =IFERROR(__xludf.DUMMYFUNCTION("""COMPUTED_VALUE"""),750.0) -> 750 | I87: =IFERROR(__xludf.DUMMYFUNCTION("""COMPUTED_VALUE"""),"TTB So Smart") -> TTB So Smart | J87: =IFERROR(__xludf.DUMMYFUNCTION("""COMPUTED_VALUE"""),"Credit Payment") -> Credit Payment | K87: =IFERROR(__xludf.DUMMYFUNCTION("""COMPUTED_VALUE"""),"Caltex") -> Caltex
E88: =IFERROR(__xludf.DUMMYFUNCTION("""COMPUTED_VALUE"""),45934.0) -> 45934 | F88: =IFERROR(__xludf.DUMMYFUNCTION("""COMPUTED_VALUE"""),"Food & Drink") -> Food & Drink | G88: =IFERROR(__xludf.DUMMYFUNCTION("""COMPUTED_VALUE"""),"Main meals") -> Main meals | H88: =IFERROR(__xludf.DUMMYFUNCTION("""COMPUTED_VALUE"""),169.0) -> 169 | I88: =IFERROR(__xludf.DUMMYFUNCTION("""COMPUTED_VALUE"""),"UOB One") -> UOB One | J88: =IFERROR(__xludf.DUMMYFUNCTION("""COMPUTED_VALUE"""),"Credit Spending") -> Credit Spending | L88: =IFERROR(__xludf.DUMMYFUNCTION("""COMPUTED_VALUE"""),"Taco Bell") -> Taco Bell
E89: =IFERROR(__xludf.DUMMYFUNCTION("""COMPUTED_VALUE"""),45933.0) -> 45933 | F89: =IFERROR(__xludf.DUMMYFUNCTION("""COMPUTED_VALUE"""),"Food & Drink") -> Food & Drink | G89: =IFERROR(__xludf.DUMMYFUNCTION("""COMPUTED_VALUE"""),"Drinks") -> Drinks | H89: =IFERROR(__xludf.DUMMYFUNCTION("""COMPUTED_VALUE"""),35.0) -> 35 | I89: =IFERROR(__xludf.DUMMYFUNCTION("""COMPUTED_VALUE"""),"Mobile Banking") -> Mobile Banking | L89: =IFERROR(__xludf.DUMMYFUNCTION("""COMPUTED_VALUE"""),"ชานม") -> ชานม
E90: =IFERROR(__xludf.DUMMYFUNCTION("""COMPUTED_VALUE"""),45933.0) -> 45933 | F90: =IFERROR(__xludf.DUMMYFUNCTION("""COMPUTED_VALUE"""),"Food & Drink") -> Food & Drink | G90: =IFERROR(__xludf.DUMMYFUNCTION("""COMPUTED_VALUE"""),"Groceries") -> Groceries | H90: =IFERROR(__xludf.DUMMYFUNCTION("""COMPUTED_VALUE"""),41.0) -> 41 | I90: =IFERROR(__xludf.DUMMYFUNCTION("""COMPUTED_VALUE"""),"TTB So Smart") -> TTB So Smart | J90: =IFERROR(__xludf.DUMMYFUNCTION("""COMPUTED_VALUE"""),"Credit Payment") -> Credit Payment | K90: =IFERROR(__xludf.DUMMYFUNCTION("""COMPUTED_VALUE"""),"Lotus") -> Lotus | L90: =IFERROR(__xludf.DUMMYFUNCTION("""COMPUTED_VALUE"""),"หมู") -> หมู
E91: =IFERROR(__xludf.DUMMYFUNCTION("""COMPUTED_VALUE"""),45933.0) -> 45933 | F91: =IFERROR(__xludf.DUMMYFUNCTION("""COMPUTED_VALUE"""),"Food & Drink") -> Food & Drink | G91: =IFERROR(__xludf.DUMMYFUNCTION("""COMPUTED_VALUE"""),"Snacks") -> Snacks | H91: =IFERROR(__xludf.DUMMYFUNCTION("""COMPUTED_VALUE"""),39.0) -> 39 | I91: =IFERROR(__xludf.DUMMYFUNCTION("""COMPUTED_VALUE"""),"TTB So Smart") -> TTB So Smart | J91: =IFERROR(__xludf.DUMMYFUNCTION("""COMPUTED_VALUE"""),"Credit Payment") -> Credit Payment | K91: =IFERROR(__xludf.DUMMYFUNCTION("""COMPUTED_VALUE"""),"Lotus") -> Lotus | L91: =IFERROR(__xludf.DUMMYFUNCTION("""COMPUTED_VALUE"""),"ขนมปัง") -> ขนมปัง
E92: =IFERROR(__xludf.DUMMYFUNCTION("""COMPUTED_VALUE"""),45933.0) -> 45933 | F92: =IFERROR(__xludf.DUMMYFUNCTION("""COMPUTED_VALUE"""),"Food & Drink") -> Food & Drink | G92: =IFERROR(__xludf.DUMMYFUNCTION("""COMPUTED_VALUE"""),"Snacks") -> Snacks | H92: =IFERROR(__xludf.DUMMYFUNCTION("""COMPUTED_VALUE"""),66.0) -> 66 | I92: =IFERROR(__xludf.DUMMYFUNCTION("""COMPUTED_VALUE"""),"Mobile Banking") -> Mobile Banking | K92: =IFERROR(__xludf.DUMMYFUNCTION("""COMPUTED_VALUE"""),"7-Eleven") -> 7-Eleven
E93: =IFERROR(__xludf.DUMMYFUNCTION("""COMPUTED_VALUE"""),45933.0) -> 45933 | F93: =IFERROR(__xludf.DUMMYFUNCTION("""COMPUTED_VALUE"""),"Transportation") -> Transportation | G93: =IFERROR(__xludf.DUMMYFUNCTION("""COMPUTED_VALUE"""),"Maintenance") -> Maintenance | H93: =IFERROR(__xludf.DUMMYFUNCTION("""COMPUTED_VALUE"""),1456.0) -> 1456 | I93: =IFERROR(__xludf.DUMMYFUNCTION("""COMPUTED_VALUE"""),"KTC Bangchak") -> KTC Bangchak | J93: =IFERROR(__xludf.DUMMYFUNCTION("""COMPUTED_VALUE"""),"Credit Payment") -> Credit Payment | K93: =IFERROR(__xludf.DUMMYFUNCTION("""COMPUTED_VALUE"""),"Auto 1") -> Auto 1 | L93: =IFERROR(__xludf.DUMMYFUNCTION("""COMPUTED_VALUE"""),"ผ่อนยางรถ 6/10") -> ผ่อนยางรถ 6/10
E94: =IFERROR(__xludf.DUMMYFUNCTION("""COMPUTED_VALUE"""),45932.0) -> 45932 | F94: =IFERROR(__xludf.DUMMYFUNCTION("""COMPUTED_VALUE"""),"Food & Drink") -> Food & Drink | G94: =IFERROR(__xludf.DUMMYFUNCTION("""COMPUTED_VALUE"""),"Main meals") -> Main meals | H94: =IFERROR(__xludf.DUMMYFUNCTION("""COMPUTED_VALUE"""),59.0) -> 59 | I94: =IFERROR(__xludf.DUMMYFUNCTION("""COMPUTED_VALUE"""),"KTC Bangchak") -> KTC Bangchak | J94: =IFERROR(__xludf.DUMMYFUNCTION("""COMPUTED_VALUE"""),"Credit Payment") -> Credit Payment | K94: =IFERROR(__xludf.DUMMYFUNCTION("""COMPUTED_VALUE"""),"KFC") -> KFC
E95: =IFERROR(__xludf.DUMMYFUNCTION("""COMPUTED_VALUE"""),45931.0) -> 45931 | F95: =IFERROR(__xludf.DUMMYFUNCTION("""COMPUTED_VALUE"""),"Food & Drink") -> Food & Drink | G95: =IFERROR(__xludf.DUMMYFUNCTION("""COMPUTED_VALUE"""),"Snacks") -> Snacks | H95: =IFERROR(__xludf.DUMMYFUNCTION("""COMPUTED_VALUE"""),118.0) -> 118 | I95: =IFERROR(__xludf.DUMMYFUNCTION("""COMPUTED_VALUE"""),"Mobile Banking") -> Mobile Banking | K95: =IFERROR(__xludf.DUMMYFUNCTION("""COMPUTED_VALUE"""),"7-Eleven") -> 7-Eleven
